Workbook
Name frmASM: 'Data Entry'!$D$9
Name frmCity: 'Data Entry'!$D$7
Name frmCommRate: Products!$G$3
Name frmDate: 'Data Entry'!$D$5
Name frmDesc: 'Data Entry'!$C$13:$C$24
Name frmInvNo: 'Data Entry'!$D$4
Name frmParty: 'Data Entry'!$D$6
Name frmQty: 'Data Entry'!$D$13:$D$24
Name frmR40: 'Data Entry'!$F$13:$F$24
Name frmSubParty: 'Data Entry'!$D$8
Name lstASM: 'OFFSET(Lists'!$C$2,'COUNTA(Lists'!$C$2:$C$500
Name lstCity: 'OFFSET(Lists'!$B$2,'COUNTA(Lists'!$B$2:$B$500
Name lstParty: 'OFFSET(Lists'!$A$2,'COUNTA(Lists'!$A$2:$A$500
Name lstProduct: 'OFFSET(Products'!$B$4,'COUNTA(Products'!$B$4:$B$500
Name lstSubParty: 'OFFSET(Lists'!$D$2,'COUNTA(Lists'!$D$2:$D$500

Sheet Data Entry
A1: ▦ | B1: WAQAR RICE MILLS | H1: SEPTEMBER 2026
B2: Shamshad Khan Shaheed Road, Kamoke · Sales Invoice Data Entry
B3: INVOICE DETAILS | F3: INVOICE SUMMARY
B4: Invoice No. | D4: 15
B5: Invoice Date | D5: 46267 | F5: Amount | I5: =$H$25 -> 1272188
B6: Party (Name) | D6: Pak Rice Traders | F6: Commission | I6: =$I$25 -> 4452.658
B7: City | D7: Dina | F7: Total Bags | I7: =$D$25 -> 200
B8: Sub Party
B9: ASM / Salesperson | D9: Farhan Khalid
B11: LINE ITEMS
B12: Sr | C12: Description (Product) | D12: Bags | E12: Pack Wt (KG) | F12: Rate 40Kg | G12: Rate / Pack | H12: AMOUNT | I12: Commission | J12: Weight (KG)
B13: 1 | C13: MASAR SABIT 25KG | D13: 30 | E13: =IFERROR(INDEX(Products!$E$4:$E$500,MATCH($C13,Products!$B$4:$B$500,0)),"") -> 25 | F13: 8000 | G13: =IF(OR($C13="",$F13=""),"",$F13/40*$E13) -> 5000 | H13: =IF(OR($G13="",$D13=""),"",ROUND($G13*$D13,0)) -> 150000 | I13: =IF($H13="","",$H13*IFERROR(INDEX(Products!$I$4:$I$500,MATCH($C13,Products!$B$4:$B$500,0)),frmCommRate)) -> 525 | J13: =IF($C13="","",$D13*$E13) -> 750
B14: 2 | C14: DAAL MASH CHARI 25KG | D14: 20 | E14: =IFERROR(INDEX(Products!$E$4:$E$500,MATCH($C14,Products!$B$4:$B$500,0)),"") -> 25 | F14: 16250 | G14: =IF(OR($C14="",$F14=""),"",$F14/40*$E14) -> 10156.25 | H14: =IF(OR($G14="",$D14=""),"",ROUND($G14*$D14,0)) -> 203125 | I14: =IF($H14="","",$H14*IFERROR(INDEX(Products!$I$4:$I$500,MATCH($C14,Products!$B$4:$B$500,0)),frmCommRate)) -> 710.9375 | J14: =IF($C14="","",$D14*$E14) -> 500
B15: 3 | C15: DAAL MOONG 25KG | D15: 30 | E15: =IFERROR(INDEX(Products!$E$4:$E$500,MATCH($C15,Products!$B$4:$B$500,0)),"") -> 25 | F15: 10250 | G15: =IF(OR($C15="",$F15=""),"",$F15/40*$E15) -> 6406.25 | H15: =IF(OR($G15="",$D15=""),"",ROUND($G15*$D15,0)) -> 192188 | I15: =IF($H15="","",$H15*IFERROR(INDEX(Products!$I$4:$I$500,MATCH($C15,Products!$B$4:$B$500,0)),frmCommRate)) -> 672.658 | J15: =IF($C15="","",$D15*$E15) -> 750
B16: 4 | C16: DALL MASOOR 25KG | D16: 20 | E16: =IFERROR(INDEX(Products!$E$4:$E$500,MATCH($C16,Products!$B$4:$B$500,0)),"") -> 25 | F16: 8400 | G16: =IF(OR($C16="",$F16=""),"",$F16/40*$E16) -> 5250 | H16: =IF(OR($G16="",$D16=""),"",ROUND($G16*$D16,0)) -> 105000 | I16: =IF($H16="","",$H16*IFERROR(INDEX(Products!$I$4:$I$500,MATCH($C16,Products!$B$4:$B$500,0)),frmCommRate)) -> 367.5 | J16: =IF($C16="","",$D16*$E16) -> 500
B17: 5 | C17: DAAL CHANNA SUPREME 25KG | D17: 100 | E17: =IFERROR(INDEX(Products!$E$4:$E$500,MATCH($C17,Products!$B$4:$B$500,0)),"") -> 25 | F17: 9950 | G17: =IF(OR($C17="",$F17=""),"",$F17/40*$E17) -> 6218.75 | H17: =IF(OR($G17="",$D17=""),"",ROUND($G17*$D17,0)) -> 621875 | I17: =IF($H17="","",$H17*IFERROR(INDEX(Products!$I$4:$I$500,MATCH($C17,Products!$B$4:$B$500,0)),frmCommRate)) -> 2176.5625 | J17: =IF($C17="","",$D17*$E17) -> 2500
B18: 6 | E18: =IFERROR(INDEX(Products!$E$4:$E$500,MATCH($C18,Products!$B$4:$B$500,0)),"") | G18: =IF(OR($C18="",$F18=""),"",$F18/40*$E18) | H18: =IF(OR($G18="",$D18=""),"",ROUND($G18*$D18,0)) | I18: =IF($H18="","",$H18*IFERROR(INDEX(Products!$I$4:$I$500,MATCH($C18,Products!$B$4:$B$500,0)),frmCommRate)) | J18: =IF($C18="","",$D18*$E18)
B19: 7 | E19: =IFERROR(INDEX(Products!$E$4:$E$500,MATCH($C19,Products!$B$4:$B$500,0)),"") | G19: =IF(OR($C19="",$F19=""),"",$F19/40*$E19) | H19: =IF(OR($G19="",$D19=""),"",ROUND($G19*$D19,0)) | I19: =IF($H19="","",$H19*IFERROR(INDEX(Products!$I$4:$I$500,MATCH($C19,Products!$B$4:$B$500,0)),frmCommRate)) | J19: =IF($C19="","",$D19*$E19)
B20: 8 | E20: =IFERROR(INDEX(Products!$E$4:$E$500,MATCH($C20,Products!$B$4:$B$500,0)),"") | G20: =IF(OR($C20="",$F20=""),"",$F20/40*$E20) | H20: =IF(OR($G20="",$D20=""),"",ROUND($G20*$D20,0)) | I20: =IF($H20="","",$H20*IFERROR(INDEX(Products!$I$4:$I$500,MATCH($C20,Products!$B$4:$B$500,0)),frmCommRate)) | J20: =IF($C20="","",$D20*$E20)
B21: 9 | E21: =IFERROR(INDEX(Products!$E$4:$E$500,MATCH($C21,Products!$B$4:$B$500,0)),"") | G21: =IF(OR($C21="",$F21=""),"",$F21/40*$E21) | H21: =IF(OR($G21="",$D21=""),"",ROUND($G21*$D21,0)) | I21: =IF($H21="","",$H21*IFERROR(INDEX(Products!$I$4:$I$500,MATCH($C21,Products!$B$4:$B$500,0)),frmCommRate)) | J21: =IF($C21="","",$D21*$E21)
B22: 10 | E22: =IFERROR(INDEX(Products!$E$4:$E$500,MATCH($C22,Products!$B$4:$B$500,0)),"") | G22: =IF(OR($C22="",$F22=""),"",$F22/40*$E22) | H22: =IF(OR($G22="",$D22=""),"",ROUND($G22*$D22,0)) | I22: =IF($H22="","",$H22*IFERROR(INDEX(Products!$I$4:$I$500,MATCH($C22,Products!$B$4:$B$500,0)),frmCommRate)) | J22: =IF($C22="","",$D22*$E22)
B23: 11 | E23: =IFERROR(INDEX(Products!$E$4:$E$500,MATCH($C23,Products!$B$4:$B$500,0)),"") | G23: =IF(OR($C23="",$F23=""),"",$F23/40*$E23) | H23: =IF(OR($G23="",$D23=""),"",ROUND($G23*$D23,0)) | I23: =IF($H23="","",$H23*IFERROR(INDEX(Products!$I$4:$I$500,MATCH($C23,Products!$B$4:$B$500,0)),frmCommRate)) | J23: =IF($C23="","",$D23*$E23)
B24: 12 | E24: =IFERROR(INDEX(Products!$E$4:$E$500,MATCH($C24,Products!$B$4:$B$500,0)),"") | G24: =IF(OR($C24="",$F24=""),"",$F24/40*$E24) | H24: =IF(OR($G24="",$D24=""),"",ROUND($G24*$D24,0)) | I24: =IF($H24="","",$H24*IFERROR(INDEX(Products!$I$4:$I$500,MATCH($C24,Products!$B$4:$B$500,0)),frmCommRate)) | J24: =IF($C24="","",$D24*$E24)
C25: INVOICE TOTAL | D25: =SUM($D$13:$D$24) -> 200 | H25: =SUM($H$13:$H$24) -> 1272188 | I25: =SUM($I$13:$I$24) -> 4452.658 | J25: =SUM($J$13:$J$24) -> 5000
B29: Fill the invoice above, then click SAVE / UPDATE. The invoice is written to the Database sheet - the grey columns there calculate themselves.

Sheet Dashboard
A2: ▦ | B2: WAQAR RICE MILLS | L2: SEPTEMBER 2026
B3: Shamshad Khan Shaheed Road, Kamoke · Sales Management System
B6: TOTAL REVENUE (PKR) | C6: ="▲ "&TEXT(IF($F$12=0,0,$B$7/$F$12),"0.0%")&" of target" -> ▲ 1.9% of target | E6: TOTAL COMMISSION | F6: ="▲ "&TEXT(IF($B$7=0,0,$E$7/$B$7),"0.00%")&" of sales" -> ▲ 0.35% of sales | H6: TOTAL WEIGHT (TONS) | I6: ="● "&TEXT(SUM(tblLines[Weight (KG)]),"#,##0")&" KG" -> ● 841,180 KG | K6: INVOICES | L6: ="● "&TEXT(SUM(tblLines[Qty (Packs)]),"#,##0")&" packs" -> ● 33,509 packs
B7: =SUM(tblLines[Amount]) -> 193457434 | E7: =SUM(tblLines[Commission]) -> 677101.02 | H7: =SUM(tblLines[Weight (KG)])/1000 -> 841.18 | K7: {=COUNTA(_xlfn.UNIQUE(_xlfn._xlws.FILTER(tblLines[Invoice '#],tblLines[Invoice '#]<>"")))} -> 35
B11: ANNUAL SALES TARGET
B12: Annual Sales Target (PKR) | F12: 10000000000 | H12: ← enter your annual target here
B13: Actual Sales to Date | F13: =$B$7 -> 193457434
B14: Achieved % | F14: =IF($F$12=0,"",F13/$F$12) -> 0.019345743 | K14: =F14 -> 0.019345743 | L14: =IFERROR(F14,0) -> 0.019345743
B15: Remaining to Target | F15: =IF($F$12=0,"",MAX(0,$F$12-F13)) -> 9806542566
B16: Implied Monthly Target | F16: =IF($F$12=0,"",$F$12/12) -> 8.3333333e+08
B20: SALES BY CATEGORY — RICE vs PULSES
B21: CATEGORY | E21: QTY (PACKS) | F21: WEIGHT (KG) | H21: AMOUNT (PKR) | I21: COMMISSION (PKR) | K21: % OF SALES | L21: SHARE
B22: Rice | E22: =SUMIF($M$48:$M$87,$B22,E$48:E$87) -> 31474 | F22: =SUMIF($M$48:$M$87,$B22,F$48:F$87) -> 790305 | H22: =SUMIF($M$48:$M$87,$B22,H$48:H$87) -> 180027193 | I22: =SUMIF($M$48:$M$87,$B22,I$48:I$87) -> 630095.18 | K22: =IF($B$7=0,"",H22/$B$7) -> 0.9305778 | L22: =IFERROR(K22,0) -> 0.9305778
B23: Pulses | E23: =SUMIF($M$48:$M$87,$B23,E$48:E$87) -> 2035 | F23: =SUMIF($M$48:$M$87,$B23,F$48:F$87) -> 50875 | H23: =SUMIF($M$48:$M$87,$B23,H$48:H$87) -> 13430241 | I23: =SUMIF($M$48:$M$87,$B23,I$48:I$87) -> 47005.844 | K23: =IF($B$7=0,"",H23/$B$7) -> 0.069422202 | L23: =IFERROR(K23,0) -> 0.069422202
B24: Other | E24: =SUMIF($M$48:$M$87,$B24,E$48:E$87) -> 0 | F24: =SUMIF($M$48:$M$87,$B24,F$48:F$87) -> 0 | H24: =SUMIF($M$48:$M$87,$B24,H$48:H$87) -> 0 | I24: =SUMIF($M$48:$M$87,$B24,I$48:I$87) -> 0 | K24: =IF($B$7=0,"",H24/$B$7) -> 0 | L24: =IFERROR(K24,0) -> 0
B25: TOTAL | E25: =SUM(E22:E24) -> 33509 | F25: =SUM(F22:F24) -> 841180 | H25: =SUM(H22:H24) -> 193457434 | I25: =SUM(I22:I24) -> 677101.02 | K25: =IF($B$7=0,"",H25/$B$7) -> 1
B29: SALES BY ASM / SALESPERSON
B30: ASM / SALESPERSON | E30: QTY (PACKS) | F30: WEIGHT (KG) | H30: AMOUNT (PKR) | I30: COMMISSION (PKR) | K30: % OF SALES | L30: SHARE
B31: {=_xlfn._xlws.SORT(_xlfn.UNIQUE(_xlfn._xlws.FILTER(TRIM(tblLines[ASM / Salesperson]),TRIM(tblLines[ASM / Salesperson])<>"")))} -> Arslan Ahmed Dar | E31: {=IF($B31="","",SUMPRODUCT((TRIM(tblLines[ASM / Salesperson])=$B31)*IF(ISNUMBER(tblLines[Qty (Packs)]),tblLines[Qty (Packs)],0)))} -> 3276 | F31: {=IF($B31="","",SUMPRODUCT((TRIM(tblLines[ASM / Salesperson])=$B31)*IF(ISNUMBER(tblLines[Weight (KG)]),tblLines[Weight (KG)],0)))} -> 82500 | H31: {=IF($B31="","",SUMPRODUCT((TRIM(tblLines[ASM / Salesperson])=$B31)*IF(ISNUMBER(tblLines[Amount]),tblLines[Amount],0)))} -> 24636878 | I31: {=IF($B31="","",SUMPRODUCT((TRIM(tblLines[ASM / Salesperson])=$B31)*IF(ISNUMBER(tblLines[Commission]),tblLines[Commission],0)))} -> 86229.073 | K31: =IF($B31="","",H31/$B$7) -> 0.12735038 | L31: =IFERROR(K31,0) -> 0.12735038
B32: Farhan Khalid | E32: {=IF($B32="","",SUMPRODUCT((TRIM(tblLines[ASM / Salesperson])=$B32)*IF(ISNUMBER(tblLines[Qty (Packs)]),tblLines[Qty (Packs)],0)))} -> 30233 | F32: {=IF($B32="","",SUMPRODUCT((TRIM(tblLines[ASM / Salesperson])=$B32)*IF(ISNUMBER(tblLines[Weight (KG)]),tblLines[Weight (KG)],0)))} -> 758680 | H32: {=IF($B32="","",SUMPRODUCT((TRIM(tblLines[ASM / Salesperson])=$B32)*IF(ISNUMBER(tblLines[Amount]),tblLines[Amount],0)))} -> 168820556 | I32: {=IF($B32="","",SUMPRODUCT((TRIM(tblLines[ASM / Salesperson])=$B32)*IF(ISNUMBER(tblLines[Commission]),tblLines[Commission],0)))} -> 590871.95 | K32: =IF($B32="","",H32/$B$7) -> 0.87264962 | L32: =IFERROR(K32,0) -> 0.87264962
E33: {=IF($B33="","",SUMPRODUCT((TRIM(tblLines[ASM / Salesperson])=$B33)*IF(ISNUMBER(tblLines[Qty (Packs)]),tblLines[Qty (Packs)],0)))} | F33: {=IF($B33="","",SUMPRODUCT((TRIM(tblLines[ASM / Salesperson])=$B33)*IF(ISNUMBER(tblLines[Weight (KG)]),tblLines[Weight (KG)],0)))} | H33: {=IF($B33="","",SUMPRODUCT((TRIM(tblLines[ASM / Salesperson])=$B33)*IF(ISNUMBER(tblLines[Amount]),tblLines[Amount],0)))} | I33: {=IF($B33="","",SUMPRODUCT((TRIM(tblLines[ASM / Salesperson])=$B33)*IF(ISNUMBER(tblLines[Commission]),tblLines[Commission],0)))} | K33: =IF($B33="","",H33/$B$7) | L33: =IFERROR(K33,0)
E34: {=IF($B34="","",SUMPRODUCT((TRIM(tblLines[ASM / Salesperson])=$B34)*IF(ISNUMBER(tblLines[Qty (Packs)]),tblLines[Qty (Packs)],0)))} | F34: {=IF($B34="","",SUMPRODUCT((TRIM(tblLines[ASM / Salesperson])=$B34)*IF(ISNUMBER(tblLines[Weight (KG)]),tblLines[Weight (KG)],0)))} | H34: {=IF($B34="","",SUMPRODUCT((TRIM(tblLines[ASM / Salesperson])=$B34)*IF(ISNUMBER(tblLines[Amount]),tblLines[Amount],0)))} | I34: {=IF($B34="","",SUMPRODUCT((TRIM(tblLines[ASM / Salesperson])=$B34)*IF(ISNUMBER(tblLines[Commission]),tblLines[Commission],0)))} | K34: =IF($B34="","",H34/$B$7) | L34: =IFERROR(K34,0)
E35: {=IF($B35="","",SUMPRODUCT((TRIM(tblLines[ASM / Salesperson])=$B35)*IF(ISNUMBER(tblLines[Qty (Packs)]),tblLines[Qty (Packs)],0)))} | F35: {=IF($B35="","",SUMPRODUCT((TRIM(tblLines[ASM / Salesperson])=$B35)*IF(ISNUMBER(tblLines[Weight (KG)]),tblLines[Weight (KG)],0)))} | H35: {=IF($B35="","",SUMPRODUCT((TRIM(tblLines[ASM / Salesperson])=$B35)*IF(ISNUMBER(tblLines[Amount]),tblLines[Amount],0)))} | I35: {=IF($B35="","",SUMPRODUCT((TRIM(tblLines[ASM / Salesperson])=$B35)*IF(ISNUMBER(tblLines[Commission]),tblLines[Commission],0)))} | K35: =IF($B35="","",H35/$B$7) | L35: =IFERROR(K35,0)
E36: {=IF($B36="","",SUMPRODUCT((TRIM(tblLines[ASM / Salesperson])=$B36)*IF(ISNUMBER(tblLines[Qty (Packs)]),tblLines[Qty (Packs)],0)))} | F36: {=IF($B36="","",SUMPRODUCT((TRIM(tblLines[ASM / Salesperson])=$B36)*IF(ISNUMBER(tblLines[Weight (KG)]),tblLines[Weight (KG)],0)))} | H36: {=IF($B36="","",SUMPRODUCT((TRIM(tblLines[ASM / Salesperson])=$B36)*IF(ISNUMBER(tblLines[Amount]),tblLines[Amount],0)))} | I36: {=IF($B36="","",SUMPRODUCT((TRIM(tblLines[ASM / Salesperson])=$B36)*IF(ISNUMBER(tblLines[Commission]),tblLines[Commission],0)))} | K36: =IF($B36="","",H36/$B$7) | L36: =IFERROR(K36,0)
E37: {=IF($B37="","",SUMPRODUCT((TRIM(tblLines[ASM / Salesperson])=$B37)*IF(ISNUMBER(tblLines[Qty (Packs)]),tblLines[Qty (Packs)],0)))} | F37: {=IF($B37="","",SUMPRODUCT((TRIM(tblLines[ASM / Salesperson])=$B37)*IF(ISNUMBER(tblLines[Weight (KG)]),tblLines[Weight (KG)],0)))} | H37: {=IF($B37="","",SUMPRODUCT((TRIM(tblLines[ASM / Salesperson])=$B37)*IF(ISNUMBER(tblLines[Amount]),tblLines[Amount],0)))} | I37: {=IF($B37="","",SUMPRODUCT((TRIM(tblLines[ASM / Salesperson])=$B37)*IF(ISNUMBER(tblLines[Commission]),tblLines[Commission],0)))} | K37: =IF($B37="","",H37/$B$7) | L37: =IFERROR(K37,0)
E38: {=IF($B38="","",SUMPRODUCT((TRIM(tblLines[ASM / Salesperson])=$B38)*IF(ISNUMBER(tblLines[Qty (Packs)]),tblLines[Qty (Packs)],0)))} | F38: {=IF($B38="","",SUMPRODUCT((TRIM(tblLines[ASM / Salesperson])=$B38)*IF(ISNUMBER(tblLines[Weight (KG)]),tblLines[Weight (KG)],0)))} | H38: {=IF($B38="","",SUMPRODUCT((TRIM(tblLines[ASM / Salesperson])=$B38)*IF(ISNUMBER(tblLines[Amount]),tblLines[Amount],0)))} | I38: {=IF($B38="","",SUMPRODUCT((TRIM(tblLines[ASM / Salesperson])=$B38)*IF(ISNUMBER(tblLines[Commission]),tblLines[Commission],0)))} | K38: =IF($B38="","",H38/$B$7) | L38: =IFERROR(K38,0)
E39: {=IF($B39="","",SUMPRODUCT((TRIM(tblLines[ASM / Salesperson])=$B39)*IF(ISNUMBER(tblLines[Qty (Packs)]),tblLines[Qty (Packs)],0)))} | F39: {=IF($B39="","",SUMPRODUCT((TRIM(tblLines[ASM / Salesperson])=$B39)*IF(ISNUMBER(tblLines[Weight (KG)]),tblLines[Weight (KG)],0)))} | H39: {=IF($B39="","",SUMPRODUCT((TRIM(tblLines[ASM / Salesperson])=$B39)*IF(ISNUMBER(tblLines[Amount]),tblLines[Amount],0)))} | I39: {=IF($B39="","",SUMPRODUCT((TRIM(tblLines[ASM / Salesperson])=$B39)*IF(ISNUMBER(tblLines[Commission]),tblLines[Commission],0)))} | K39: =IF($B39="","",H39/$B$7) | L39: =IFERROR(K39,0)
E40: {=IF($B40="","",SUMPRODUCT((TRIM(tblLines[ASM / Salesperson])=$B40)*IF(ISNUMBER(tblLines[Qty (Packs)]),tblLines[Qty (Packs)],0)))} | F40: {=IF($B40="","",SUMPRODUCT((TRIM(tblLines[ASM / Salesperson])=$B40)*IF(ISNUMBER(tblLines[Weight (KG)]),tblLines[Weight (KG)],0)))} | H40: {=IF($B40="","",SUMPRODUCT((TRIM(tblLines[ASM / Salesperson])=$B40)*IF(ISNUMBER(tblLines[Amount]),tblLines[Amount],0)))} | I40: {=IF($B40="","",SUMPRODUCT((TRIM(tblLines[ASM / Salesperson])=$B40)*IF(ISNUMBER(tblLines[Commission]),tblLines[Commission],0)))} | K40: =IF($B40="","",H40/$B$7) | L40: =IFERROR(K40,0)
E41: {=IF($B41="","",SUMPRODUCT((TRIM(tblLines[ASM / Salesperson])=$B41)*IF(ISNUMBER(tblLines[Qty (Packs)]),tblLines[Qty (Packs)],0)))} | F41: {=IF($B41="","",SUMPRODUCT((TRIM(tblLines[ASM / Salesperson])=$B41)*IF(ISNUMBER(tblLines[Weight (KG)]),tblLines[Weight (KG)],0)))} | H41: {=IF($B41="","",SUMPRODUCT((TRIM(tblLines[ASM / Salesperson])=$B41)*IF(ISNUMBER(tblLines[Amount]),tblLines[Amount],0)))} | I41: {=IF($B41="","",SUMPRODUCT((TRIM(tblLines[ASM / Salesperson])=$B41)*IF(ISNUMBER(tblLines[Commission]),tblLines[Commission],0)))} | K41: =IF($B41="","",H41/$B$7) | L41: =IFERROR(K41,0)
E42: {=IF($B42="","",SUMPRODUCT((TRIM(tblLines[ASM / Salesperson])=$B42)*IF(ISNUMBER(tblLines[Qty (Packs)]),tblLines[Qty (Packs)],0)))} | F42: {=IF($B42="","",SUMPRODUCT((TRIM(tblLines[ASM / Salesperson])=$B42)*IF(ISNUMBER(tblLines[Weight (KG)]),tblLines[Weight (KG)],0)))} | H42: {=IF($B42="","",SUMPRODUCT((TRIM(tblLines[ASM / Salesperson])=$B42)*IF(ISNUMBER(tblLines[Amount]),tblLines[Amount],0)))} | I42: {=IF($B42="","",SUMPRODUCT((TRIM(tblLines[ASM / Salesperson])=$B42)*IF(ISNUMBER(tblLines[Commission]),tblLines[Commission],0)))} | K42: =IF($B42="","",H42/$B$7) | L42: =IFERROR(K42,0)
B46: SALES BY PRODUCT
B47: PRODUCT | E47: QTY (PACKS) | F47: WEIGHT (KG) | H47: AMOUNT (PKR) | I47: COMMISSION (PKR) | K47: % OF SALES | L47: SHARE | M47: CATEGORY
B48: {=_xlfn._xlws.SORT(_xlfn.UNIQUE(_xlfn._xlws.FILTER(TRIM(tblLines[Description (Product)]),TRIM(tblLines[Description (Product)])<>"")))} -> DAAL CHANNA ECONOMY 25KG | E48: {=IF($B48="","",SUMPRODUCT((TRIM(tblLines[Description (Product)])=$B48)*IF(ISNUMBER(tblLines[Qty (Packs)]),tblLines[Qty (Packs)],0)))} -> 70 | F48: {=IF($B48="","",SUMPRODUCT((TRIM(tblLines[Description (Product)])=$B48)*IF(ISNUMBER(tblLines[Weight (KG)]),tblLines[Weight (KG)],0)))} -> 1750 | H48: {=IF($B48="","",SUMPRODUCT((TRIM(tblLines[Description (Product)])=$B48)*IF(ISNUMBER(tblLines[Amount]),tblLines[Amount],0)))} -> 365313 | I48: {=IF($B48="","",SUMPRODUCT((TRIM(tblLines[Description (Product)])=$B48)*IF(ISNUMBER(tblLines[Commission]),tblLines[Commission],0)))} -> 1278.5955 | K48: =IF($B48="","",H48/$B$7) -> 0.0018883379 | L48: =IFERROR(K48,0) -> 0.0018883379 | M48: =IF($B48="","",IFERROR(INDEX(Products!$H$4:$H$500,MATCH($B48,Products!$B$4:$B$500,0)),"Unmapped")) -> Pulses
B49: DAAL CHANNA REGULAR 25KG | E49: {=IF($B49="","",SUMPRODUCT((TRIM(tblLines[Description (Product)])=$B49)*IF(ISNUMBER(tblLines[Qty (Packs)]),tblLines[Qty (Packs)],0)))} -> 80 | F49: {=IF($B49="","",SUMPRODUCT((TRIM(tblLines[Description (Product)])=$B49)*IF(ISNUMBER(tblLines[Weight (KG)]),tblLines[Weight (KG)],0)))} -> 2000 | H49: {=IF($B49="","",SUMPRODUCT((TRIM(tblLines[Description (Product)])=$B49)*IF(ISNUMBER(tblLines[Amount]),tblLines[Amount],0)))} -> 452513 | I49: {=IF($B49="","",SUMPRODUCT((TRIM(tblLines[Description (Product)])=$B49)*IF(ISNUMBER(tblLines[Commission]),tblLines[Commission],0)))} -> 1583.7955 | K49: =IF($B49="","",H49/$B$7) -> 0.002339083 | L49: =IFERROR(K49,0) -> 0.002339083 | M49: =IF($B49="","",IFERROR(INDEX(Products!$H$4:$H$500,MATCH($B49,Products!$B$4:$B$500,0)),"Unmapped")) -> Pulses
B50: DAAL CHANNA SUPREME 25KG | E50: {=IF($B50="","",SUMPRODUCT((TRIM(tblLines[Description (Product)])=$B50)*IF(ISNUMBER(tblLines[Qty (Packs)]),tblLines[Qty (Packs)],0)))} -> 120 | F50: {=IF($B50="","",SUMPRODUCT((TRIM(tblLines[Description (Product)])=$B50)*IF(ISNUMBER(tblLines[Weight (KG)]),tblLines[Weight (KG)],0)))} -> 3000 | H50: {=IF($B50="","",SUMPRODUCT((TRIM(tblLines[Description (Product)])=$B50)*IF(ISNUMBER(tblLines[Amount]),tblLines[Amount],0)))} -> 747500 | I50: {=IF($B50="","",SUMPRODUCT((TRIM(tblLines[Description (Product)])=$B50)*IF(ISNUMBER(tblLines[Commission]),tblLines[Commission],0)))} -> 2616.25 | K50: =IF($B50="","",H50/$B$7) -> 0.0038638991 | L50: =IFERROR(K50,0) -> 0.0038638991 | M50: =IF($B50="","",IFERROR(INDEX(Products!$H$4:$H$500,MATCH($B50,Products!$B$4:$B$500,0)),"Unmapped")) -> Pulses
B51: DAAL MASH CHARI 25KG | E51: {=IF($B51="","",SUMPRODUCT((TRIM(tblLines[Description (Product)])=$B51)*IF(ISNUMBER(tblLines[Qty (Packs)]),tblLines[Qty (Packs)],0)))} -> 115 | F51: {=IF($B51="","",SUMPRODUCT((TRIM(tblLines[Description (Product)])=$B51)*IF(ISNUMBER(tblLines[Weight (KG)]),tblLines[Weight (KG)],0)))} -> 2875 | H51: {=IF($B51="","",SUMPRODUCT((TRIM(tblLines[Description (Product)])=$B51)*IF(ISNUMBER(tblLines[Amount]),tblLines[Amount],0)))} -> 1169244 | I51: {=IF($B51="","",SUMPRODUCT((TRIM(tblLines[Description (Product)])=$B51)*IF(ISNUMBER(tblLines[Commission]),tblLines[Commission],0)))} -> 4092.354 | K51: =IF($B51="","",H51/$B$7) -> 0.0060439342 | L51: =IFERROR(K51,0) -> 0.0060439342 | M51: =IF($B51="","",IFERROR(INDEX(Products!$H$4:$H$500,MATCH($B51,Products!$B$4:$B$500,0)),"Unmapped")) -> Pulses
B52: DAAL MOONG 25KG | E52: {=IF($B52="","",SUMPRODUCT((TRIM(tblLines[Description (Product)])=$B52)*IF(ISNUMBER(tblLines[Qty (Packs)]),tblLines[Qty (Packs)],0)))} -> 85 | F52: {=IF($B52="","",SUMPRODUCT((TRIM(tblLines[Description (Product)])=$B52)*IF(ISNUMBER(tblLines[Weight (KG)]),tblLines[Weight (KG)],0)))} -> 2125 | H52: {=IF($B52="","",SUMPRODUCT((TRIM(tblLines[Description (Product)])=$B52)*IF(ISNUMBER(tblLines[Amount]),tblLines[Amount],0)))} -> 545488 | I52: {=IF($B52="","",SUMPRODUCT((TRIM(tblLines[Description (Product)])=$B52)*IF(ISNUMBER(tblLines[Commission]),tblLines[Commission],0)))} -> 1909.208 | K52: =IF($B52="","",H52/$B$7) -> 0.0028196797 | L52: =IFERROR(K52,0) -> 0.0028196797 | M52: =IF($B52="","",IFERROR(INDEX(Products!$H$4:$H$500,MATCH($B52,Products!$B$4:$B$500,0)),"Unmapped")) -> Pulses
B53: DALL MASOOR 25KG | E53: {=IF($B53="","",SUMPRODUCT((TRIM(tblLines[Description (Product)])=$B53)*IF(ISNUMBER(tblLines[Qty (Packs)]),tblLines[Qty (Packs)],0)))} -> 115 | F53: {=IF($B53="","",SUMPRODUCT((TRIM(tblLines[Description (Product)])=$B53)*IF(ISNUMBER(tblLines[Weight (KG)]),tblLines[Weight (KG)],0)))} -> 2875 | H53: {=IF($B53="","",SUMPRODUCT((TRIM(tblLines[Description (Product)])=$B53)*IF(ISNUMBER(tblLines[Amount]),tblLines[Amount],0)))} -> 608281 | I53: {=IF($B53="","",SUMPRODUCT((TRIM(tblLines[Description (Product)])=$B53)*IF(ISNUMBER(tblLines[Commission]),tblLines[Commission],0)))} -> 2128.9835 | K53: =IF($B53="","",H53/$B$7) -> 0.0031442627 | L53: =IFERROR(K53,0) -> 0.0031442627 | M53: =IF($B53="","",IFERROR(INDEX(Products!$H$4:$H$500,MATCH($B53,Products!$B$4:$B$500,0)),"Unmapped")) -> Pulses
B54: HAZARA B-2, 25KG | E54: {=IF($B54="","",SUMPRODUCT((TRIM(tblLines[Description (Product)])=$B54)*IF(ISNUMBER(tblLines[Qty (Packs)]),tblLines[Qty (Packs)],0)))} -> 660 | F54: {=IF($B54="","",SUMPRODUCT((TRIM(tblLines[Description (Product)])=$B54)*IF(ISNUMBER(tblLines[Weight (KG)]),tblLines[Weight (KG)],0)))} -> 16500 | H54: {=IF($B54="","",SUMPRODUCT((TRIM(tblLines[Description (Product)])=$B54)*IF(ISNUMBER(tblLines[Amount]),tblLines[Amount],0)))} -> 1870626 | I54: {=IF($B54="","",SUMPRODUCT((TRIM(tblLines[Description (Product)])=$B54)*IF(ISNUMBER(tblLines[Commission]),tblLines[Commission],0)))} -> 6547.191 | K54: =IF($B54="","",H54/$B$7) -> 0.0096694449 | L54: =IFERROR(K54,0) -> 0.0096694449 | M54: =IF($B54="","",IFERROR(INDEX(Products!$H$4:$H$500,MATCH($B54,Products!$B$4:$B$500,0)),"Unmapped")) -> Rice
B55: KALAA CHANNA JAMBO 25KG | E55: {=IF($B55="","",SUMPRODUCT((TRIM(tblLines[Description (Product)])=$B55)*IF(ISNUMBER(tblLines[Qty (Packs)]),tblLines[Qty (Packs)],0)))} -> 45 | F55: {=IF($B55="","",SUMPRODUCT((TRIM(tblLines[Description (Product)])=$B55)*IF(ISNUMBER(tblLines[Weight (KG)]),tblLines[Weight (KG)],0)))} -> 1125 | H55: {=IF($B55="","",SUMPRODUCT((TRIM(tblLines[Description (Product)])=$B55)*IF(ISNUMBER(tblLines[Amount]),tblLines[Amount],0)))} -> 254844 | I55: {=IF($B55="","",SUMPRODUCT((TRIM(tblLines[Description (Product)])=$B55)*IF(ISNUMBER(tblLines[Commission]),tblLines[Commission],0)))} -> 891.954 | K55: =IF($B55="","",H55/$B$7) -> 0.001317313 | L55: =IFERROR(K55,0) -> 0.001317313 | M55: =IF($B55="","",IFERROR(INDEX(Products!$H$4:$H$500,MATCH($B55,Products!$B$4:$B$500,0)),"Unmapped")) -> Pulses
B56: LAAL LOBIA 25KG | E56: {=IF($B56="","",SUMPRODUCT((TRIM(tblLines[Description (Product)])=$B56)*IF(ISNUMBER(tblLines[Qty (Packs)]),tblLines[Qty (Packs)],0)))} -> 10 | F56: {=IF($B56="","",SUMPRODUCT((TRIM(tblLines[Description (Product)])=$B56)*IF(ISNUMBER(tblLines[Weight (KG)]),tblLines[Weight (KG)],0)))} -> 250 | H56: {=IF($B56="","",SUMPRODUCT((TRIM(tblLines[Description (Product)])=$B56)*IF(ISNUMBER(tblLines[Amount]),tblLines[Amount],0)))} -> 83750 | I56: {=IF($B56="","",SUMPRODUCT((TRIM(tblLines[Description (Product)])=$B56)*IF(ISNUMBER(tblLines[Commission]),tblLines[Commission],0)))} -> 293.125 | K56: =IF($B56="","",H56/$B$7) -> 0.00043291177 | L56: =IFERROR(K56,0) -> 0.00043291177 | M56: =IF($B56="","",IFERROR(INDEX(Products!$H$4:$H$500,MATCH($B56,Products!$B$4:$B$500,0)),"Unmapped")) -> Pulses
B57: MASAR SABIT 25KG | E57: {=IF($B57="","",SUMPRODUCT((TRIM(tblLines[Description (Product)])=$B57)*IF(ISNUMBER(tblLines[Qty (Packs)]),tblLines[Qty (Packs)],0)))} -> 140 | F57: {=IF($B57="","",SUMPRODUCT((TRIM(tblLines[Description (Product)])=$B57)*IF(ISNUMBER(tblLines[Weight (KG)]),tblLines[Weight (KG)],0)))} -> 3500 | H57: {=IF($B57="","",SUMPRODUCT((TRIM(tblLines[Description (Product)])=$B57)*IF(ISNUMBER(tblLines[Amount]),tblLines[Amount],0)))} -> 705626 | I57: {=IF($B57="","",SUMPRODUCT((TRIM(tblLines[Description (Product)])=$B57)*IF(ISNUMBER(tblLines[Commission]),tblLines[Commission],0)))} -> 2469.691 | K57: =IF($B57="","",H57/$B$7) -> 0.0036474484 | L57: =IFERROR(K57,0) -> 0.0036474484 | M57: =IF($B57="","",IFERROR(INDEX(Products!$H$4:$H$500,MATCH($B57,Products!$B$4:$B$500,0)),"Unmapped")) -> Pulses
B58: SINDHI CHANA 5MM 25KG | E58: {=IF($B58="","",SUMPRODUCT((TRIM(tblLines[Description (Product)])=$B58)*IF(ISNUMBER(tblLines[Qty (Packs)]),tblLines[Qty (Packs)],0)))} -> 10 | F58: {=IF($B58="","",SUMPRODUCT((TRIM(tblLines[Description (Product)])=$B58)*IF(ISNUMBER(tblLines[Weight (KG)]),tblLines[Weight (KG)],0)))} -> 250 | H58: {=IF($B58="","",SUMPRODUCT((TRIM(tblLines[Description (Product)])=$B58)*IF(ISNUMBER(tblLines[Amount]),tblLines[Amount],0)))} -> 45938 | I58: {=IF($B58="","",SUMPRODUCT((TRIM(tblLines[Description (Product)])=$B58)*IF(ISNUMBER(tblLines[Commission]),tblLines[Commission],0)))} -> 160.783 | K58: =IF($B58="","",H58/$B$7) -> 0.00023745792 | L58: =IFERROR(K58,0) -> 0.00023745792 | M58: =IF($B58="","",IFERROR(INDEX(Products!$H$4:$H$500,MATCH($B58,Products!$B$4:$B$500,0)),"Unmapped")) -> Pulses
B59: WHITE CHANNA 6MM 25KG | E59: {=IF($B59="","",SUMPRODUCT((TRIM(tblLines[Description (Product)])=$B59)*IF(ISNUMBER(tblLines[Qty (Packs)]),tblLines[Qty (Packs)],0)))} -> 20 | F59: {=IF($B59="","",SUMPRODUCT((TRIM(tblLines[Description (Product)])=$B59)*IF(ISNUMBER(tblLines[Weight (KG)]),tblLines[Weight (KG)],0)))} -> 500 | H59: {=IF($B59="","",SUMPRODUCT((TRIM(tblLines[Description (Product)])=$B59)*IF(ISNUMBER(tblLines[Amount]),tblLines[Amount],0)))} -> 106250 | I59: {=IF($B59="","",SUMPRODUCT((TRIM(tblLines[Description (Product)])=$B59)*IF(ISNUMBER(tblLines[Commission]),tblLines[Commission],0)))} -> 371.875 | K59: =IF($B59="","",H59/$B$7) -> 0.00054921642 | L59: =IFERROR(K59,0) -> 0.00054921642 | M59: =IF($B59="","",IFERROR(INDEX(Products!$H$4:$H$500,MATCH($B59,Products!$B$4:$B$500,0)),"Unmapped")) -> Pulses
B60: WHITE CHANNA 8MM 25KG | E60: {=IF($B60="","",SUMPRODUCT((TRIM(tblLines[Description (Product)])=$B60)*IF(ISNUMBER(tblLines[Qty (Packs)]),tblLines[Qty (Packs)],0)))} -> 65 | F60: {=IF($B60="","",SUMPRODUCT((TRIM(tblLines[Description (Product)])=$B60)*IF(ISNUMBER(tblLines[Weight (KG)]),tblLines[Weight (KG)],0)))} -> 1625 | H60: {=IF($B60="","",SUMPRODUCT((TRIM(tblLines[Description (Product)])=$B60)*IF(ISNUMBER(tblLines[Amount]),tblLines[Amount],0)))} -> 369844 | I60: {=IF($B60="","",SUMPRODUCT((TRIM(tblLines[Description (Product)])=$B60)*IF(ISNUMBER(tblLines[Commission]),tblLines[Commission],0)))} -> 1294.454 | K60: =IF($B60="","",H60/$B$7) -> 0.001911759 | L60: =IFERROR(K60,0) -> 0.001911759 | M60: =IF($B60="","",IFERROR(INDEX(Products!$H$4:$H$500,MATCH($B60,Products!$B$4:$B$500,0)),"Unmapped")) -> Pulses
... B79: ZAFARANI SUTRANGI 25KG | E79: {=IF($B79="","",SUMPRODUCT((TRIM(tblLines[Description (Product)])=$B79)*IF(ISNUMBER(tblLines[Qty (Packs)]),tblLines[Qty (Packs)],0)))} -> 1370 | F79: {=IF($B79="","",SUMPRODUCT((TRIM(tblLines[Description (Product)])=$B79)*IF(ISNUMBER(tblLines[Weight (KG)]),tblLines[Weight (KG)],0)))} -> 34250 | H79: {=IF($B79="","",SUMPRODUCT((TRIM(tblLines[Description (Product)])=$B79)*IF(ISNUMBER(tblLines[Amount]),tblLines[Amount],0)))} -> 9178750 | I79: {=IF($B79="","",SUMPRODUCT((TRIM(tblLines[Description (Product)])=$B79)*IF(ISNUMBER(tblLines[Commission]),tblLines[Commission],0)))} -> 32125.625 | K79: =IF($B79="","",H79/$B$7) -> 0.047445838 | L79: =IFERROR(K79,0) -> 0.047445838 | M79: =IF($B79="","",IFERROR(INDEX(Products!$H$4:$H$500,MATCH($B79,Products!$B$4:$B$500,0)),"Unmapped")) -> Rice
E80: {=IF($B80="","",SUMPRODUCT((TRIM(tblLines[Description (Product)])=$B80)*IF(ISNUMBER(tblLines[Qty (Packs)]),tblLines[Qty (Packs)],0)))} | F80: {=IF($B80="","",SUMPRODUCT((TRIM(tblLines[Description (Product)])=$B80)*IF(ISNUMBER(tblLines[Weight (KG)]),tblLines[Weight (KG)],0)))} | H80: {=IF($B80="","",SUMPRODUCT((TRIM(tblLines[Description (Product)])=$B80)*IF(ISNUMBER(tblLines[Amount]),tblLines[Amount],0)))} | I80: {=IF($B80="","",SUMPRODUCT((TRIM(tblLines[Description (Product)])=$B80)*IF(ISNUMBER(tblLines[Commission]),tblLines[Commission],0)))} | K80: =IF($B80="","",H80/$B$7) | L80: =IFERROR(K80,0) | M80: =IF($B80="","",IFERROR(INDEX(Products!$H$4:$H$500,MATCH($B80,Products!$B$4:$B$500,0)),"Unmapped"))
E81: {=IF($B81="","",SUMPRODUCT((TRIM(tblLines[Description (Product)])=$B81)*IF(ISNUMBER(tblLines[Qty (Packs)]),tblLines[Qty (Packs)],0)))} | F81: {=IF($B81="","",SUMPRODUCT((TRIM(tblLines[Description (Product)])=$B81)*IF(ISNUMBER(tblLines[Weight (KG)]),tblLines[Weight (KG)],0)))} | H81: {=IF($B81="","",SUMPRODUCT((TRIM(tblLines[Description (Product)])=$B81)*IF(ISNUMBER(tblLines[Amount]),tblLines[Amount],0)))} | I81: {=IF($B81="","",SUMPRODUCT((TRIM(tblLines[Description (Product)])=$B81)*IF(ISNUMBER(tblLines[Commission]),tblLines[Commission],0)))} | K81: =IF($B81="","",H81/$B$7) | L81: =IFERROR(K81,0) | M81: =IF($B81="","",IFERROR(INDEX(Products!$H$4:$H$500,MATCH($B81,Products!$B$4:$B$500,0)),"Unmapped"))
E82: {=IF($B82="","",SUMPRODUCT((TRIM(tblLines[Description (Product)])=$B82)*IF(ISNUMBER(tblLines[Qty (Packs)]),tblLines[Qty (Packs)],0)))} | F82: {=IF($B82="","",SUMPRODUCT((TRIM(tblLines[Description (Product)])=$B82)*IF(ISNUMBER(tblLines[Weight (KG)]),tblLines[Weight (KG)],0)))} | H82: {=IF($B82="","",SUMPRODUCT((TRIM(tblLines[Description (Product)])=$B82)*IF(ISNUMBER(tblLines[Amount]),tblLines[Amount],0)))} | I82: {=IF($B82="","",SUMPRODUCT((TRIM(tblLines[Description (Product)])=$B82)*IF(ISNUMBER(tblLines[Commission]),tblLines[Commission],0)))} | K82: =IF($B82="","",H82/$B$7) | L82: =IFERROR(K82,0) | M82: =IF($B82="","",IFERROR(INDEX(Products!$H$4:$H$500,MATCH($B82,Products!$B$4:$B$500,0)),"Unmapped"))
E83: {=IF($B83="","",SUMPRODUCT((TRIM(tblLines[Description (Product)])=$B83)*IF(ISNUMBER(tblLines[Qty (Packs)]),tblLines[Qty (Packs)],0)))} | F83: {=IF($B83="","",SUMPRODUCT((TRIM(tblLines[Description (Product)])=$B83)*IF(ISNUMBER(tblLines[Weight (KG)]),tblLines[Weight (KG)],0)))} | H83: {=IF($B83="","",SUMPRODUCT((TRIM(tblLines[Description (Product)])=$B83)*IF(ISNUMBER(tblLines[Amount]),tblLines[Amount],0)))} | I83: {=IF($B83="","",SUMPRODUCT((TRIM(tblLines[Description (Product)])=$B83)*IF(ISNUMBER(tblLines[Commission]),tblLines[Commission],0)))} | K83: =IF($B83="","",H83/$B$7) | L83: =IFERROR(K83,0) | M83: =IF($B83="","",IFERROR(INDEX(Products!$H$4:$H$500,MATCH($B83,Products!$B$4:$B$500,0)),"Unmapped"))
E84: {=IF($B84="","",SUMPRODUCT((TRIM(tblLines[Description (Product)])=$B84)*IF(ISNUMBER(tblLines[Qty (Packs)]),tblLines[Qty (Packs)],0)))} | F84: {=IF($B84="","",SUMPRODUCT((TRIM(tblLines[Description (Product)])=$B84)*IF(ISNUMBER(tblLines[Weight (KG)]),tblLines[Weight (KG)],0)))} | H84: {=IF($B84="","",SUMPRODUCT((TRIM(tblLines[Description (Product)])=$B84)*IF(ISNUMBER(tblLines[Amount]),tblLines[Amount],0)))} | I84: {=IF($B84="","",SUMPRODUCT((TRIM(tblLines[Description (Product)])=$B84)*IF(ISNUMBER(tblLines[Commission]),tblLines[Commission],0)))} | K84: =IF($B84="","",H84/$B$7) | L84: =IFERROR(K84,0) | M84: =IF($B84="","",IFERROR(INDEX(Products!$H$4:$H$500,MATCH($B84,Products!$B$4:$B$500,0)),"Unmapped"))
E85: {=IF($B85="","",SUMPRODUCT((TRIM(tblLines[Description (Product)])=$B85)*IF(ISNUMBER(tblLines[Qty (Packs)]),tblLines[Qty (Packs)],0)))} | F85: {=IF($B85="","",SUMPRODUCT((TRIM(tblLines[Description (Product)])=$B85)*IF(ISNUMBER(tblLines[Weight (KG)]),tblLines[Weight (KG)],0)))} | H85: {=IF($B85="","",SUMPRODUCT((TRIM(tblLines[Description (Product)])=$B85)*IF(ISNUMBER(tblLines[Amount]),tblLines[Amount],0)))} | I85: {=IF($B85="","",SUMPRODUCT((TRIM(tblLines[Description (Product)])=$B85)*IF(ISNUMBER(tblLines[Commission]),tblLines[Commission],0)))} | K85: =IF($B85="","",H85/$B$7) | L85: =IFERROR(K85,0) | M85: =IF($B85="","",IFERROR(INDEX(Products!$H$4:$H$500,MATCH($B85,Products!$B$4:$B$500,0)),"Unmapped"))
E86: {=IF($B86="","",SUMPRODUCT((TRIM(tblLines[Description (Product)])=$B86)*IF(ISNUMBER(tblLines[Qty (Packs)]),tblLines[Qty (Packs)],0)))} | F86: {=IF($B86="","",SUMPRODUCT((TRIM(tblLines[Description (Product)])=$B86)*IF(ISNUMBER(tblLines[Weight (KG)]),tblLines[Weight (KG)],0)))} | H86: {=IF($B86="","",SUMPRODUCT((TRIM(tblLines[Description (Product)])=$B86)*IF(ISNUMBER(tblLines[Amount]),tblLines[Amount],0)))} | I86: {=IF($B86="","",SUMPRODUCT((TRIM(tblLines[Description (Product)])=$B86)*IF(ISNUMBER(tblLines[Commission]),tblLines[Commission],0)))} | K86: =IF($B86="","",H86/$B$7) | L86: =IFERROR(K86,0) | M86: =IF($B86="","",IFERROR(INDEX(Products!$H$4:$H$500,MATCH($B86,Products!$B$4:$B$500,0)),"Unmapped"))
E87: {=IF($B87="","",SUMPRODUCT((TRIM(tblLines[Description (Product)])=$B87)*IF(ISNUMBER(tblLines[Qty (Packs)]),tblLines[Qty (Packs)],0)))} | F87: {=IF($B87="","",SUMPRODUCT((TRIM(tblLines[Description (Product)])=$B87)*IF(ISNUMBER(tblLines[Weight (KG)]),tblLines[Weight (KG)],0)))} | H87: {=IF($B87="","",SUMPRODUCT((TRIM(tblLines[Description (Product)])=$B87)*IF(ISNUMBER(tblLines[Amount]),tblLines[Amount],0)))} | I87: {=IF($B87="","",SUMPRODUCT((TRIM(tblLines[Description (Product)])=$B87)*IF(ISNUMBER(tblLines[Commission]),tblLines[Commission],0)))} | K87: =IF($B87="","",H87/$B$7) | L87: =IFERROR(K87,0) | M87: =IF($B87="","",IFERROR(INDEX(Products!$H$4:$H$500,MATCH($B87,Products!$B$4:$B$500,0)),"Unmapped"))
B90: PAYMENTS & RECOVERY
B92: TOTAL RECOVERED (PKR) | C92: ="▲ "&TEXT(IF($B$7=0,0,$B$93/$B$7),"0.0%")&" of sales" -> ▲ 0.0% of sales | E92: OUTSTANDING (PKR) | F92: ="● "&TEXT(IF($B$7=0,0,$E$93/$B$7),"0.0%")&" still due" -> ● 100.0% still due | H92: RECOVERY RATE | K92: PAYMENTS LOGGED
B93: =SUM(tblPayments[Amount]) -> 0 | E93: =$B$7-$B$93 -> 193457434 | H93: =IF($B$7=0,"",$B$93/$B$7) -> 0 | K93: =COUNT(tblPayments[Amount]) -> 0
B96: RECOVERY BY PARTY
B97: PARTY (NAME) | E97: INVOICED (PKR) | F97: RECOVERED (PKR) | H97: OUTSTANDING (PKR) | I97: LAST PAYMENT | K97: % RECOVERED | L97: SHARE
B98: =IF(Payments!J21="","",Payments!J21) -> Allah Walay Traders | E98: =IF($B98="","",Payments!K21) -> 9287189 | F98: =IF($B98="","",Payments!L21) -> 0 | H98: =IF($B98="","",Payments!M21) -> 9287189 | I98: =IF($B98="","",IF(_xlfn.MAXIFS(tblPayments[Date],tblPayments[Party (Name)],$B98)=0,"",_xlfn.MAXIFS(tblPayments[Date],tblPayments[Party (Name)],$B98))) | K98: =IF(OR($B98="",$E98=0),"",$F98/$E98) -> 0 | L98: =IFERROR(K98,0) -> 0
B99: =IF(Payments!J22="","",Payments!J22) -> Ashfaq Commission shop | E99: =IF($B99="","",Payments!K22) -> 5062500 | F99: =IF($B99="","",Payments!L22) -> 0 | H99: =IF($B99="","",Payments!M22) -> 5062500 | I99: =IF($B99="","",IF(_xlfn.MAXIFS(tblPayments[Date],tblPayments[Party (Name)],$B99)=0,"",_xlfn.MAXIFS(tblPayments[Date],tblPayments[Party (Name)],$B99))) | K99: =IF(OR($B99="",$E99=0),"",$F99/$E99) -> 0 | L99: =IFERROR(K99,0) -> 0
B100: =IF(Payments!J23="","",Payments!J23) -> Bhayya Traders | E100: =IF($B100="","",Payments!K23) -> 4556250 | F100: =IF($B100="","",Payments!L23) -> 0 | H100: =IF($B100="","",Payments!M23) -> 4556250 | I100: =IF($B100="","",IF(_xlfn.MAXIFS(tblPayments[Date],tblPayments[Party (Name)],$B100)=0,"",_xlfn.MAXIFS(tblPayments[Date],tblPayments[Party (Name)],$B100))) | K100: =IF(OR($B100="",$E100=0),"",$F100/$E100) -> 0 | L100: =IFERROR(K100,0) -> 0
B101: =IF(Payments!J24="","",Payments!J24) -> Hamdard Traders | E101: =IF($B101="","",Payments!K24) -> 6053807 | F101: =IF($B101="","",Payments!L24) -> 0 | H101: =IF($B101="","",Payments!M24) -> 6053807 | I101: =IF($B101="","",IF(_xlfn.MAXIFS(tblPayments[Date],tblPayments[Party (Name)],$B101)=0,"",_xlfn.MAXIFS(tblPayments[Date],tblPayments[Party (Name)],$B101))) | K101: =IF(OR($B101="",$E101=0),"",$F101/$E101) -> 0 | L101: =IFERROR(K101,0) -> 0
B102: =IF(Payments!J25="","",Payments!J25) -> Hassan Enterprises | E102: =IF($B102="","",Payments!K25) -> 12054139 | F102: =IF($B102="","",Payments!L25) -> 0 | H102: =IF($B102="","",Payments!M25) -> 12054139 | I102: =IF($B102="","",IF(_xlfn.MAXIFS(tblPayments[Date],tblPayments[Party (Name)],$B102)=0,"",_xlfn.MAXIFS(tblPayments[Date],tblPayments[Party (Name)],$B102))) | K102: =IF(OR($B102="",$E102=0),"",$F102/$E102) -> 0 | L102: =IFERROR(K102,0) -> 0
B103: =IF(Payments!J26="","",Payments!J26) -> Imran Traders | E103: =IF($B103="","",Payments!K26) -> 3237500 | F103: =IF($B103="","",Payments!L26) -> 0 | H103: =IF($B103="","",Payments!M26) -> 3237500 | I103: =IF($B103="","",IF(_xlfn.MAXIFS(tblPayments[Date],tblPayments[Party (Name)],$B103)=0,"",_xlfn.MAXIFS(tblPayments[Date],tblPayments[Party (Name)],$B103))) | K103: =IF(OR($B103="",$E103=0),"",$F103/$E103) -> 0 | L103: =IFERROR(K103,0) -> 0
B104: =IF(Payments!J27="","",Payments!J27) -> Pak Rice Traders | E104: =IF($B104="","",Payments!K27) -> 122823474 | F104: =IF($B104="","",Payments!L27) -> 0 | H104: =IF($B104="","",Payments!M27) -> 122823474 | I104: =IF($B104="","",IF(_xlfn.MAXIFS(tblPayments[Date],tblPayments[Party (Name)],$B104)=0,"",_xlfn.MAXIFS(tblPayments[Date],tblPayments[Party (Name)],$B104))) | K104: =IF(OR($B104="",$E104=0),"",$F104/$E104) -> 0 | L104: =IFERROR(K104,0) -> 0
B105: =IF(Payments!J28="","",Payments!J28) -> Pakistan Traders | E105: =IF($B105="","",Payments!K28) -> 2545313 | F105: =IF($B105="","",Payments!L28) -> 0 | H105: =IF($B105="","",Payments!M28) -> 2545313 | I105: =IF($B105="","",IF(_xlfn.MAXIFS(tblPayments[Date],tblPayments[Party (Name)],$B105)=0,"",_xlfn.MAXIFS(tblPayments[Date],tblPayments[Party (Name)],$B105))) | K105: =IF(OR($B105="",$E105=0),"",$F105/$E105) -> 0 | L105: =IFERROR(K105,0) -> 0
B106: =IF(Payments!J29="","",Payments!J29) -> Shalimar Traders | E106: =IF($B106="","",Payments!K29) -> 20111694 | F106: =IF($B106="","",Payments!L29) -> 0 | H106: =IF($B106="","",Payments!M29) -> 20111694 | I106: =IF($B106="","",IF(_xlfn.MAXIFS(tblPayments[Date],tblPayments[Party (Name)],$B106)=0,"",_xlfn.MAXIFS(tblPayments[Date],tblPayments[Party (Name)],$B106))) | K106: =IF(OR($B106="",$E106=0),"",$F106/$E106) -> 0 | L106: =IFERROR(K106,0) -> 0
B107: =IF(Payments!J30="","",Payments!J30) -> Sheikh Traders | E107: =IF($B107="","",Payments!K30) -> 4249063 | F107: =IF($B107="","",Payments!L30) -> 0 | H107: =IF($B107="","",Payments!M30) -> 4249063 | I107: =IF($B107="","",IF(_xlfn.MAXIFS(tblPayments[Date],tblPayments[Party (Name)],$B107)=0,"",_xlfn.MAXIFS(tblPayments[Date],tblPayments[Party (Name)],$B107))) | K107: =IF(OR($B107="",$E107=0),"",$F107/$E107) -> 0 | L107: =IFERROR(K107,0) -> 0
B108: =IF(Payments!J31="","",Payments!J31) -> Tayyab Traders | E108: =IF($B108="","",Payments!K31) -> 3476505 | F108: =IF($B108="","",Payments!L31) -> 0 | H108: =IF($B108="","",Payments!M31) -> 3476505 | I108: =IF($B108="","",IF(_xlfn.MAXIFS(tblPayments[Date],tblPayments[Party (Name)],$B108)=0,"",_xlfn.MAXIFS(tblPayments[Date],tblPayments[Party (Name)],$B108))) | K108: =IF(OR($B108="",$E108=0),"",$F108/$E108) -> 0 | L108: =IFERROR(K108,0) -> 0
B109: =IF(Payments!J32="","",Payments!J32) | E109: =IF($B109="","",Payments!K32) | F109: =IF($B109="","",Payments!L32) | H109: =IF($B109="","",Payments!M32) | I109: =IF($B109="","",IF(_xlfn.MAXIFS(tblPayments[Date],tblPayments[Party (Name)],$B109)=0,"",_xlfn.MAXIFS(tblPayments[Date],tblPayments[Party (Name)],$B109))) | K109: =IF(OR($B109="",$E109=0),"",$F109/$E109) | L109: =IFERROR(K109,0)

Sheet Database
A1: Invoice # | B1: Invoice Date | C1: Party (Name) | D1: Sub Party | E1: City | F1: ASM / Salesperson | G1: Description (Product) | H1: Qty (Packs) | I1: Rate 40Kg | J1: Pack Wt (KG) | K1: Rate / Pack | L1: Amount | M1: Commission | N1: Weight (KG)
A2: 6 | B2: 46266 | C2: Pak Rice Traders | E2: Dina | F2: Farhan Khalid | G2: ZAFARANI STEAM PLATINUM 25KG | H2: 125 | I2: 13500 | J2: =IFERROR(INDEX(Products!$E$4:$E$500,MATCH(tblLines[[#This Row],[Description (Product)]],Products!$B$4:$B$500,0)),"") -> 25 | K2: =IF(OR(tblLines[[#This Row],[Description (Product)]]="",tblLines[[#This Row],[Rate 40Kg]]=""),"",tblLines[[#This Row],[Rate 40Kg]]/40*tblLines[[#This Row],[Pack Wt (KG)]]) -> 8437.5 | L2: =IF(OR(tblLines[[#This Row],[Rate / Pack]]="",tblLines[[#This Row],[Qty (Packs)]]=""),"",ROUND(tblLines[[#This Row],[Rate / Pack]]*tblLines[[#This Row],[Qty (Packs)]],0)) -> 1054688 | M2: =IF(tblLines[[#This Row],[Amount]]="","",tblLines[[#This Row],[Amount]]*IFERROR(INDEX(Products!$I$4:$I$500,MATCH(tblLines[[#This Row],[Description (Product)]],Products!$B$4:$B$500,0)),frmCommRate)) -> 3691.408 | N2: =IF(tblLines[[#This Row],[Qty (Packs)]]="","",tblLines[[#This Row],[Qty (Packs)]]*tblLines[[#This Row],[Pack Wt (KG)]]) -> 3125
A3: 6 | B3: 46266 | C3: Pak Rice Traders | E3: Dina | F3: Farhan Khalid | G3: ZAFARANI SUTRANGI 25KG | H3: 200 | I3: 10600 | J3: =IFERROR(INDEX(Products!$E$4:$E$500,MATCH(tblLines[[#This Row],[Description (Product)]],Products!$B$4:$B$500,0)),"") -> 25 | K3: =IF(OR(tblLines[[#This Row],[Description (Product)]]="",tblLines[[#This Row],[Rate 40Kg]]=""),"",tblLines[[#This Row],[Rate 40Kg]]/40*tblLines[[#This Row],[Pack Wt (KG)]]) -> 6625 | L3: =IF(OR(tblLines[[#This Row],[Rate / Pack]]="",tblLines[[#This Row],[Qty (Packs)]]=""),"",ROUND(tblLines[[#This Row],[Rate / Pack]]*tblLines[[#This Row],[Qty (Packs)]],0)) -> 1325000 | M3: =IF(tblLines[[#This Row],[Amount]]="","",tblLines[[#This Row],[Amount]]*IFERROR(INDEX(Products!$I$4:$I$500,MATCH(tblLines[[#This Row],[Description (Product)]],Products!$B$4:$B$500,0)),frmCommRate)) -> 4637.5 | N3: =IF(tblLines[[#This Row],[Qty (Packs)]]="","",tblLines[[#This Row],[Qty (Packs)]]*tblLines[[#This Row],[Pack Wt (KG)]]) -> 5000
A4: 6 | B4: 46266 | C4: Pak Rice Traders | E4: Dina | F4: Farhan Khalid | G4: ZAFARANI STEAM B-1, 25KG | H4: 50 | I4: 7650 | J4: =IFERROR(INDEX(Products!$E$4:$E$500,MATCH(tblLines[[#This Row],[Description (Product)]],Products!$B$4:$B$500,0)),"") -> 25 | K4: =IF(OR(tblLines[[#This Row],[Description (Product)]]="",tblLines[[#This Row],[Rate 40Kg]]=""),"",tblLines[[#This Row],[Rate 40Kg]]/40*tblLines[[#This Row],[Pack Wt (KG)]]) -> 4781.25 | L4: =IF(OR(tblLines[[#This Row],[Rate / Pack]]="",tblLines[[#This Row],[Qty (Packs)]]=""),"",ROUND(tblLines[[#This Row],[Rate / Pack]]*tblLines[[#This Row],[Qty (Packs)]],0)) -> 239063 | M4: =IF(tblLines[[#This Row],[Amount]]="","",tblLines[[#This Row],[Amount]]*IFERROR(INDEX(Products!$I$4:$I$500,MATCH(tblLines[[#This Row],[Description (Product)]],Products!$B$4:$B$500,0)),frmCommRate)) -> 836.7205 | N4: =IF(tblLines[[#This Row],[Qty (Packs)]]="","",tblLines[[#This Row],[Qty (Packs)]]*tblLines[[#This Row],[Pack Wt (KG)]]) -> 1250
A5: 6 | B5: 46266 | C5: Pak Rice Traders | E5: Dina | F5: Farhan Khalid | G5: ZAFARANI SELLA GOLDEN 25KG | H5: 125 | I5: 12150 | J5: =IFERROR(INDEX(Products!$E$4:$E$500,MATCH(tblLines[[#This Row],[Description (Product)]],Products!$B$4:$B$500,0)),"") -> 25 | K5: =IF(OR(tblLines[[#This Row],[Description (Product)]]="",tblLines[[#This Row],[Rate 40Kg]]=""),"",tblLines[[#This Row],[Rate 40Kg]]/40*tblLines[[#This Row],[Pack Wt (KG)]]) -> 7593.75 | L5: =IF(OR(tblLines[[#This Row],[Rate / Pack]]="",tblLines[[#This Row],[Qty (Packs)]]=""),"",ROUND(tblLines[[#This Row],[Rate / Pack]]*tblLines[[#This Row],[Qty (Packs)]],0)) -> 949219 | M5: =IF(tblLines[[#This Row],[Amount]]="","",tblLines[[#This Row],[Amount]]*IFERROR(INDEX(Products!$I$4:$I$500,MATCH(tblLines[[#This Row],[Description (Product)]],Products!$B$4:$B$500,0)),frmCommRate)) -> 3322.2665 | N5: =IF(tblLines[[#This Row],[Qty (Packs)]]="","",tblLines[[#This Row],[Qty (Packs)]]*tblLines[[#This Row],[Pack Wt (KG)]]) -> 3125 | Q5: weight in tons | R5: =SUM(tblLines[Weight (KG)])/1000 -> 841.18
A6: 7 | B6: 46266 | C6: Pak Rice Traders | E6: Dina | F6: Farhan Khalid | G6: DAAL MOONG 25KG | H6: 25 | I6: 10250 | J6: =IFERROR(INDEX(Products!$E$4:$E$500,MATCH(tblLines[[#This Row],[Description (Product)]],Products!$B$4:$B$500,0)),"") -> 25 | K6: =IF(OR(tblLines[[#This Row],[Description (Product)]]="",tblLines[[#This Row],[Rate 40Kg]]=""),"",tblLines[[#This Row],[Rate 40Kg]]/40*tblLines[[#This Row],[Pack Wt (KG)]]) -> 6406.25 | L6: =IF(OR(tblLines[[#This Row],[Rate / Pack]]="",tblLines[[#This Row],[Qty (Packs)]]=""),"",ROUND(tblLines[[#This Row],[Rate / Pack]]*tblLines[[#This Row],[Qty (Packs)]],0)) -> 160156 | M6: =IF(tblLines[[#This Row],[Amount]]="","",tblLines[[#This Row],[Amount]]*IFERROR(INDEX(Products!$I$4:$I$500,MATCH(tblLines[[#This Row],[Description (Product)]],Products!$B$4:$B$500,0)),frmCommRate)) -> 560.546 | N6: =IF(tblLines[[#This Row],[Qty (Packs)]]="","",tblLines[[#This Row],[Qty (Packs)]]*tblLines[[#This Row],[Pack Wt (KG)]]) -> 625 | Q6: Total Sale | R6: =SUM(tblLines[Amount]) -> 193457434
A7: 7 | B7: 46266 | C7: Pak Rice Traders | E7: Dina | F7: Farhan Khalid | G7: DALL MASOOR 25KG | H7: 20 | I7: 8400 | J7: =IFERROR(INDEX(Products!$E$4:$E$500,MATCH(tblLines[[#This Row],[Description (Product)]],Products!$B$4:$B$500,0)),"") -> 25 | K7: =IF(OR(tblLines[[#This Row],[Description (Product)]]="",tblLines[[#This Row],[Rate 40Kg]]=""),"",tblLines[[#This Row],[Rate 40Kg]]/40*tblLines[[#This Row],[Pack Wt (KG)]]) -> 5250 | L7: =IF(OR(tblLines[[#This Row],[Rate / Pack]]="",tblLines[[#This Row],[Qty (Packs)]]=""),"",ROUND(tblLines[[#This Row],[Rate / Pack]]*tblLines[[#This Row],[Qty (Packs)]],0)) -> 105000 | M7: =IF(tblLines[[#This Row],[Amount]]="","",tblLines[[#This Row],[Amount]]*IFERROR(INDEX(Products!$I$4:$I$500,MATCH(tblLines[[#This Row],[Description (Product)]],Products!$B$4:$B$500,0)),frmCommRate)) -> 367.5 | N7: =IF(tblLines[[#This Row],[Qty (Packs)]]="","",tblLines[[#This Row],[Qty (Packs)]]*tblLines[[#This Row],[Pack Wt (KG)]]) -> 500 | Q7: commission | R7: =SUM(tblLines[Commission]) -> 677101.02
A8: 7 | B8: 46266 | C8: Pak Rice Traders | E8: Dina | F8: Farhan Khalid | G8: DAAL MASH CHARI 25KG | H8: 25 | I8: 16250 | J8: =IFERROR(INDEX(Products!$E$4:$E$500,MATCH(tblLines[[#This Row],[Description (Product)]],Products!$B$4:$B$500,0)),"") -> 25 | K8: =IF(OR(tblLines[[#This Row],[Description (Product)]]="",tblLines[[#This Row],[Rate 40Kg]]=""),"",tblLines[[#This Row],[Rate 40Kg]]/40*tblLines[[#This Row],[Pack Wt (KG)]]) -> 10156.25 | L8: =IF(OR(tblLines[[#This Row],[Rate / Pack]]="",tblLines[[#This Row],[Qty (Packs)]]=""),"",ROUND(tblLines[[#This Row],[Rate / Pack]]*tblLines[[#This Row],[Qty (Packs)]],0)) -> 253906 | M8: =IF(tblLines[[#This Row],[Amount]]="","",tblLines[[#This Row],[Amount]]*IFERROR(INDEX(Products!$I$4:$I$500,MATCH(tblLines[[#This Row],[Description (Product)]],Products!$B$4:$B$500,0)),frmCommRate)) -> 888.671 | N8: =IF(tblLines[[#This Row],[Qty (Packs)]]="","",tblLines[[#This Row],[Qty (Packs)]]*tblLines[[#This Row],[Pack Wt (KG)]]) -> 625 | Q8: Total Packs | R8: =SUM(tblLines[Qty (Packs)]) -> 33509
A9: 7 | B9: 46266 | C9: Pak Rice Traders | E9: Dina | F9: Farhan Khalid | G9: MASAR SABIT 25KG | H9: 30 | I9: 8000 | J9: =IFERROR(INDEX(Products!$E$4:$E$500,MATCH(tblLines[[#This Row],[Description (Product)]],Products!$B$4:$B$500,0)),"") -> 25 | K9: =IF(OR(tblLines[[#This Row],[Description (Product)]]="",tblLines[[#This Row],[Rate 40Kg]]=""),"",tblLines[[#This Row],[Rate 40Kg]]/40*tblLines[[#This Row],[Pack Wt (KG)]]) -> 5000 | L9: =IF(OR(tblLines[[#This Row],[Rate / Pack]]="",tblLines[[#This Row],[Qty (Packs)]]=""),"",ROUND(tblLines[[#This Row],[Rate / Pack]]*tblLines[[#This Row],[Qty (Packs)]],0)) -> 150000 | M9: =IF(tblLines[[#This Row],[Amount]]="","",tblLines[[#This Row],[Amount]]*IFERROR(INDEX(Products!$I$4:$I$500,MATCH(tblLines[[#This Row],[Description (Product)]],Products!$B$4:$B$500,0)),frmCommRate)) -> 525 | N9: =IF(tblLines[[#This Row],[Qty (Packs)]]="","",tblLines[[#This Row],[Qty (Packs)]]*tblLines[[#This Row],[Pack Wt (KG)]]) -> 750 | Q9: Avg of Ton | R9: =R6/R5 -> 229983.4
A10: 14 | B10: 46267 | C10: Pak Rice Traders | E10: Dina | F10: Farhan Khalid | G10: ZAFARANI STEAM PLATINUM 25KG | H10: 200 | I10: 13500 | J10: =IFERROR(INDEX(Products!$E$4:$E$500,MATCH(tblLines[[#This Row],[Description (Product)]],Products!$B$4:$B$500,0)),"") -> 25 | K10: =IF(OR(tblLines[[#This Row],[Description (Product)]]="",tblLines[[#This Row],[Rate 40Kg]]=""),"",tblLines[[#This Row],[Rate 40Kg]]/40*tblLines[[#This Row],[Pack Wt (KG)]]) -> 8437.5 | L10: =IF(OR(tblLines[[#This Row],[Rate / Pack]]="",tblLines[[#This Row],[Qty (Packs)]]=""),"",ROUND(tblLines[[#This Row],[Rate / Pack]]*tblLines[[#This Row],[Qty (Packs)]],0)) -> 1687500 | M10: =IF(tblLines[[#This Row],[Amount]]="","",tblLines[[#This Row],[Amount]]*IFERROR(INDEX(Products!$I$4:$I$500,MATCH(tblLines[[#This Row],[Description (Product)]],Products!$B$4:$B$500,0)),frmCommRate)) -> 5906.25 | N10: =IF(tblLines[[#This Row],[Qty (Packs)]]="","",tblLines[[#This Row],[Qty (Packs)]]*tblLines[[#This Row],[Pack Wt (KG)]]) -> 5000 | Q10: Avg of Pack | R10: =R6/R8 -> 5773.2977
A11: 14 | B11: 46267 | C11: Pak Rice Traders | E11: Dina | F11: Farhan Khalid | G11: ZAFARANI SUTRANGI 25KG | H11: 200 | I11: 10600 | J11: =IFERROR(INDEX(Products!$E$4:$E$500,MATCH(tblLines[[#This Row],[Description (Product)]],Products!$B$4:$B$500,0)),"") -> 25 | K11: =IF(OR(tblLines[[#This Row],[Description (Product)]]="",tblLines[[#This Row],[Rate 40Kg]]=""),"",tblLines[[#This Row],[Rate 40Kg]]/40*tblLines[[#This Row],[Pack Wt (KG)]]) -> 6625 | L11: =IF(OR(tblLines[[#This Row],[Rate / Pack]]="",tblLines[[#This Row],[Qty (Packs)]]=""),"",ROUND(tblLines[[#This Row],[Rate / Pack]]*tblLines[[#This Row],[Qty (Packs)]],0)) -> 1325000 | M11: =IF(tblLines[[#This Row],[Amount]]="","",tblLines[[#This Row],[Amount]]*IFERROR(INDEX(Products!$I$4:$I$500,MATCH(tblLines[[#This Row],[Description (Product)]],Products!$B$4:$B$500,0)),frmCommRate)) -> 4637.5 | N11: =IF(tblLines[[#This Row],[Qty (Packs)]]="","",tblLines[[#This Row],[Qty (Packs)]]*tblLines[[#This Row],[Pack Wt (KG)]]) -> 5000
A12: 15 | B12: 46267 | C12: Pak Rice Traders | E12: Dina | F12: Farhan Khalid | G12: MASAR SABIT 25KG | H12: 30 | I12: 8000 | J12: =IFERROR(INDEX(Products!$E$4:$E$500,MATCH(tblLines[[#This Row],[Description (Product)]],Products!$B$4:$B$500,0)),"") -> 25 | K12: =IF(OR(tblLines[[#This Row],[Description (Product)]]="",tblLines[[#This Row],[Rate 40Kg]]=""),"",tblLines[[#This Row],[Rate 40Kg]]/40*tblLines[[#This Row],[Pack Wt (KG)]]) -> 5000 | L12: =IF(OR(tblLines[[#This Row],[Rate / Pack]]="",tblLines[[#This Row],[Qty (Packs)]]=""),"",ROUND(tblLines[[#This Row],[Rate / Pack]]*tblLines[[#This Row],[Qty (Packs)]],0)) -> 150000 | M12: =IF(tblLines[[#This Row],[Amount]]="","",tblLines[[#This Row],[Amount]]*IFERROR(INDEX(Products!$I$4:$I$500,MATCH(tblLines[[#This Row],[Description (Product)]],Products!$B$4:$B$500,0)),frmCommRate)) -> 525 | N12: =IF(tblLines[[#This Row],[Qty (Packs)]]="","",tblLines[[#This Row],[Qty (Packs)]]*tblLines[[#This Row],[Pack Wt (KG)]]) -> 750
A13: 15 | B13: 46267 | C13: Pak Rice Traders | E13: Dina | F13: Farhan Khalid | G13: DAAL MASH CHARI 25KG | H13: 20 | I13: 16250 | J13: =IFERROR(INDEX(Products!$E$4:$E$500,MATCH(tblLines[[#This Row],[Description (Product)]],Products!$B$4:$B$500,0)),"") -> 25 | K13: =IF(OR(tblLines[[#This Row],[Description (Product)]]="",tblLines[[#This Row],[Rate 40Kg]]=""),"",tblLines[[#This Row],[Rate 40Kg]]/40*tblLines[[#This Row],[Pack Wt (KG)]]) -> 10156.25 | L13: =IF(OR(tblLines[[#This Row],[Rate / Pack]]="",tblLines[[#This Row],[Qty (Packs)]]=""),"",ROUND(tblLines[[#This Row],[Rate / Pack]]*tblLines[[#This Row],[Qty (Packs)]],0)) -> 203125 | M13: =IF(tblLines[[#This Row],[Amount]]="","",tblLines[[#This Row],[Amount]]*IFERROR(INDEX(Products!$I$4:$I$500,MATCH(tblLines[[#This Row],[Description (Product)]],Products!$B$4:$B$500,0)),frmCommRate)) -> 710.9375 | N13: =IF(tblLines[[#This Row],[Qty (Packs)]]="","",tblLines[[#This Row],[Qty (Packs)]]*tblLines[[#This Row],[Pack Wt (KG)]]) -> 500
A14: 15 | B14: 46267 | C14: Pak Rice Traders | E14: Dina | F14: Farhan Khalid | G14: DAAL MOONG 25KG | H14: 30 | I14: 10250 | J14: =IFERROR(INDEX(Products!$E$4:$E$500,MATCH(tblLines[[#This Row],[Description (Product)]],Products!$B$4:$B$500,0)),"") -> 25 | K14: =IF(OR(tblLines[[#This Row],[Description (Product)]]="",tblLines[[#This Row],[Rate 40Kg]]=""),"",tblLines[[#This Row],[Rate 40Kg]]/40*tblLines[[#This Row],[Pack Wt (KG)]]) -> 6406.25 | L14: =IF(OR(tblLines[[#This Row],[Rate / Pack]]="",tblLines[[#This Row],[Qty (Packs)]]=""),"",ROUND(tblLines[[#This Row],[Rate / Pack]]*tblLines[[#This Row],[Qty (Packs)]],0)) -> 192188 | M14: =IF(tblLines[[#This Row],[Amount]]="","",tblLines[[#This Row],[Amount]]*IFERROR(INDEX(Products!$I$4:$I$500,MATCH(tblLines[[#This Row],[Description (Product)]],Products!$B$4:$B$500,0)),frmCommRate)) -> 672.658 | N14: =IF(tblLines[[#This Row],[Qty (Packs)]]="","",tblLines[[#This Row],[Qty (Packs)]]*tblLines[[#This Row],[Pack Wt (KG)]]) -> 750
A15: 15 | B15: 46267 | C15: Pak Rice Traders | E15: Dina | F15: Farhan Khalid | G15: DALL MASOOR 25KG | H15: 20 | I15: 8400 | J15: =IFERROR(INDEX(Products!$E$4:$E$500,MATCH(tblLines[[#This Row],[Description (Product)]],Products!$B$4:$B$500,0)),"") -> 25 | K15: =IF(OR(tblLines[[#This Row],[Description (Product)]]="",tblLines[[#This Row],[Rate 40Kg]]=""),"",tblLines[[#This Row],[Rate 40Kg]]/40*tblLines[[#This Row],[Pack Wt (KG)]]) -> 5250 | L15: =IF(OR(tblLines[[#This Row],[Rate / Pack]]="",tblLines[[#This Row],[Qty (Packs)]]=""),"",ROUND(tblLines[[#This Row],[Rate / Pack]]*tblLines[[#This Row],[Qty (Packs)]],0)) -> 105000 | M15: =IF(tblLines[[#This Row],[Amount]]="","",tblLines[[#This Row],[Amount]]*IFERROR(INDEX(Products!$I$4:$I$500,MATCH(tblLines[[#This Row],[Description (Product)]],Products!$B$4:$B$500,0)),frmCommRate)) -> 367.5 | N15: =IF(tblLines[[#This Row],[Qty (Packs)]]="","",tblLines[[#This Row],[Qty (Packs)]]*tblLines[[#This Row],[Pack Wt (KG)]]) -> 500
A16: 15 | B16: 46267 | C16: Pak Rice Traders | E16: Dina | F16: Farhan Khalid | G16: DAAL CHANNA SUPREME 25KG | H16: 100 | I16: 9950 | J16: =IFERROR(INDEX(Products!$E$4:$E$500,MATCH(tblLines[[#This Row],[Description (Product)]],Products!$B$4:$B$500,0)),"") -> 25 | K16: =IF(OR(tblLines[[#This Row],[Description (Product)]]="",tblLines[[#This Row],[Rate 40Kg]]=""),"",tblLines[[#This Row],[Rate 40Kg]]/40*tblLines[[#This Row],[Pack Wt (KG)]]) -> 6218.75 | L16: =IF(OR(tblLines[[#This Row],[Rate / Pack]]="",tblLines[[#This Row],[Qty (Packs)]]=""),"",ROUND(tblLines[[#This Row],[Rate / Pack]]*tblLines[[#This Row],[Qty (Packs)]],0)) -> 621875 | M16: =IF(tblLines[[#This Row],[Amount]]="","",tblLines[[#This Row],[Amount]]*IFERROR(INDEX(Products!$I$4:$I$500,MATCH(tblLines[[#This Row],[Description (Product)]],Products!$B$4:$B$500,0)),frmCommRate)) -> 2176.5625 | N16: =IF(tblLines[[#This Row],[Qty (Packs)]]="","",tblLines[[#This Row],[Qty (Packs)]]*tblLines[[#This Row],[Pack Wt (KG)]]) -> 2500
A17: 16 | B17: 46267 | C17: Allah Walay Traders | E17: Nakyal Ajk | F17: Farhan Khalid | G17: ZAFARANI STEAM PLATINUM 25KG | H17: 200 | I17: 13700 | J17: =IFERROR(INDEX(Products!$E$4:$E$500,MATCH(tblLines[[#This Row],[Description (Product)]],Products!$B$4:$B$500,0)),"") -> 25 | K17: =IF(OR(tblLines[[#This Row],[Description (Product)]]="",tblLines[[#This Row],[Rate 40Kg]]=""),"",tblLines[[#This Row],[Rate 40Kg]]/40*tblLines[[#This Row],[Pack Wt (KG)]]) -> 8562.5 | L17: =IF(OR(tblLines[[#This Row],[Rate / Pack]]="",tblLines[[#This Row],[Qty (Packs)]]=""),"",ROUND(tblLines[[#This Row],[Rate / Pack]]*tblLines[[#This Row],[Qty (Packs)]],0)) -> 1712500 | M17: =IF(tblLines[[#This Row],[Amount]]="","",tblLines[[#This Row],[Amount]]*IFERROR(INDEX(Products!$I$4:$I$500,MATCH(tblLines[[#This Row],[Description (Product)]],Products!$B$4:$B$500,0)),frmCommRate)) -> 5993.75 | N17: =IF(tblLines[[#This Row],[Qty (Packs)]]="","",tblLines[[#This Row],[Qty (Packs)]]*tblLines[[#This Row],[Pack Wt (KG)]]) -> 5000
A18: 16 | B18: 46267 | C18: Allah Walay Traders | E18: Nakyal Ajk | F18: Farhan Khalid | G18: ZAFARANI STEAM SHORT GRAIN 25KG | H18: 50 | I18: 9000 | J18: =IFERROR(INDEX(Products!$E$4:$E$500,MATCH(tblLines[[#This Row],[Description (Product)]],Products!$B$4:$B$500,0)),"") -> 25 | K18: =IF(OR(tblLines[[#This Row],[Description (Product)]]="",tblLines[[#This Row],[Rate 40Kg]]=""),"",tblLines[[#This Row],[Rate 40Kg]]/40*tblLines[[#This Row],[Pack Wt (KG)]]) -> 5625 | L18: =IF(OR(tblLines[[#This Row],[Rate / Pack]]="",tblLines[[#This Row],[Qty (Packs)]]=""),"",ROUND(tblLines[[#This Row],[Rate / Pack]]*tblLines[[#This Row],[Qty (Packs)]],0)) -> 281250 | M18: =IF(tblLines[[#This Row],[Amount]]="","",tblLines[[#This Row],[Amount]]*IFERROR(INDEX(Products!$I$4:$I$500,MATCH(tblLines[[#This Row],[Description (Product)]],Products!$B$4:$B$500,0)),frmCommRate)) -> 984.375 | N18: =IF(tblLines[[#This Row],[Qty (Packs)]]="","",tblLines[[#This Row],[Qty (Packs)]]*tblLines[[#This Row],[Pack Wt (KG)]]) -> 1250
A19: 16 | B19: 46267 | C19: Allah Walay Traders | E19: Nakyal Ajk | F19: Farhan Khalid | G19: ZAFARANI STEAM B-1, 25KG | H19: 130 | I19: 7850 | J19: =IFERROR(INDEX(Products!$E$4:$E$500,MATCH(tblLines[[#This Row],[Description (Product)]],Products!$B$4:$B$500,0)),"") -> 25 | K19: =IF(OR(tblLines[[#This Row],[Description (Product)]]="",tblLines[[#This Row],[Rate 40Kg]]=""),"",tblLines[[#This Row],[Rate 40Kg]]/40*tblLines[[#This Row],[Pack Wt (KG)]]) -> 4906.25 | L19: =IF(OR(tblLines[[#This Row],[Rate / Pack]]="",tblLines[[#This Row],[Qty (Packs)]]=""),"",ROUND(tblLines[[#This Row],[Rate / Pack]]*tblLines[[#This Row],[Qty (Packs)]],0)) -> 637813 | M19: =IF(tblLines[[#This Row],[Amount]]="","",tblLines[[#This Row],[Amount]]*IFERROR(INDEX(Products!$I$4:$I$500,MATCH(tblLines[[#This Row],[Description (Product)]],Products!$B$4:$B$500,0)),frmCommRate)) -> 2232.3455 | N19: =IF(tblLines[[#This Row],[Qty (Packs)]]="","",tblLines[[#This Row],[Qty (Packs)]]*tblLines[[#This Row],[Pack Wt (KG)]]) -> 3250
A20: 16 | B20: 46267 | C20: Allah Walay Traders | E20: Nakyal Ajk | F20: Farhan Khalid | G20: ZAFARANI SELLA GOLDEN 25KG | H20: 50 | I20: 12900 | J20: =IFERROR(INDEX(Products!$E$4:$E$500,MATCH(tblLines[[#This Row],[Description (Product)]],Products!$B$4:$B$500,0)),"") -> 25 | K20: =IF(OR(tblLines[[#This Row],[Description (Product)]]="",tblLines[[#This Row],[Rate 40Kg]]=""),"",tblLines[[#This Row],[Rate 40Kg]]/40*tblLines[[#This Row],[Pack Wt (KG)]]) -> 8062.5 | L20: =IF(OR(tblLines[[#This Row],[Rate / Pack]]="",tblLines[[#This Row],[Qty (Packs)]]=""),"",ROUND(tblLines[[#This Row],[Rate / Pack]]*tblLines[[#This Row],[Qty (Packs)]],0)) -> 403125 | M20: =IF(tblLines[[#This Row],[Amount]]="","",tblLines[[#This Row],[Amount]]*IFERROR(INDEX(Products!$I$4:$I$500,MATCH(tblLines[[#This Row],[Description (Product)]],Products!$B$4:$B$500,0)),frmCommRate)) -> 1410.9375 | N20: =IF(tblLines[[#This Row],[Qty (Packs)]]="","",tblLines[[#This Row],[Qty (Packs)]]*tblLines[[#This Row],[Pack Wt (KG)]]) -> 1250
A21: 16 | B21: 46267 | C21: Allah Walay Traders | E21: Nakyal Ajk | F21: Farhan Khalid | G21: ZAFARANI STEAM B-2, 25KG | H21: 130 | I21: 6050 | J21: =IFERROR(INDEX(Products!$E$4:$E$500,MATCH(tblLines[[#This Row],[Description (Product)]],Products!$B$4:$B$500,0)),"") -> 25 | K21: =IF(OR(tblLines[[#This Row],[Description (Product)]]="",tblLines[[#This Row],[Rate 40Kg]]=""),"",tblLines[[#This Row],[Rate 40Kg]]/40*tblLines[[#This Row],[Pack Wt (KG)]]) -> 3781.25 | L21: =IF(OR(tblLines[[#This Row],[Rate / Pack]]="",tblLines[[#This Row],[Qty (Packs)]]=""),"",ROUND(tblLines[[#This Row],[Rate / Pack]]*tblLines[[#This Row],[Qty (Packs)]],0)) -> 491563 | M21: =IF(tblLines[[#This Row],[Amount]]="","",tblLines[[#This Row],[Amount]]*IFERROR(INDEX(Products!$I$4:$I$500,MATCH(tblLines[[#This Row],[Description (Product)]],Products!$B$4:$B$500,0)),frmCommRate)) -> 1720.4705 | N21: =IF(tblLines[[#This Row],[Qty (Packs)]]="","",tblLines[[#This Row],[Qty (Packs)]]*tblLines[[#This Row],[Pack Wt (KG)]]) -> 3250
A22: 16 | B22: 46267 | C22: Allah Walay Traders | E22: Nakyal Ajk | F22: Farhan Khalid | G22: ZAFARANI STEAM SHADMANI 25KG | H22: 50 | I22: 9900 | J22: =IFERROR(INDEX(Products!$E$4:$E$500,MATCH(tblLines[[#This Row],[Description (Product)]],Products!$B$4:$B$500,0)),"") -> 25 | K22: =IF(OR(tblLines[[#This Row],[Description (Product)]]="",tblLines[[#This Row],[Rate 40Kg]]=""),"",tblLines[[#This Row],[Rate 40Kg]]/40*tblLines[[#This Row],[Pack Wt (KG)]]) -> 6187.5 | L22: =IF(OR(tblLines[[#This Row],[Rate / Pack]]="",tblLines[[#This Row],[Qty (Packs)]]=""),"",ROUND(tblLines[[#This Row],[Rate / Pack]]*tblLines[[#This Row],[Qty (Packs)]],0)) -> 309375 | M22: =IF(tblLines[[#This Row],[Amount]]="","",tblLines[[#This Row],[Amount]]*IFERROR(INDEX(Products!$I$4:$I$500,MATCH(tblLines[[#This Row],[Description (Product)]],Products!$B$4:$B$500,0)),frmCommRate)) -> 1082.8125 | N22: =IF(tblLines[[#This Row],[Qty (Packs)]]="","",tblLines[[#This Row],[Qty (Packs)]]*tblLines[[#This Row],[Pack Wt (KG)]]) -> 1250
... A65: 90 | B65: 46273 | C65: Sheikh Traders | E65: Lalamusa | F65: Farhan Khalid | G65: MASAR SABIT 25KG | H65: 10 | I65: 8150 | J65: =IFERROR(INDEX(Products!$E$4:$E$500,MATCH(tblLines[[#This Row],[Description (Product)]],Products!$B$4:$B$500,0)),"") -> 25 | K65: =IF(OR(tblLines[[#This Row],[Description (Product)]]="",tblLines[[#This Row],[Rate 40Kg]]=""),"",tblLines[[#This Row],[Rate 40Kg]]/40*tblLines[[#This Row],[Pack Wt (KG)]]) -> 5093.75 | L65: =IF(OR(tblLines[[#This Row],[Rate / Pack]]="",tblLines[[#This Row],[Qty (Packs)]]=""),"",ROUND(tblLines[[#This Row],[Rate / Pack]]*tblLines[[#This Row],[Qty (Packs)]],0)) -> 50938 | M65: =IF(tblLines[[#This Row],[Amount]]="","",tblLines[[#This Row],[Amount]]*IFERROR(INDEX(Products!$I$4:$I$500,MATCH(tblLines[[#This Row],[Description (Product)]],Products!$B$4:$B$500,0)),frmCommRate)) -> 178.283 | N65: =IF(tblLines[[#This Row],[Qty (Packs)]]="","",tblLines[[#This Row],[Qty (Packs)]]*tblLines[[#This Row],[Pack Wt (KG)]]) -> 250
A66: 53 | B66: 46270 | C66: Pak Rice Traders | D66: M Zaman Kotli | E66: Dina | F66: Arslan Ahmed Dar | G66: ZAFARANI STEAM PLATINUM 25KG | H66: 550 | I66: 13500 | J66: =IFERROR(INDEX(Products!$E$4:$E$500,MATCH(tblLines[[#This Row],[Description (Product)]],Products!$B$4:$B$500,0)),"") -> 25 | K66: =IF(OR(tblLines[[#This Row],[Description (Product)]]="",tblLines[[#This Row],[Rate 40Kg]]=""),"",tblLines[[#This Row],[Rate 40Kg]]/40*tblLines[[#This Row],[Pack Wt (KG)]]) -> 8437.5 | L66: =IF(OR(tblLines[[#This Row],[Rate / Pack]]="",tblLines[[#This Row],[Qty (Packs)]]=""),"",ROUND(tblLines[[#This Row],[Rate / Pack]]*tblLines[[#This Row],[Qty (Packs)]],0)) -> 4640625 | M66: =IF(tblLines[[#This Row],[Amount]]="","",tblLines[[#This Row],[Amount]]*IFERROR(INDEX(Products!$I$4:$I$500,MATCH(tblLines[[#This Row],[Description (Product)]],Products!$B$4:$B$500,0)),frmCommRate)) -> 16242.188 | N66: =IF(tblLines[[#This Row],[Qty (Packs)]]="","",tblLines[[#This Row],[Qty (Packs)]]*tblLines[[#This Row],[Pack Wt (KG)]]) -> 13750
A67: 53 | B67: 46270 | C67: Pak Rice Traders | D67: M Zaman Kotli | E67: Dina | F67: Arslan Ahmed Dar | G67: ZAFARANI STEAM B-1, 25KG | H67: 200 | I67: 7650 | J67: =IFERROR(INDEX(Products!$E$4:$E$500,MATCH(tblLines[[#This Row],[Description (Product)]],Products!$B$4:$B$500,0)),"") -> 25 | K67: =IF(OR(tblLines[[#This Row],[Description (Product)]]="",tblLines[[#This Row],[Rate 40Kg]]=""),"",tblLines[[#This Row],[Rate 40Kg]]/40*tblLines[[#This Row],[Pack Wt (KG)]]) -> 4781.25 | L67: =IF(OR(tblLines[[#This Row],[Rate / Pack]]="",tblLines[[#This Row],[Qty (Packs)]]=""),"",ROUND(tblLines[[#This Row],[Rate / Pack]]*tblLines[[#This Row],[Qty (Packs)]],0)) -> 956250 | M67: =IF(tblLines[[#This Row],[Amount]]="","",tblLines[[#This Row],[Amount]]*IFERROR(INDEX(Products!$I$4:$I$500,MATCH(tblLines[[#This Row],[Description (Product)]],Products!$B$4:$B$500,0)),frmCommRate)) -> 3346.875 | N67: =IF(tblLines[[#This Row],[Qty (Packs)]]="","",tblLines[[#This Row],[Qty (Packs)]]*tblLines[[#This Row],[Pack Wt (KG)]]) -> 5000
A68: 67 | B68: 46272 | C68: Shalimar Traders | E68: Gilgit | F68: Farhan Khalid | G68: ZAFARANI STEAM B-1, 25KG | H68: 300 | I68: 7850 | J68: =IFERROR(INDEX(Products!$E$4:$E$500,MATCH(tblLines[[#This Row],[Description (Product)]],Products!$B$4:$B$500,0)),"") -> 25 | K68: =IF(OR(tblLines[[#This Row],[Description (Product)]]="",tblLines[[#This Row],[Rate 40Kg]]=""),"",tblLines[[#This Row],[Rate 40Kg]]/40*tblLines[[#This Row],[Pack Wt (KG)]]) -> 4906.25 | L68: =IF(OR(tblLines[[#This Row],[Rate / Pack]]="",tblLines[[#This Row],[Qty (Packs)]]=""),"",ROUND(tblLines[[#This Row],[Rate / Pack]]*tblLines[[#This Row],[Qty (Packs)]],0)) -> 1471875 | M68: =IF(tblLines[[#This Row],[Amount]]="","",tblLines[[#This Row],[Amount]]*IFERROR(INDEX(Products!$I$4:$I$500,MATCH(tblLines[[#This Row],[Description (Product)]],Products!$B$4:$B$500,0)),frmCommRate)) -> 5151.5625 | N68: =IF(tblLines[[#This Row],[Qty (Packs)]]="","",tblLines[[#This Row],[Qty (Packs)]]*tblLines[[#This Row],[Pack Wt (KG)]]) -> 7500
A69: 67 | B69: 46272 | C69: Shalimar Traders | E69: Gilgit | F69: Farhan Khalid | G69: ZAFARANI STEAM PLATINUM 25KG | H69: 260 | I69: 13500 | J69: =IFERROR(INDEX(Products!$E$4:$E$500,MATCH(tblLines[[#This Row],[Description (Product)]],Products!$B$4:$B$500,0)),"") -> 25 | K69: =IF(OR(tblLines[[#This Row],[Description (Product)]]="",tblLines[[#This Row],[Rate 40Kg]]=""),"",tblLines[[#This Row],[Rate 40Kg]]/40*tblLines[[#This Row],[Pack Wt (KG)]]) -> 8437.5 | L69: =IF(OR(tblLines[[#This Row],[Rate / Pack]]="",tblLines[[#This Row],[Qty (Packs)]]=""),"",ROUND(tblLines[[#This Row],[Rate / Pack]]*tblLines[[#This Row],[Qty (Packs)]],0)) -> 2193750 | M69: =IF(tblLines[[#This Row],[Amount]]="","",tblLines[[#This Row],[Amount]]*IFERROR(INDEX(Products!$I$4:$I$500,MATCH(tblLines[[#This Row],[Description (Product)]],Products!$B$4:$B$500,0)),frmCommRate)) -> 7678.125 | N69: =IF(tblLines[[#This Row],[Qty (Packs)]]="","",tblLines[[#This Row],[Qty (Packs)]]*tblLines[[#This Row],[Pack Wt (KG)]]) -> 6500
A70: 67 | B70: 46272 | C70: Shalimar Traders | E70: Gilgit | F70: Farhan Khalid | G70: ZAFARANI SELLA GOLDEN 25KG | H70: 200 | I70: 12350 | J70: =IFERROR(INDEX(Products!$E$4:$E$500,MATCH(tblLines[[#This Row],[Description (Product)]],Products!$B$4:$B$500,0)),"") -> 25 | K70: =IF(OR(tblLines[[#This Row],[Description (Product)]]="",tblLines[[#This Row],[Rate 40Kg]]=""),"",tblLines[[#This Row],[Rate 40Kg]]/40*tblLines[[#This Row],[Pack Wt (KG)]]) -> 7718.75 | L70: =IF(OR(tblLines[[#This Row],[Rate / Pack]]="",tblLines[[#This Row],[Qty (Packs)]]=""),"",ROUND(tblLines[[#This Row],[Rate / Pack]]*tblLines[[#This Row],[Qty (Packs)]],0)) -> 1543750 | M70: =IF(tblLines[[#This Row],[Amount]]="","",tblLines[[#This Row],[Amount]]*IFERROR(INDEX(Products!$I$4:$I$500,MATCH(tblLines[[#This Row],[Description (Product)]],Products!$B$4:$B$500,0)),frmCommRate)) -> 5403.125 | N70: =IF(tblLines[[#This Row],[Qty (Packs)]]="","",tblLines[[#This Row],[Qty (Packs)]]*tblLines[[#This Row],[Pack Wt (KG)]]) -> 5000
A71: 67 | B71: 46272 | C71: Shalimar Traders | E71: Gilgit | F71: Farhan Khalid | G71: ZAFARANI STEAM B-2, 25KG | H71: 200 | I71: 6050 | J71: =IFERROR(INDEX(Products!$E$4:$E$500,MATCH(tblLines[[#This Row],[Description (Product)]],Products!$B$4:$B$500,0)),"") -> 25 | K71: =IF(OR(tblLines[[#This Row],[Description (Product)]]="",tblLines[[#This Row],[Rate 40Kg]]=""),"",tblLines[[#This Row],[Rate 40Kg]]/40*tblLines[[#This Row],[Pack Wt (KG)]]) -> 3781.25 | L71: =IF(OR(tblLines[[#This Row],[Rate / Pack]]="",tblLines[[#This Row],[Qty (Packs)]]=""),"",ROUND(tblLines[[#This Row],[Rate / Pack]]*tblLines[[#This Row],[Qty (Packs)]],0)) -> 756250 | M71: =IF(tblLines[[#This Row],[Amount]]="","",tblLines[[#This Row],[Amount]]*IFERROR(INDEX(Products!$I$4:$I$500,MATCH(tblLines[[#This Row],[Description (Product)]],Products!$B$4:$B$500,0)),frmCommRate)) -> 2646.875 | N71: =IF(tblLines[[#This Row],[Qty (Packs)]]="","",tblLines[[#This Row],[Qty (Packs)]]*tblLines[[#This Row],[Pack Wt (KG)]]) -> 5000
A72: 68 | B72: 46272 | C72: Shalimar Traders | E72: Gilgit | F72: Farhan Khalid | G72: ZAFARANI LOBIA PINTO 25KG | H72: 480 | I72: 12000 | J72: =IFERROR(INDEX(Products!$E$4:$E$500,MATCH(tblLines[[#This Row],[Description (Product)]],Products!$B$4:$B$500,0)),"") -> 25 | K72: =IF(OR(tblLines[[#This Row],[Description (Product)]]="",tblLines[[#This Row],[Rate 40Kg]]=""),"",tblLines[[#This Row],[Rate 40Kg]]/40*tblLines[[#This Row],[Pack Wt (KG)]]) -> 7500 | L72: =IF(OR(tblLines[[#This Row],[Rate / Pack]]="",tblLines[[#This Row],[Qty (Packs)]]=""),"",ROUND(tblLines[[#This Row],[Rate / Pack]]*tblLines[[#This Row],[Qty (Packs)]],0)) -> 3600000 | M72: =IF(tblLines[[#This Row],[Amount]]="","",tblLines[[#This Row],[Amount]]*IFERROR(INDEX(Products!$I$4:$I$500,MATCH(tblLines[[#This Row],[Description (Product)]],Products!$B$4:$B$500,0)),frmCommRate)) -> 12600 | N72: =IF(tblLines[[#This Row],[Qty (Packs)]]="","",tblLines[[#This Row],[Qty (Packs)]]*tblLines[[#This Row],[Pack Wt (KG)]]) -> 12000
A73: 107 | B73: 46274 | C73: Allah Walay Traders | E73: Nakyal Ajk | F73: Farhan Khalid | G73: ZAFARANI STEAM GOLD 25KG | H73: 50 | I73: 12500 | J73: =IFERROR(INDEX(Products!$E$4:$E$500,MATCH(tblLines[[#This Row],[Description (Product)]],Products!$B$4:$B$500,0)),"") -> 25 | K73: =IF(OR(tblLines[[#This Row],[Description (Product)]]="",tblLines[[#This Row],[Rate 40Kg]]=""),"",tblLines[[#This Row],[Rate 40Kg]]/40*tblLines[[#This Row],[Pack Wt (KG)]]) -> 7812.5 | L73: =IF(OR(tblLines[[#This Row],[Rate / Pack]]="",tblLines[[#This Row],[Qty (Packs)]]=""),"",ROUND(tblLines[[#This Row],[Rate / Pack]]*tblLines[[#This Row],[Qty (Packs)]],0)) -> 390625 | M73: =IF(tblLines[[#This Row],[Amount]]="","",tblLines[[#This Row],[Amount]]*IFERROR(INDEX(Products!$I$4:$I$500,MATCH(tblLines[[#This Row],[Description (Product)]],Products!$B$4:$B$500,0)),frmCommRate)) -> 1367.1875 | N73: =IF(tblLines[[#This Row],[Qty (Packs)]]="","",tblLines[[#This Row],[Qty (Packs)]]*tblLines[[#This Row],[Pack Wt (KG)]]) -> 1250
A74: 107 | B74: 46274 | C74: Allah Walay Traders | E74: Nakyal Ajk | F74: Farhan Khalid | G74: ZAFARANI STEAM B-2, 25KG | H74: 100 | I74: 5900 | J74: =IFERROR(INDEX(Products!$E$4:$E$500,MATCH(tblLines[[#This Row],[Description (Product)]],Products!$B$4:$B$500,0)),"") -> 25 | K74: =IF(OR(tblLines[[#This Row],[Description (Product)]]="",tblLines[[#This Row],[Rate 40Kg]]=""),"",tblLines[[#This Row],[Rate 40Kg]]/40*tblLines[[#This Row],[Pack Wt (KG)]]) -> 3687.5 | L74: =IF(OR(tblLines[[#This Row],[Rate / Pack]]="",tblLines[[#This Row],[Qty (Packs)]]=""),"",ROUND(tblLines[[#This Row],[Rate / Pack]]*tblLines[[#This Row],[Qty (Packs)]],0)) -> 368750 | M74: =IF(tblLines[[#This Row],[Amount]]="","",tblLines[[#This Row],[Amount]]*IFERROR(INDEX(Products!$I$4:$I$500,MATCH(tblLines[[#This Row],[Description (Product)]],Products!$B$4:$B$500,0)),frmCommRate)) -> 1290.625 | N74: =IF(tblLines[[#This Row],[Qty (Packs)]]="","",tblLines[[#This Row],[Qty (Packs)]]*tblLines[[#This Row],[Pack Wt (KG)]]) -> 2500
A75: 107 | B75: 46274 | C75: Allah Walay Traders | E75: Nakyal Ajk | F75: Farhan Khalid | G75: ZAFARANI STEAM PLATINUM 25KG | H75: 340 | I75: 13300 | J75: =IFERROR(INDEX(Products!$E$4:$E$500,MATCH(tblLines[[#This Row],[Description (Product)]],Products!$B$4:$B$500,0)),"") -> 25 | K75: =IF(OR(tblLines[[#This Row],[Description (Product)]]="",tblLines[[#This Row],[Rate 40Kg]]=""),"",tblLines[[#This Row],[Rate 40Kg]]/40*tblLines[[#This Row],[Pack Wt (KG)]]) -> 8312.5 | L75: =IF(OR(tblLines[[#This Row],[Rate / Pack]]="",tblLines[[#This Row],[Qty (Packs)]]=""),"",ROUND(tblLines[[#This Row],[Rate / Pack]]*tblLines[[#This Row],[Qty (Packs)]],0)) -> 2826250 | M75: =IF(tblLines[[#This Row],[Amount]]="","",tblLines[[#This Row],[Amount]]*IFERROR(INDEX(Products!$I$4:$I$500,MATCH(tblLines[[#This Row],[Description (Product)]],Products!$B$4:$B$500,0)),frmCommRate)) -> 9891.875 | N75: =IF(tblLines[[#This Row],[Qty (Packs)]]="","",tblLines[[#This Row],[Qty (Packs)]]*tblLines[[#This Row],[Pack Wt (KG)]]) -> 8500
A76: 107 | B76: 46274 | C76: Allah Walay Traders | E76: Nakyal Ajk | F76: Farhan Khalid | G76: ZAFARANI SUTRANGI 25KG | H76: 50 | I76: 10600 | J76: =IFERROR(INDEX(Products!$E$4:$E$500,MATCH(tblLines[[#This Row],[Description (Product)]],Products!$B$4:$B$500,0)),"") -> 25 | K76: =IF(OR(tblLines[[#This Row],[Description (Product)]]="",tblLines[[#This Row],[Rate 40Kg]]=""),"",tblLines[[#This Row],[Rate 40Kg]]/40*tblLines[[#This Row],[Pack Wt (KG)]]) -> 6625 | L76: =IF(OR(tblLines[[#This Row],[Rate / Pack]]="",tblLines[[#This Row],[Qty (Packs)]]=""),"",ROUND(tblLines[[#This Row],[Rate / Pack]]*tblLines[[#This Row],[Qty (Packs)]],0)) -> 331250 | M76: =IF(tblLines[[#This Row],[Amount]]="","",tblLines[[#This Row],[Amount]]*IFERROR(INDEX(Products!$I$4:$I$500,MATCH(tblLines[[#This Row],[Description (Product)]],Products!$B$4:$B$500,0)),frmCommRate)) -> 1159.375 | N76: =IF(tblLines[[#This Row],[Qty (Packs)]]="","",tblLines[[#This Row],[Qty (Packs)]]*tblLines[[#This Row],[Pack Wt (KG)]]) -> 1250
A77: 107 | B77: 46274 | C77: Allah Walay Traders | E77: Nakyal Ajk | F77: Farhan Khalid | G77: ZAFARANI STEAM SHADMANI 25KG | H77: 50 | I77: 9900 | J77: =IFERROR(INDEX(Products!$E$4:$E$500,MATCH(tblLines[[#This Row],[Description (Product)]],Products!$B$4:$B$500,0)),"") -> 25 | K77: =IF(OR(tblLines[[#This Row],[Description (Product)]]="",tblLines[[#This Row],[Rate 40Kg]]=""),"",tblLines[[#This Row],[Rate 40Kg]]/40*tblLines[[#This Row],[Pack Wt (KG)]]) -> 6187.5 | L77: =IF(OR(tblLines[[#This Row],[Rate / Pack]]="",tblLines[[#This Row],[Qty (Packs)]]=""),"",ROUND(tblLines[[#This Row],[Rate / Pack]]*tblLines[[#This Row],[Qty (Packs)]],0)) -> 309375 | M77: =IF(tblLines[[#This Row],[Amount]]="","",tblLines[[#This Row],[Amount]]*IFERROR(INDEX(Products!$I$4:$I$500,MATCH(tblLines[[#This Row],[Description (Product)]],Products!$B$4:$B$500,0)),frmCommRate)) -> 1082.8125 | N77: =IF(tblLines[[#This Row],[Qty (Packs)]]="","",tblLines[[#This Row],[Qty (Packs)]]*tblLines[[#This Row],[Pack Wt (KG)]]) -> 1250
A78: 107 | B78: 46274 | C78: Allah Walay Traders | E78: Nakyal Ajk | F78: Farhan Khalid | G78: ZAFARANI SELLA GOLDEN 25KG | H78: 50 | I78: 12150 | J78: =IFERROR(INDEX(Products!$E$4:$E$500,MATCH(tblLines[[#This Row],[Description (Product)]],Products!$B$4:$B$500,0)),"") -> 25 | K78: =IF(OR(tblLines[[#This Row],[Description (Product)]]="",tblLines[[#This Row],[Rate 40Kg]]=""),"",tblLines[[#This Row],[Rate 40Kg]]/40*tblLines[[#This Row],[Pack Wt (KG)]]) -> 7593.75 | L78: =IF(OR(tblLines[[#This Row],[Rate / Pack]]="",tblLines[[#This Row],[Qty (Packs)]]=""),"",ROUND(tblLines[[#This Row],[Rate / Pack]]*tblLines[[#This Row],[Qty (Packs)]],0)) -> 379688 | M78: =IF(tblLines[[#This Row],[Amount]]="","",tblLines[[#This Row],[Amount]]*IFERROR(INDEX(Products!$I$4:$I$500,MATCH(tblLines[[#This Row],[Description (Product)]],Products!$B$4:$B$500,0)),frmCommRate)) -> 1328.908 | N78: =IF(tblLines[[#This Row],[Qty (Packs)]]="","",tblLines[[#This Row],[Qty (Packs)]]*tblLines[[#This Row],[Pack Wt (KG)]]) -> 1250
A79: 110 | B79: 46274 | C79: Hamdard Traders | E79: Gahkuch | F79: Farhan Khalid | G79: ZAFARANI STEAM B-2, 25KG | H79: 75 | I79: 6050 | J79: =IFERROR(INDEX(Products!$E$4:$E$500,MATCH(tblLines[[#This Row],[Description (Product)]],Products!$B$4:$B$500,0)),"") -> 25 | K79: =IF(OR(tblLines[[#This Row],[Description (Product)]]="",tblLines[[#This Row],[Rate 40Kg]]=""),"",tblLines[[#This Row],[Rate 40Kg]]/40*tblLines[[#This Row],[Pack Wt (KG)]]) -> 3781.25 | L79: =IF(OR(tblLines[[#This Row],[Rate / Pack]]="",tblLines[[#This Row],[Qty (Packs)]]=""),"",ROUND(tblLines[[#This Row],[Rate / Pack]]*tblLines[[#This Row],[Qty (Packs)]],0)) -> 283594 | M79: =IF(tblLines[[#This Row],[Amount]]="","",tblLines[[#This Row],[Amount]]*IFERROR(INDEX(Products!$I$4:$I$500,MATCH(tblLines[[#This Row],[Description (Product)]],Products!$B$4:$B$500,0)),frmCommRate)) -> 992.579 | N79: =IF(tblLines[[#This Row],[Qty (Packs)]]="","",tblLines[[#This Row],[Qty (Packs)]]*tblLines[[#This Row],[Pack Wt (KG)]]) -> 1875
... A90: 111 | B90: 46274 | C90: Hamdard Traders | E90: Gahkuch | F90: Farhan Khalid | G90: DAAL CHANNA REGULAR 25KG | H90: 20 | I90: 9101 | J90: =IFERROR(INDEX(Products!$E$4:$E$500,MATCH(tblLines[[#This Row],[Description (Product)]],Products!$B$4:$B$500,0)),"") -> 25 | K90: =IF(OR(tblLines[[#This Row],[Description (Product)]]="",tblLines[[#This Row],[Rate 40Kg]]=""),"",tblLines[[#This Row],[Rate 40Kg]]/40*tblLines[[#This Row],[Pack Wt (KG)]]) -> 5688.125 | L90: =IF(OR(tblLines[[#This Row],[Rate / Pack]]="",tblLines[[#This Row],[Qty (Packs)]]=""),"",ROUND(tblLines[[#This Row],[Rate / Pack]]*tblLines[[#This Row],[Qty (Packs)]],0)) -> 113763 | M90: =IF(tblLines[[#This Row],[Amount]]="","",tblLines[[#This Row],[Amount]]*IFERROR(INDEX(Products!$I$4:$I$500,MATCH(tblLines[[#This Row],[Description (Product)]],Products!$B$4:$B$500,0)),frmCommRate)) -> 398.1705 | N90: =IF(tblLines[[#This Row],[Qty (Packs)]]="","",tblLines[[#This Row],[Qty (Packs)]]*tblLines[[#This Row],[Pack Wt (KG)]]) -> 500
J91: =IFERROR(INDEX(Products!$E$4:$E$500,MATCH(tblLines[[#This Row],[Description (Product)]],Products!$B$4:$B$500,0)),"") | K91: =IF(OR(tblLines[[#This Row],[Description (Product)]]="",tblLines[[#This Row],[Rate 40Kg]]=""),"",tblLines[[#This Row],[Rate 40Kg]]/40*tblLines[[#This Row],[Pack Wt (KG)]]) | L91: =IF(OR(tblLines[[#This Row],[Rate / Pack]]="",tblLines[[#This Row],[Qty (Packs)]]=""),"",ROUND(tblLines[[#This Row],[Rate / Pack]]*tblLines[[#This Row],[Qty (Packs)]],0)) | M91: =IF(tblLines[[#This Row],[Amount]]="","",tblLines[[#This Row],[Amount]]*IFERROR(INDEX(Products!$I$4:$I$500,MATCH(tblLines[[#This Row],[Description (Product)]],Products!$B$4:$B$500,0)),frmCommRate)) | N91: =IF(tblLines[[#This Row],[Qty (Packs)]]="","",tblLines[[#This Row],[Qty (Packs)]]*tblLines[[#This Row],[Pack Wt (KG)]])
J92: =IFERROR(INDEX(Products!$E$4:$E$500,MATCH(tblLines[[#This Row],[Description (Product)]],Products!$B$4:$B$500,0)),"") | K92: =IF(OR(tblLines[[#This Row],[Description (Product)]]="",tblLines[[#This Row],[Rate 40Kg]]=""),"",tblLines[[#This Row],[Rate 40Kg]]/40*tblLines[[#This Row],[Pack Wt (KG)]]) | L92: =IF(OR(tblLines[[#This Row],[Rate / Pack]]="",tblLines[[#This Row],[Qty (Packs)]]=""),"",ROUND(tblLines[[#This Row],[Rate / Pack]]*tblLines[[#This Row],[Qty (Packs)]],0)) | M92: =IF(tblLines[[#This Row],[Amount]]="","",tblLines[[#This Row],[Amount]]*IFERROR(INDEX(Products!$I$4:$I$500,MATCH(tblLines[[#This Row],[Description (Product)]],Products!$B$4:$B$500,0)),frmCommRate)) | N92: =IF(tblLines[[#This Row],[Qty (Packs)]]="","",tblLines[[#This Row],[Qty (Packs)]]*tblLines[[#This Row],[Pack Wt (KG)]])
J93: =IFERROR(INDEX(Products!$E$4:$E$500,MATCH(tblLines[[#This Row],[Description (Product)]],Products!$B$4:$B$500,0)),"") | K93: =IF(OR(tblLines[[#This Row],[Description (Product)]]="",tblLines[[#This Row],[Rate 40Kg]]=""),"",tblLines[[#This Row],[Rate 40Kg]]/40*tblLines[[#This Row],[Pack Wt (KG)]]) | L93: =IF(OR(tblLines[[#This Row],[Rate / Pack]]="",tblLines[[#This Row],[Qty (Packs)]]=""),"",ROUND(tblLines[[#This Row],[Rate / Pack]]*tblLines[[#This Row],[Qty (Packs)]],0)) | M93: =IF(tblLines[[#This Row],[Amount]]="","",tblLines[[#This Row],[Amount]]*IFERROR(INDEX(Products!$I$4:$I$500,MATCH(tblLines[[#This Row],[Description (Product)]],Products!$B$4:$B$500,0)),frmCommRate)) | N93: =IF(tblLines[[#This Row],[Qty (Packs)]]="","",tblLines[[#This Row],[Qty (Packs)]]*tblLines[[#This Row],[Pack Wt (KG)]])
J94: =IFERROR(INDEX(Products!$E$4:$E$500,MATCH(tblLines[[#This Row],[Description (Product)]],Products!$B$4:$B$500,0)),"") | K94: =IF(OR(tblLines[[#This Row],[Description (Product)]]="",tblLines[[#This Row],[Rate 40Kg]]=""),"",tblLines[[#This Row],[Rate 40Kg]]/40*tblLines[[#This Row],[Pack Wt (KG)]]) | L94: =IF(OR(tblLines[[#This Row],[Rate / Pack]]="",tblLines[[#This Row],[Qty (Packs)]]=""),"",ROUND(tblLines[[#This Row],[Rate / Pack]]*tblLines[[#This Row],[Qty (Packs)]],0)) | M94: =IF(tblLines[[#This Row],[Amount]]="","",tblLines[[#This Row],[Amount]]*IFERROR(INDEX(Products!$I$4:$I$500,MATCH(tblLines[[#This Row],[Description (Product)]],Products!$B$4:$B$500,0)),frmCommRate)) | N94: =IF(tblLines[[#This Row],[Qty (Packs)]]="","",tblLines[[#This Row],[Qty (Packs)]]*tblLines[[#This Row],[Pack Wt (KG)]])
J95: =IFERROR(INDEX(Products!$E$4:$E$500,MATCH(tblLines[[#This Row],[Description (Product)]],Products!$B$4:$B$500,0)),"") | K95: =IF(OR(tblLines[[#This Row],[Description (Product)]]="",tblLines[[#This Row],[Rate 40Kg]]=""),"",tblLines[[#This Row],[Rate 40Kg]]/40*tblLines[[#This Row],[Pack Wt (KG)]]) | L95: =IF(OR(tblLines[[#This Row],[Rate / Pack]]="",tblLines[[#This Row],[Qty (Packs)]]=""),"",ROUND(tblLines[[#This Row],[Rate / Pack]]*tblLines[[#This Row],[Qty (Packs)]],0)) | M95: =IF(tblLines[[#This Row],[Amount]]="","",tblLines[[#This Row],[Amount]]*IFERROR(INDEX(Products!$I$4:$I$500,MATCH(tblLines[[#This Row],[Description (Product)]],Products!$B$4:$B$500,0)),frmCommRate)) | N95: =IF(tblLines[[#This Row],[Qty (Packs)]]="","",tblLines[[#This Row],[Qty (Packs)]]*tblLines[[#This Row],[Pack Wt (KG)]])
A96: 4 | B96: 46266 | C96: Pak Rice Traders | D96: Sheikh Abid Gujjar Khan | E96: Dina | F96: Arslan Ahmed Dar | G96: ZAFARANI STEAM PLATINUM 25KG | H96: 200 | I96: 13500 | J96: =IFERROR(INDEX(Products!$E$4:$E$500,MATCH(tblLines[[#This Row],[Description (Product)]],Products!$B$4:$B$500,0)),"") -> 25 | K96: =IF(OR(tblLines[[#This Row],[Description (Product)]]="",tblLines[[#This Row],[Rate 40Kg]]=""),"",tblLines[[#This Row],[Rate 40Kg]]/40*tblLines[[#This Row],[Pack Wt (KG)]]) -> 8437.5 | L96: =IF(OR(tblLines[[#This Row],[Rate / Pack]]="",tblLines[[#This Row],[Qty (Packs)]]=""),"",ROUND(tblLines[[#This Row],[Rate / Pack]]*tblLines[[#This Row],[Qty (Packs)]],0)) -> 1687500 | M96: =IF(tblLines[[#This Row],[Amount]]="","",tblLines[[#This Row],[Amount]]*IFERROR(INDEX(Products!$I$4:$I$500,MATCH(tblLines[[#This Row],[Description (Product)]],Products!$B$4:$B$500,0)),frmCommRate)) -> 5906.25 | N96: =IF(tblLines[[#This Row],[Qty (Packs)]]="","",tblLines[[#This Row],[Qty (Packs)]]*tblLines[[#This Row],[Pack Wt (KG)]]) -> 5000
A97: 4 | B97: 46266 | C97: Pak Rice Traders | D97: Sheikh Abid Gujjar Khan | E97: Dina | F97: Arslan Ahmed Dar | G97: ZAFARANI STEAM PLATINUM 5KG | H97: 30 | I97: 14000 | J97: =IFERROR(INDEX(Products!$E$4:$E$500,MATCH(tblLines[[#This Row],[Description (Product)]],Products!$B$4:$B$500,0)),"") -> 40 | K97: =IF(OR(tblLines[[#This Row],[Description (Product)]]="",tblLines[[#This Row],[Rate 40Kg]]=""),"",tblLines[[#This Row],[Rate 40Kg]]/40*tblLines[[#This Row],[Pack Wt (KG)]]) -> 14000 | L97: =IF(OR(tblLines[[#This Row],[Rate / Pack]]="",tblLines[[#This Row],[Qty (Packs)]]=""),"",ROUND(tblLines[[#This Row],[Rate / Pack]]*tblLines[[#This Row],[Qty (Packs)]],0)) -> 420000 | M97: =IF(tblLines[[#This Row],[Amount]]="","",tblLines[[#This Row],[Amount]]*IFERROR(INDEX(Products!$I$4:$I$500,MATCH(tblLines[[#This Row],[Description (Product)]],Products!$B$4:$B$500,0)),frmCommRate)) -> 1470 | N97: =IF(tblLines[[#This Row],[Qty (Packs)]]="","",tblLines[[#This Row],[Qty (Packs)]]*tblLines[[#This Row],[Pack Wt (KG)]]) -> 1200
A98: 4 | B98: 46266 | C98: Pak Rice Traders | D98: Sheikh Abid Gujjar Khan | E98: Dina | F98: Arslan Ahmed Dar | G98: ZAFARANI STEAM B-1, 25KG | H98: 230 | I98: 7650 | J98: =IFERROR(INDEX(Products!$E$4:$E$500,MATCH(tblLines[[#This Row],[Description (Product)]],Products!$B$4:$B$500,0)),"") -> 25 | K98: =IF(OR(tblLines[[#This Row],[Description (Product)]]="",tblLines[[#This Row],[Rate 40Kg]]=""),"",tblLines[[#This Row],[Rate 40Kg]]/40*tblLines[[#This Row],[Pack Wt (KG)]]) -> 4781.25 | L98: =IF(OR(tblLines[[#This Row],[Rate / Pack]]="",tblLines[[#This Row],[Qty (Packs)]]=""),"",ROUND(tblLines[[#This Row],[Rate / Pack]]*tblLines[[#This Row],[Qty (Packs)]],0)) -> 1099688 | M98: =IF(tblLines[[#This Row],[Amount]]="","",tblLines[[#This Row],[Amount]]*IFERROR(INDEX(Products!$I$4:$I$500,MATCH(tblLines[[#This Row],[Description (Product)]],Products!$B$4:$B$500,0)),frmCommRate)) -> 3848.908 | N98: =IF(tblLines[[#This Row],[Qty (Packs)]]="","",tblLines[[#This Row],[Qty (Packs)]]*tblLines[[#This Row],[Pack Wt (KG)]]) -> 5750
A99: 4 | B99: 46266 | C99: Pak Rice Traders | D99: Sheikh Abid Gujjar Khan | E99: Dina | F99: Arslan Ahmed Dar | G99: ZAFARANI STEAM GOLD 25KG | H99: 100 | I99: 12500 | J99: =IFERROR(INDEX(Products!$E$4:$E$500,MATCH(tblLines[[#This Row],[Description (Product)]],Products!$B$4:$B$500,0)),"") -> 25 | K99: =IF(OR(tblLines[[#This Row],[Description (Product)]]="",tblLines[[#This Row],[Rate 40Kg]]=""),"",tblLines[[#This Row],[Rate 40Kg]]/40*tblLines[[#This Row],[Pack Wt (KG)]]) -> 7812.5 | L99: =IF(OR(tblLines[[#This Row],[Rate / Pack]]="",tblLines[[#This Row],[Qty (Packs)]]=""),"",ROUND(tblLines[[#This Row],[Rate / Pack]]*tblLines[[#This Row],[Qty (Packs)]],0)) -> 781250 | M99: =IF(tblLines[[#This Row],[Amount]]="","",tblLines[[#This Row],[Amount]]*IFERROR(INDEX(Products!$I$4:$I$500,MATCH(tblLines[[#This Row],[Description (Product)]],Products!$B$4:$B$500,0)),frmCommRate)) -> 2734.375 | N99: =IF(tblLines[[#This Row],[Qty (Packs)]]="","",tblLines[[#This Row],[Qty (Packs)]]*tblLines[[#This Row],[Pack Wt (KG)]]) -> 2500
A100: 4 | B100: 46266 | C100: Pak Rice Traders | D100: Sheikh Abid Gujjar Khan | E100: Dina | F100: Arslan Ahmed Dar | G100: ZAFARANI STEAM PLATINUM 1KG | H100: 50 | I100: 14200 | J100: =IFERROR(INDEX(Products!$E$4:$E$500,MATCH(tblLines[[#This Row],[Description (Product)]],Products!$B$4:$B$500,0)),"") -> 20 | K100: =IF(OR(tblLines[[#This Row],[Description (Product)]]="",tblLines[[#This Row],[Rate 40Kg]]=""),"",tblLines[[#This Row],[Rate 40Kg]]/40*tblLines[[#This Row],[Pack Wt (KG)]]) -> 7100 | L100: =IF(OR(tblLines[[#This Row],[Rate / Pack]]="",tblLines[[#This Row],[Qty (Packs)]]=""),"",ROUND(tblLines[[#This Row],[Rate / Pack]]*tblLines[[#This Row],[Qty (Packs)]],0)) -> 355000 | M100: =IF(tblLines[[#This Row],[Amount]]="","",tblLines[[#This Row],[Amount]]*IFERROR(INDEX(Products!$I$4:$I$500,MATCH(tblLines[[#This Row],[Description (Product)]],Products!$B$4:$B$500,0)),frmCommRate)) -> 1242.5 | N100: =IF(tblLines[[#This Row],[Qty (Packs)]]="","",tblLines[[#This Row],[Qty (Packs)]]*tblLines[[#This Row],[Pack Wt (KG)]]) -> 1000
J101: =IFERROR(INDEX(Products!$E$4:$E$500,MATCH(tblLines[[#This Row],[Description (Product)]],Products!$B$4:$B$500,0)),"") | K101: =IF(OR(tblLines[[#This Row],[Description (Product)]]="",tblLines[[#This Row],[Rate 40Kg]]=""),"",tblLines[[#This Row],[Rate 40Kg]]/40*tblLines[[#This Row],[Pack Wt (KG)]]) | L101: =IF(OR(tblLines[[#This Row],[Rate / Pack]]="",tblLines[[#This Row],[Qty (Packs)]]=""),"",ROUND(tblLines[[#This Row],[Rate / Pack]]*tblLines[[#This Row],[Qty (Packs)]],0)) | M101: =IF(tblLines[[#This Row],[Amount]]="","",tblLines[[#This Row],[Amount]]*IFERROR(INDEX(Products!$I$4:$I$500,MATCH(tblLines[[#This Row],[Description (Product)]],Products!$B$4:$B$500,0)),frmCommRate)) | N101: =IF(tblLines[[#This Row],[Qty (Packs)]]="","",tblLines[[#This Row],[Qty (Packs)]]*tblLines[[#This Row],[Pack Wt (KG)]])
J102: =IFERROR(INDEX(Products!$E$4:$E$500,MATCH(tblLines[[#This Row],[Description (Product)]],Products!$B$4:$B$500,0)),"") | K102: =IF(OR(tblLines[[#This Row],[Description (Product)]]="",tblLines[[#This Row],[Rate 40Kg]]=""),"",tblLines[[#This Row],[Rate 40Kg]]/40*tblLines[[#This Row],[Pack Wt (KG)]]) | L102: =IF(OR(tblLines[[#This Row],[Rate / Pack]]="",tblLines[[#This Row],[Qty (Packs)]]=""),"",ROUND(tblLines[[#This Row],[Rate / Pack]]*tblLines[[#This Row],[Qty (Packs)]],0)) | M102: =IF(tblLines[[#This Row],[Amount]]="","",tblLines[[#This Row],[Amount]]*IFERROR(INDEX(Products!$I$4:$I$500,MATCH(tblLines[[#This Row],[Description (Product)]],Products!$B$4:$B$500,0)),frmCommRate)) | N102: =IF(tblLines[[#This Row],[Qty (Packs)]]="","",tblLines[[#This Row],[Qty (Packs)]]*tblLines[[#This Row],[Pack Wt (KG)]])
A103: 5 | B103: 46266 | C103: Pak Rice Traders | D103: Talha & co Kotla | E103: Dina | F103: Arslan Ahmed Dar | G103: ZAFARANI SELLA GOLDEN 25KG | H103: 100 | I103: 12150 | J103: =IFERROR(INDEX(Products!$E$4:$E$500,MATCH(tblLines[[#This Row],[Description (Product)]],Products!$B$4:$B$500,0)),"") -> 25 | K103: =IF(OR(tblLines[[#This Row],[Description (Product)]]="",tblLines[[#This Row],[Rate 40Kg]]=""),"",tblLines[[#This Row],[Rate 40Kg]]/40*tblLines[[#This Row],[Pack Wt (KG)]]) -> 7593.75 | L103: =IF(OR(tblLines[[#This Row],[Rate / Pack]]="",tblLines[[#This Row],[Qty (Packs)]]=""),"",ROUND(tblLines[[#This Row],[Rate / Pack]]*tblLines[[#This Row],[Qty (Packs)]],0)) -> 759375 | M103: =IF(tblLines[[#This Row],[Amount]]="","",tblLines[[#This Row],[Amount]]*IFERROR(INDEX(Products!$I$4:$I$500,MATCH(tblLines[[#This Row],[Description (Product)]],Products!$B$4:$B$500,0)),frmCommRate)) -> 2657.8125 | N103: =IF(tblLines[[#This Row],[Qty (Packs)]]="","",tblLines[[#This Row],[Qty (Packs)]]*tblLines[[#This Row],[Pack Wt (KG)]]) -> 2500
A104: 5 | B104: 46266 | C104: Pak Rice Traders | D104: Talha & co Kotla | E104: Dina | F104: Arslan Ahmed Dar | G104: ZAFARANI STEAM PLATINUM 25KG | H104: 400 | I104: 13500 | J104: =IFERROR(INDEX(Products!$E$4:$E$500,MATCH(tblLines[[#This Row],[Description (Product)]],Products!$B$4:$B$500,0)),"") -> 25 | K104: =IF(OR(tblLines[[#This Row],[Description (Product)]]="",tblLines[[#This Row],[Rate 40Kg]]=""),"",tblLines[[#This Row],[Rate 40Kg]]/40*tblLines[[#This Row],[Pack Wt (KG)]]) -> 8437.5 | L104: =IF(OR(tblLines[[#This Row],[Rate / Pack]]="",tblLines[[#This Row],[Qty (Packs)]]=""),"",ROUND(tblLines[[#This Row],[Rate / Pack]]*tblLines[[#This Row],[Qty (Packs)]],0)) -> 3375000 | M104: =IF(tblLines[[#This Row],[Amount]]="","",tblLines[[#This Row],[Amount]]*IFERROR(INDEX(Products!$I$4:$I$500,MATCH(tblLines[[#This Row],[Description (Product)]],Products!$B$4:$B$500,0)),frmCommRate)) -> 11812.5 | N104: =IF(tblLines[[#This Row],[Qty (Packs)]]="","",tblLines[[#This Row],[Qty (Packs)]]*tblLines[[#This Row],[Pack Wt (KG)]]) -> 10000
J105: =IFERROR(INDEX(Products!$E$4:$E$500,MATCH(tblLines[[#This Row],[Description (Product)]],Products!$B$4:$B$500,0)),"") | K105: =IF(OR(tblLines[[#This Row],[Description (Product)]]="",tblLines[[#This Row],[Rate 40Kg]]=""),"",tblLines[[#This Row],[Rate 40Kg]]/40*tblLines[[#This Row],[Pack Wt (KG)]]) | L105: =IF(OR(tblLines[[#This Row],[Rate / Pack]]="",tblLines[[#This Row],[Qty (Packs)]]=""),"",ROUND(tblLines[[#This Row],[Rate / Pack]]*tblLines[[#This Row],[Qty (Packs)]],0)) | M105: =IF(tblLines[[#This Row],[Amount]]="","",tblLines[[#This Row],[Amount]]*IFERROR(INDEX(Products!$I$4:$I$500,MATCH(tblLines[[#This Row],[Description (Product)]],Products!$B$4:$B$500,0)),frmCommRate)) | N105: =IF(tblLines[[#This Row],[Qty (Packs)]]="","",tblLines[[#This Row],[Qty (Packs)]]*tblLines[[#This Row],[Pack Wt (KG)]])
J106: =IFERROR(INDEX(Products!$E$4:$E$500,MATCH(tblLines[[#This Row],[Description (Product)]],Products!$B$4:$B$500,0)),"") | K106: =IF(OR(tblLines[[#This Row],[Description (Product)]]="",tblLines[[#This Row],[Rate 40Kg]]=""),"",tblLines[[#This Row],[Rate 40Kg]]/40*tblLines[[#This Row],[Pack Wt (KG)]]) | L106: =IF(OR(tblLines[[#This Row],[Rate / Pack]]="",tblLines[[#This Row],[Qty (Packs)]]=""),"",ROUND(tblLines[[#This Row],[Rate / Pack]]*tblLines[[#This Row],[Qty (Packs)]],0)) | M106: =IF(tblLines[[#This Row],[Amount]]="","",tblLines[[#This Row],[Amount]]*IFERROR(INDEX(Products!$I$4:$I$500,MATCH(tblLines[[#This Row],[Description (Product)]],Products!$B$4:$B$500,0)),frmCommRate)) | N106: =IF(tblLines[[#This Row],[Qty (Packs)]]="","",tblLines[[#This Row],[Qty (Packs)]]*tblLines[[#This Row],[Pack Wt (KG)]])
A107: 69 | B107: 46272 | C107: Pak Rice Traders | E107: Dina | F107: Farhan Khalid | G107: ZAFARANI STEAM PLATINUM 1KG | H107: 250 | I107: 14000 | J107: =IFERROR(INDEX(Products!$E$4:$E$500,MATCH(tblLines[[#This Row],[Description (Product)]],Products!$B$4:$B$500,0)),"") -> 20 | K107: =IF(OR(tblLines[[#This Row],[Description (Product)]]="",tblLines[[#This Row],[Rate 40Kg]]=""),"",tblLines[[#This Row],[Rate 40Kg]]/40*tblLines[[#This Row],[Pack Wt (KG)]]) -> 7000 | L107: =IF(OR(tblLines[[#This Row],[Rate / Pack]]="",tblLines[[#This Row],[Qty (Packs)]]=""),"",ROUND(tblLines[[#This Row],[Rate / Pack]]*tblLines[[#This Row],[Qty (Packs)]],0)) -> 1750000 | M107: =IF(tblLines[[#This Row],[Amount]]="","",tblLines[[#This Row],[Amount]]*IFERROR(INDEX(Products!$I$4:$I$500,MATCH(tblLines[[#This Row],[Description (Product)]],Products!$B$4:$B$500,0)),frmCommRate)) -> 6125 | N107: =IF(tblLines[[#This Row],[Qty (Packs)]]="","",tblLines[[#This Row],[Qty (Packs)]]*tblLines[[#This Row],[Pack Wt (KG)]]) -> 5000
A108: 69 | B108: 46272 | C108: Pak Rice Traders | E108: Dina | F108: Farhan Khalid | G108: ZAFARANI STEAM B-1, 25KG | H108: 400 | I108: 7650 | J108: =IFERROR(INDEX(Products!$E$4:$E$500,MATCH(tblLines[[#This Row],[Description (Product)]],Products!$B$4:$B$500,0)),"") -> 25 | K108: =IF(OR(tblLines[[#This Row],[Description (Product)]]="",tblLines[[#This Row],[Rate 40Kg]]=""),"",tblLines[[#This Row],[Rate 40Kg]]/40*tblLines[[#This Row],[Pack Wt (KG)]]) -> 4781.25 | L108: =IF(OR(tblLines[[#This Row],[Rate / Pack]]="",tblLines[[#This Row],[Qty (Packs)]]=""),"",ROUND(tblLines[[#This Row],[Rate / Pack]]*tblLines[[#This Row],[Qty (Packs)]],0)) -> 1912500 | M108: =IF(tblLines[[#This Row],[Amount]]="","",tblLines[[#This Row],[Amount]]*IFERROR(INDEX(Products!$I$4:$I$500,MATCH(tblLines[[#This Row],[Description (Product)]],Products!$B$4:$B$500,0)),frmCommRate)) -> 6693.75 | N108: =IF(tblLines[[#This Row],[Qty (Packs)]]="","",tblLines[[#This Row],[Qty (Packs)]]*tblLines[[#This Row],[Pack Wt (KG)]]) -> 10000
J109: =IFERROR(INDEX(Products!$E$4:$E$500,MATCH(tblLines[[#This Row],[Description (Product)]],Products!$B$4:$B$500,0)),"") | K109: =IF(OR(tblLines[[#This Row],[Description (Product)]]="",tblLines[[#This Row],[Rate 40Kg]]=""),"",tblLines[[#This Row],[Rate 40Kg]]/40*tblLines[[#This Row],[Pack Wt (KG)]]) | L109: =IF(OR(tblLines[[#This Row],[Rate / Pack]]="",tblLines[[#This Row],[Qty (Packs)]]=""),"",ROUND(tblLines[[#This Row],[Rate / Pack]]*tblLines[[#This Row],[Qty (Packs)]],0)) | M109: =IF(tblLines[[#This Row],[Amount]]="","",tblLines[[#This Row],[Amount]]*IFERROR(INDEX(Products!$I$4:$I$500,MATCH(tblLines[[#This Row],[Description (Product)]],Products!$B$4:$B$500,0)),frmCommRate)) | N109: =IF(tblLines[[#This Row],[Qty (Packs)]]="","",tblLines[[#This Row],[Qty (Packs)]]*tblLines[[#This Row],[Pack Wt (KG)]])
J110: =IFERROR(INDEX(Products!$E$4:$E$500,MATCH(tblLines[[#This Row],[Description (Product)]],Products!$B$4:$B$500,0)),"") | K110: =IF(OR(tblLines[[#This Row],[Description (Product)]]="",tblLines[[#This Row],[Rate 40Kg]]=""),"",tblLines[[#This Row],[Rate 40Kg]]/40*tblLines[[#This Row],[Pack Wt (KG)]]) | L110: =IF(OR(tblLines[[#This Row],[Rate / Pack]]="",tblLines[[#This Row],[Qty (Packs)]]=""),"",ROUND(tblLines[[#This Row],[Rate / Pack]]*tblLines[[#This Row],[Qty (Packs)]],0)) | M110: =IF(tblLines[[#This Row],[Amount]]="","",tblLines[[#This Row],[Amount]]*IFERROR(INDEX(Products!$I$4:$I$500,MATCH(tblLines[[#This Row],[Description (Product)]],Products!$B$4:$B$500,0)),frmCommRate)) | N110: =IF(tblLines[[#This Row],[Qty (Packs)]]="","",tblLines[[#This Row],[Qty (Packs)]]*tblLines[[#This Row],[Pack Wt (KG)]])
J111: =IFERROR(INDEX(Products!$E$4:$E$500,MATCH(tblLines[[#This Row],[Description (Product)]],Products!$B$4:$B$500,0)),"") | K111: =IF(OR(tblLines[[#This Row],[Description (Product)]]="",tblLines[[#This Row],[Rate 40Kg]]=""),"",tblLines[[#This Row],[Rate 40Kg]]/40*tblLines[[#This Row],[Pack Wt (KG)]]) | L111: =IF(OR(tblLines[[#This Row],[Rate / Pack]]="",tblLines[[#This Row],[Qty (Packs)]]=""),"",ROUND(tblLines[[#This Row],[Rate / Pack]]*tblLines[[#This Row],[Qty (Packs)]],0)) | M111: =IF(tblLines[[#This Row],[Amount]]="","",tblLines[[#This Row],[Amount]]*IFERROR(INDEX(Products!$I$4:$I$500,MATCH(tblLines[[#This Row],[Description (Product)]],Products!$B$4:$B$500,0)),frmCommRate)) | N111: =IF(tblLines[[#This Row],[Qty (Packs)]]="","",tblLines[[#This Row],[Qty (Packs)]]*tblLines[[#This Row],[Pack Wt (KG)]])
J112: =IFERROR(INDEX(Products!$E$4:$E$500,MATCH(tblLines[[#This Row],[Description (Product)]],Products!$B$4:$B$500,0)),"") | K112: =IF(OR(tblLines[[#This Row],[Description (Product)]]="",tblLines[[#This Row],[Rate 40Kg]]=""),"",tblLines[[#This Row],[Rate 40Kg]]/40*tblLines[[#This Row],[Pack Wt (KG)]]) | L112: =IF(OR(tblLines[[#This Row],[Rate / Pack]]="",tblLines[[#This Row],[Qty (Packs)]]=""),"",ROUND(tblLines[[#This Row],[Rate / Pack]]*tblLines[[#This Row],[Qty (Packs)]],0)) | M112: =IF(tblLines[[#This Row],[Amount]]="","",tblLines[[#This Row],[Amount]]*IFERROR(INDEX(Products!$I$4:$I$500,MATCH(tblLines[[#This Row],[Description (Product)]],Products!$B$4:$B$500,0)),frmCommRate)) | N112: =IF(tblLines[[#This Row],[Qty (Packs)]]="","",tblLines[[#This Row],[Qty (Packs)]]*tblLines[[#This Row],[Pack Wt (KG)]])
J113: =IFERROR(INDEX(Products!$E$4:$E$500,MATCH(tblLines[[#This Row],[Description (Product)]],Products!$B$4:$B$500,0)),"") | K113: =IF(OR(tblLines[[#This Row],[Description (Product)]]="",tblLines[[#This Row],[Rate 40Kg]]=""),"",tblLines[[#This Row],[Rate 40Kg]]/40*tblLines[[#This Row],[Pack Wt (KG)]]) | L113: =IF(OR(tblLines[[#This Row],[Rate / Pack]]="",tblLines[[#This Row],[Qty (Packs)]]=""),"",ROUND(tblLines[[#This Row],[Rate / Pack]]*tblLines[[#This Row],[Qty (Packs)]],0)) | M113: =IF(tblLines[[#This Row],[Amount]]="","",tblLines[[#This Row],[Amount]]*IFERROR(INDEX(Products!$I$4:$I$500,MATCH(tblLines[[#This Row],[Description (Product)]],Products!$B$4:$B$500,0)),frmCommRate)) | N113: =IF(tblLines[[#This Row],[Qty (Packs)]]="","",tblLines[[#This Row],[Qty (Packs)]]*tblLines[[#This Row],[Pack Wt (KG)]])
A114: 70 | B114: 46272 | C114: Pak Rice Traders | D114: Sheikh Abid Gujjar Khan | E114: Dina | F114: Arslan Ahmed Dar | G114: DAAL MASH CHARI 25KG | H114: 30 | I114: 16250 | J114: =IFERROR(INDEX(Products!$E$4:$E$500,MATCH(tblLines[[#This Row],[Description (Product)]],Products!$B$4:$B$500,0)),"") -> 25 | K114: =IF(OR(tblLines[[#This Row],[Description (Product)]]="",tblLines[[#This Row],[Rate 40Kg]]=""),"",tblLines[[#This Row],[Rate 40Kg]]/40*tblLines[[#This Row],[Pack Wt (KG)]]) -> 10156.25 | L114: =IF(OR(tblLines[[#This Row],[Rate / Pack]]="",tblLines[[#This Row],[Qty (Packs)]]=""),"",ROUND(tblLines[[#This Row],[Rate / Pack]]*tblLines[[#This Row],[Qty (Packs)]],0)) -> 304688 | M114: =IF(tblLines[[#This Row],[Amount]]="","",tblLines[[#This Row],[Amount]]*IFERROR(INDEX(Products!$I$4:$I$500,MATCH(tblLines[[#This Row],[Description (Product)]],Products!$B$4:$B$500,0)),frmCommRate)) -> 1066.408 | N114: =IF(tblLines[[#This Row],[Qty (Packs)]]="","",tblLines[[#This Row],[Qty (Packs)]]*tblLines[[#This Row],[Pack Wt (KG)]]) -> 750
A115: 70 | B115: 46272 | C115: Pak Rice Traders | D115: Sheikh Abid Gujjar Khan | E115: Dina | F115: Arslan Ahmed Dar | G115: DAAL CHANNA ECONOMY 25KG | H115: 70 | I115: 8350 | J115: =IFERROR(INDEX(Products!$E$4:$E$500,MATCH(tblLines[[#This Row],[Description (Product)]],Products!$B$4:$B$500,0)),"") -> 25 | K115: =IF(OR(tblLines[[#This Row],[Description (Product)]]="",tblLines[[#This Row],[Rate 40Kg]]=""),"",tblLines[[#This Row],[Rate 40Kg]]/40*tblLines[[#This Row],[Pack Wt (KG)]]) -> 5218.75 | L115: =IF(OR(tblLines[[#This Row],[Rate / Pack]]="",tblLines[[#This Row],[Qty (Packs)]]=""),"",ROUND(tblLines[[#This Row],[Rate / Pack]]*tblLines[[#This Row],[Qty (Packs)]],0)) -> 365313 | M115: =IF(tblLines[[#This Row],[Amount]]="","",tblLines[[#This Row],[Amount]]*IFERROR(INDEX(Products!$I$4:$I$500,MATCH(tblLines[[#This Row],[Description (Product)]],Products!$B$4:$B$500,0)),frmCommRate)) -> 1278.5955 | N115: =IF(tblLines[[#This Row],[Qty (Packs)]]="","",tblLines[[#This Row],[Qty (Packs)]]*tblLines[[#This Row],[Pack Wt (KG)]]) -> 1750
A116: 70 | B116: 46272 | C116: Pak Rice Traders | D116: Sheikh Abid Gujjar Khan | E116: Dina | F116: Arslan Ahmed Dar | G116: WHITE CHANNA 8MM 25KG | H116: 60 | I116: 9100 | J116: =IFERROR(INDEX(Products!$E$4:$E$500,MATCH(tblLines[[#This Row],[Description (Product)]],Products!$B$4:$B$500,0)),"") -> 25 | K116: =IF(OR(tblLines[[#This Row],[Description (Product)]]="",tblLines[[#This Row],[Rate 40Kg]]=""),"",tblLines[[#This Row],[Rate 40Kg]]/40*tblLines[[#This Row],[Pack Wt (KG)]]) -> 5687.5 | L116: =IF(OR(tblLines[[#This Row],[Rate / Pack]]="",tblLines[[#This Row],[Qty (Packs)]]=""),"",ROUND(tblLines[[#This Row],[Rate / Pack]]*tblLines[[#This Row],[Qty (Packs)]],0)) -> 341250 | M116: =IF(tblLines[[#This Row],[Amount]]="","",tblLines[[#This Row],[Amount]]*IFERROR(INDEX(Products!$I$4:$I$500,MATCH(tblLines[[#This Row],[Description (Product)]],Products!$B$4:$B$500,0)),frmCommRate)) -> 1194.375 | N116: =IF(tblLines[[#This Row],[Qty (Packs)]]="","",tblLines[[#This Row],[Qty (Packs)]]*tblLines[[#This Row],[Pack Wt (KG)]]) -> 1500
A117: 70 | B117: 46272 | C117: Pak Rice Traders | D117: Sheikh Abid Gujjar Khan | E117: Dina | F117: Arslan Ahmed Dar | G117: DALL MASOOR 25KG | H117: 40 | I117: 8500 | J117: =IFERROR(INDEX(Products!$E$4:$E$500,MATCH(tblLines[[#This Row],[Description (Product)]],Products!$B$4:$B$500,0)),"") -> 25 | K117: =IF(OR(tblLines[[#This Row],[Description (Product)]]="",tblLines[[#This Row],[Rate 40Kg]]=""),"",tblLines[[#This Row],[Rate 40Kg]]/40*tblLines[[#This Row],[Pack Wt (KG)]]) -> 5312.5 | L117: =IF(OR(tblLines[[#This Row],[Rate / Pack]]="",tblLines[[#This Row],[Qty (Packs)]]=""),"",ROUND(tblLines[[#This Row],[Rate / Pack]]*tblLines[[#This Row],[Qty (Packs)]],0)) -> 212500 | M117: =IF(tblLines[[#This Row],[Amount]]="","",tblLines[[#This Row],[Amount]]*IFERROR(INDEX(Products!$I$4:$I$500,MATCH(tblLines[[#This Row],[Description (Product)]],Products!$B$4:$B$500,0)),frmCommRate)) -> 743.75 | N117: =IF(tblLines[[#This Row],[Qty (Packs)]]="","",tblLines[[#This Row],[Qty (Packs)]]*tblLines[[#This Row],[Pack Wt (KG)]]) -> 1000
A118: 70 | B118: 46272 | C118: Pak Rice Traders | D118: Sheikh Abid Gujjar Khan | E118: Dina | F118: Arslan Ahmed Dar | G118: DAAL CHANNA SUPREME 25KG | H118: 20 | I118: 10050 | J118: =IFERROR(INDEX(Products!$E$4:$E$500,MATCH(tblLines[[#This Row],[Description (Product)]],Products!$B$4:$B$500,0)),"") -> 25 | K118: =IF(OR(tblLines[[#This Row],[Description (Product)]]="",tblLines[[#This Row],[Rate 40Kg]]=""),"",tblLines[[#This Row],[Rate 40Kg]]/40*tblLines[[#This Row],[Pack Wt (KG)]]) -> 6281.25 | L118: =IF(OR(tblLines[[#This Row],[Rate / Pack]]="",tblLines[[#This Row],[Qty (Packs)]]=""),"",ROUND(tblLines[[#This Row],[Rate / Pack]]*tblLines[[#This Row],[Qty (Packs)]],0)) -> 125625 | M118: =IF(tblLines[[#This Row],[Amount]]="","",tblLines[[#This Row],[Amount]]*IFERROR(INDEX(Products!$I$4:$I$500,MATCH(tblLines[[#This Row],[Description (Product)]],Products!$B$4:$B$500,0)),frmCommRate)) -> 439.6875 | N118: =IF(tblLines[[#This Row],[Qty (Packs)]]="","",tblLines[[#This Row],[Qty (Packs)]]*tblLines[[#This Row],[Pack Wt (KG)]]) -> 500
J119: =IFERROR(INDEX(Products!$E$4:$E$500,MATCH(tblLines[[#This Row],[Description (Product)]],Products!$B$4:$B$500,0)),"") | K119: =IF(OR(tblLines[[#This Row],[Description (Product)]]="",tblLines[[#This Row],[Rate 40Kg]]=""),"",tblLines[[#This Row],[Rate 40Kg]]/40*tblLines[[#This Row],[Pack Wt (KG)]]) | L119: =IF(OR(tblLines[[#This Row],[Rate / Pack]]="",tblLines[[#This Row],[Qty (Packs)]]=""),"",ROUND(tblLines[[#This Row],[Rate / Pack]]*tblLines[[#This Row],[Qty (Packs)]],0)) | M119: =IF(tblLines[[#This Row],[Amount]]="","",tblLines[[#This Row],[Amount]]*IFERROR(INDEX(Products!$I$4:$I$500,MATCH(tblLines[[#This Row],[Description (Product)]],Products!$B$4:$B$500,0)),frmCommRate)) | N119: =IF(tblLines[[#This Row],[Qty (Packs)]]="","",tblLines[[#This Row],[Qty (Packs)]]*tblLines[[#This Row],[Pack Wt (KG)]])
A120: 91 | B120: 46273 | C120: Pak Rice Traders | D120: Shahmeer Traders Kharian | E120: Dina | F120: Arslan Ahmed Dar | G120: ZAFARANI STEAM PLATINUM 25KG | H120: 150 | I120: 13300 | J120: =IFERROR(INDEX(Products!$E$4:$E$500,MATCH(tblLines[[#This Row],[Description (Product)]],Products!$B$4:$B$500,0)),"") -> 25 | K120: =IF(OR(tblLines[[#This Row],[Description (Product)]]="",tblLines[[#This Row],[Rate 40Kg]]=""),"",tblLines[[#This Row],[Rate 40Kg]]/40*tblLines[[#This Row],[Pack Wt (KG)]]) -> 8312.5 | L120: =IF(OR(tblLines[[#This Row],[Rate / Pack]]="",tblLines[[#This Row],[Qty (Packs)]]=""),"",ROUND(tblLines[[#This Row],[Rate / Pack]]*tblLines[[#This Row],[Qty (Packs)]],0)) -> 1246875 | M120: =IF(tblLines[[#This Row],[Amount]]="","",tblLines[[#This Row],[Amount]]*IFERROR(INDEX(Products!$I$4:$I$500,MATCH(tblLines[[#This Row],[Description (Product)]],Products!$B$4:$B$500,0)),frmCommRate)) -> 4364.0625 | N120: =IF(tblLines[[#This Row],[Qty (Packs)]]="","",tblLines[[#This Row],[Qty (Packs)]]*tblLines[[#This Row],[Pack Wt (KG)]]) -> 3750
J121: =IFERROR(INDEX(Products!$E$4:$E$500,MATCH(tblLines[[#This Row],[Description (Product)]],Products!$B$4:$B$500,0)),"") | K121: =IF(OR(tblLines[[#This Row],[Description (Product)]]="",tblLines[[#This Row],[Rate 40Kg]]=""),"",tblLines[[#This Row],[Rate 40Kg]]/40*tblLines[[#This Row],[Pack Wt (KG)]]) | L121: =IF(OR(tblLines[[#This Row],[Rate / Pack]]="",tblLines[[#This Row],[Qty (Packs)]]=""),"",ROUND(tblLines[[#This Row],[Rate / Pack]]*tblLines[[#This Row],[Qty (Packs)]],0)) | M121: =IF(tblLines[[#This Row],[Amount]]="","",tblLines[[#This Row],[Amount]]*IFERROR(INDEX(Products!$I$4:$I$500,MATCH(tblLines[[#This Row],[Description (Product)]],Products!$B$4:$B$500,0)),frmCommRate)) | N121: =IF(tblLines[[#This Row],[Qty (Packs)]]="","",tblLines[[#This Row],[Qty (Packs)]]*tblLines[[#This Row],[Pack Wt (KG)]])
J122: =IFERROR(INDEX(Products!$E$4:$E$500,MATCH(tblLines[[#This Row],[Description (Product)]],Products!$B$4:$B$500,0)),"") | K122: =IF(OR(tblLines[[#This Row],[Description (Product)]]="",tblLines[[#This Row],[Rate 40Kg]]=""),"",tblLines[[#This Row],[Rate 40Kg]]/40*tblLines[[#This Row],[Pack Wt (KG)]]) | L122: =IF(OR(tblLines[[#This Row],[Rate / Pack]]="",tblLines[[#This Row],[Qty (Packs)]]=""),"",ROUND(tblLines[[#This Row],[Rate / Pack]]*tblLines[[#This Row],[Qty (Packs)]],0)) | M122: =IF(tblLines[[#This Row],[Amount]]="","",tblLines[[#This Row],[Amount]]*IFERROR(INDEX(Products!$I$4:$I$500,MATCH(tblLines[[#This Row],[Description (Product)]],Products!$B$4:$B$500,0)),frmCommRate)) | N122: =IF(tblLines[[#This Row],[Qty (Packs)]]="","",tblLines[[#This Row],[Qty (Packs)]]*tblLines[[#This Row],[Pack Wt (KG)]])
J123: =IFERROR(INDEX(Products!$E$4:$E$500,MATCH(tblLines[[#This Row],[Description (Product)]],Products!$B$4:$B$500,0)),"") | K123: =IF(OR(tblLines[[#This Row],[Description (Product)]]="",tblLines[[#This Row],[Rate 40Kg]]=""),"",tblLines[[#This Row],[Rate 40Kg]]/40*tblLines[[#This Row],[Pack Wt (KG)]]) | L123: =IF(OR(tblLines[[#This Row],[Rate / Pack]]="",tblLines[[#This Row],[Qty (Packs)]]=""),"",ROUND(tblLines[[#This Row],[Rate / Pack]]*tblLines[[#This Row],[Qty (Packs)]],0)) | M123: =IF(tblLines[[#This Row],[Amount]]="","",tblLines[[#This Row],[Amount]]*IFERROR(INDEX(Products!$I$4:$I$500,MATCH(tblLines[[#This Row],[Description (Product)]],Products!$B$4:$B$500,0)),frmCommRate)) | N123: =IF(tblLines[[#This Row],[Qty (Packs)]]="","",tblLines[[#This Row],[Qty (Packs)]]*tblLines[[#This Row],[Pack Wt (KG)]])
J124: =IFERROR(INDEX(Products!$E$4:$E$500,MATCH(tblLines[[#This Row],[Description (Product)]],Products!$B$4:$B$500,0)),"") | K124: =IF(OR(tblLines[[#This Row],[Description (Product)]]="",tblLines[[#This Row],[Rate 40Kg]]=""),"",tblLines[[#This Row],[Rate 40Kg]]/40*tblLines[[#This Row],[Pack Wt (KG)]]) | L124: =IF(OR(tblLines[[#This Row],[Rate / Pack]]="",tblLines[[#This Row],[Qty (Packs)]]=""),"",ROUND(tblLines[[#This Row],[Rate / Pack]]*tblLines[[#This Row],[Qty (Packs)]],0)) | M124: =IF(tblLines[[#This Row],[Amount]]="","",tblLines[[#This Row],[Amount]]*IFERROR(INDEX(Products!$I$4:$I$500,MATCH(tblLines[[#This Row],[Description (Product)]],Products!$B$4:$B$500,0)),frmCommRate)) | N124: =IF(tblLines[[#This Row],[Qty (Packs)]]="","",tblLines[[#This Row],[Qty (Packs)]]*tblLines[[#This Row],[Pack Wt (KG)]])
A125: 92 | B125: 46273 | C125: Pak Rice Traders | D125: Iftikhar Traders | E125: Dina | F125: Arslan Ahmed Dar | G125: ZAFARANI STEAM PLATINUM 1KG | H125: 10 | I125: 14200 | J125: =IFERROR(INDEX(Products!$E$4:$E$500,MATCH(tblLines[[#This Row],[Description (Product)]],Products!$B$4:$B$500,0)),"") -> 20 | K125: =IF(OR(tblLines[[#This Row],[Description (Product)]]="",tblLines[[#This Row],[Rate 40Kg]]=""),"",tblLines[[#This Row],[Rate 40Kg]]/40*tblLines[[#This Row],[Pack Wt (KG)]]) -> 7100 | L125: =IF(OR(tblLines[[#This Row],[Rate / Pack]]="",tblLines[[#This Row],[Qty (Packs)]]=""),"",ROUND(tblLines[[#This Row],[Rate / Pack]]*tblLines[[#This Row],[Qty (Packs)]],0)) -> 71000 | M125: =IF(tblLines[[#This Row],[Amount]]="","",tblLines[[#This Row],[Amount]]*IFERROR(INDEX(Products!$I$4:$I$500,MATCH(tblLines[[#This Row],[Description (Product)]],Products!$B$4:$B$500,0)),frmCommRate)) -> 248.5 | N125: =IF(tblLines[[#This Row],[Qty (Packs)]]="","",tblLines[[#This Row],[Qty (Packs)]]*tblLines[[#This Row],[Pack Wt (KG)]]) -> 200
A126: 92 | B126: 46273 | C126: Pak Rice Traders | D126: Iftikhar Traders | E126: Dina | F126: Arslan Ahmed Dar | G126: ZAFARANI STEAM PLATINUM 25KG | H126: 490 | I126: 13500 | J126: =IFERROR(INDEX(Products!$E$4:$E$500,MATCH(tblLines[[#This Row],[Description (Product)]],Products!$B$4:$B$500,0)),"") -> 25 | K126: =IF(OR(tblLines[[#This Row],[Description (Product)]]="",tblLines[[#This Row],[Rate 40Kg]]=""),"",tblLines[[#This Row],[Rate 40Kg]]/40*tblLines[[#This Row],[Pack Wt (KG)]]) -> 8437.5 | L126: =IF(OR(tblLines[[#This Row],[Rate / Pack]]="",tblLines[[#This Row],[Qty (Packs)]]=""),"",ROUND(tblLines[[#This Row],[Rate / Pack]]*tblLines[[#This Row],[Qty (Packs)]],0)) -> 4134375 | M126: =IF(tblLines[[#This Row],[Amount]]="","",tblLines[[#This Row],[Amount]]*IFERROR(INDEX(Products!$I$4:$I$500,MATCH(tblLines[[#This Row],[Description (Product)]],Products!$B$4:$B$500,0)),frmCommRate)) -> 14470.312 | N126: =IF(tblLines[[#This Row],[Qty (Packs)]]="","",tblLines[[#This Row],[Qty (Packs)]]*tblLines[[#This Row],[Pack Wt (KG)]]) -> 12250
A127: 92 | B127: 46273 | C127: Pak Rice Traders | D127: Iftikhar Traders | E127: Dina | F127: Arslan Ahmed Dar | G127: ZAFARANI STEAM PLATINUM 5KG | H127: 30 | I127: 14000 | J127: =IFERROR(INDEX(Products!$E$4:$E$500,MATCH(tblLines[[#This Row],[Description (Product)]],Products!$B$4:$B$500,0)),"") -> 40 | K127: =IF(OR(tblLines[[#This Row],[Description (Product)]]="",tblLines[[#This Row],[Rate 40Kg]]=""),"",tblLines[[#This Row],[Rate 40Kg]]/40*tblLines[[#This Row],[Pack Wt (KG)]]) -> 14000 | L127: =IF(OR(tblLines[[#This Row],[Rate / Pack]]="",tblLines[[#This Row],[Qty (Packs)]]=""),"",ROUND(tblLines[[#This Row],[Rate / Pack]]*tblLines[[#This Row],[Qty (Packs)]],0)) -> 420000 | M127: =IF(tblLines[[#This Row],[Amount]]="","",tblLines[[#This Row],[Amount]]*IFERROR(INDEX(Products!$I$4:$I$500,MATCH(tblLines[[#This Row],[Description (Product)]],Products!$B$4:$B$500,0)),frmCommRate)) -> 1470 | N127: =IF(tblLines[[#This Row],[Qty (Packs)]]="","",tblLines[[#This Row],[Qty (Packs)]]*tblLines[[#This Row],[Pack Wt (KG)]]) -> 1200
A128: 92 | B128: 46273 | C128: Pak Rice Traders | D128: Iftikhar Traders | E128: Dina | F128: Arslan Ahmed Dar | G128: ZAFARANI SELLA GOLDEN 25KG | H128: 110 | I128: 12150 | J128: =IFERROR(INDEX(Products!$E$4:$E$500,MATCH(tblLines[[#This Row],[Description (Product)]],Products!$B$4:$B$500,0)),"") -> 25 | K128: =IF(OR(tblLines[[#This Row],[Description (Product)]]="",tblLines[[#This Row],[Rate 40Kg]]=""),"",tblLines[[#This Row],[Rate 40Kg]]/40*tblLines[[#This Row],[Pack Wt (KG)]]) -> 7593.75 | L128: =IF(OR(tblLines[[#This Row],[Rate / Pack]]="",tblLines[[#This Row],[Qty (Packs)]]=""),"",ROUND(tblLines[[#This Row],[Rate / Pack]]*tblLines[[#This Row],[Qty (Packs)]],0)) -> 835313 | M128: =IF(tblLines[[#This Row],[Amount]]="","",tblLines[[#This Row],[Amount]]*IFERROR(INDEX(Products!$I$4:$I$500,MATCH(tblLines[[#This Row],[Description (Product)]],Products!$B$4:$B$500,0)),frmCommRate)) -> 2923.5955 | N128: =IF(tblLines[[#This Row],[Qty (Packs)]]="","",tblLines[[#This Row],[Qty (Packs)]]*tblLines[[#This Row],[Pack Wt (KG)]]) -> 2750
J129: =IFERROR(INDEX(Products!$E$4:$E$500,MATCH(tblLines[[#This Row],[Description (Product)]],Products!$B$4:$B$500,0)),"") | K129: =IF(OR(tblLines[[#This Row],[Description (Product)]]="",tblLines[[#This Row],[Rate 40Kg]]=""),"",tblLines[[#This Row],[Rate 40Kg]]/40*tblLines[[#This Row],[Pack Wt (KG)]]) | L129: =IF(OR(tblLines[[#This Row],[Rate / Pack]]="",tblLines[[#This Row],[Qty (Packs)]]=""),"",ROUND(tblLines[[#This Row],[Rate / Pack]]*tblLines[[#This Row],[Qty (Packs)]],0)) | M129: =IF(tblLines[[#This Row],[Amount]]="","",tblLines[[#This Row],[Amount]]*IFERROR(INDEX(Products!$I$4:$I$500,MATCH(tblLines[[#This Row],[Description (Product)]],Products!$B$4:$B$500,0)),frmCommRate)) | N129: =IF(tblLines[[#This Row],[Qty (Packs)]]="","",tblLines[[#This Row],[Qty (Packs)]]*tblLines[[#This Row],[Pack Wt (KG)]])
J130: =IFERROR(INDEX(Products!$E$4:$E$500,MATCH(tblLines[[#This Row],[Description (Product)]],Products!$B$4:$B$500,0)),"") | K130: =IF(OR(tblLines[[#This Row],[Description (Product)]]="",tblLines[[#This Row],[Rate 40Kg]]=""),"",tblLines[[#This Row],[Rate 40Kg]]/40*tblLines[[#This Row],[Pack Wt (KG)]]) | L130: =IF(OR(tblLines[[#This Row],[Rate / Pack]]="",tblLines[[#This Row],[Qty (Packs)]]=""),"",ROUND(tblLines[[#This Row],[Rate / Pack]]*tblLines[[#This Row],[Qty (Packs)]],0)) | M130: =IF(tblLines[[#This Row],[Amount]]="","",tblLines[[#This Row],[Amount]]*IFERROR(INDEX(Products!$I$4:$I$500,MATCH(tblLines[[#This Row],[Description (Product)]],Products!$B$4:$B$500,0)),frmCommRate)) | N130: =IF(tblLines[[#This Row],[Qty (Packs)]]="","",tblLines[[#This Row],[Qty (Packs)]]*tblLines[[#This Row],[Pack Wt (KG)]])
J131: =IFERROR(INDEX(Products!$E$4:$E$500,MATCH(tblLines[[#This Row],[Description (Product)]],Products!$B$4:$B$500,0)),"") | K131: =IF(OR(tblLines[[#This Row],[Description (Product)]]="",tblLines[[#This Row],[Rate 40Kg]]=""),"",tblLines[[#This Row],[Rate 40Kg]]/40*tblLines[[#This Row],[Pack Wt (KG)]]) | L131: =IF(OR(tblLines[[#This Row],[Rate / Pack]]="",tblLines[[#This Row],[Qty (Packs)]]=""),"",ROUND(tblLines[[#This Row],[Rate / Pack]]*tblLines[[#This Row],[Qty (Packs)]],0)) | M131: =IF(tblLines[[#This Row],[Amount]]="","",tblLines[[#This Row],[Amount]]*IFERROR(INDEX(Products!$I$4:$I$500,MATCH(tblLines[[#This Row],[Description (Product)]],Products!$B$4:$B$500,0)),frmCommRate)) | N131: =IF(tblLines[[#This Row],[Qty (Packs)]]="","",tblLines[[#This Row],[Qty (Packs)]]*tblLines[[#This Row],[Pack Wt (KG)]])
J132: =IFERROR(INDEX(Products!$E$4:$E$500,MATCH(tblLines[[#This Row],[Description (Product)]],Products!$B$4:$B$500,0)),"") | K132: =IF(OR(tblLines[[#This Row],[Description (Product)]]="",tblLines[[#This Row],[Rate 40Kg]]=""),"",tblLines[[#This Row],[Rate 40Kg]]/40*tblLines[[#This Row],[Pack Wt (KG)]]) | L132: =IF(OR(tblLines[[#This Row],[Rate / Pack]]="",tblLines[[#This Row],[Qty (Packs)]]=""),"",ROUND(tblLines[[#This Row],[Rate / Pack]]*tblLines[[#This Row],[Qty (Packs)]],0)) | M132: =IF(tblLines[[#This Row],[Amount]]="","",tblLines[[#This Row],[Amount]]*IFERROR(INDEX(Products!$I$4:$I$500,MATCH(tblLines[[#This Row],[Description (Product)]],Products!$B$4:$B$500,0)),frmCommRate)) | N132: =IF(tblLines[[#This Row],[Qty (Packs)]]="","",tblLines[[#This Row],[Qty (Packs)]]*tblLines[[#This Row],[Pack Wt (KG)]])
J133: =IFERROR(INDEX(Products!$E$4:$E$500,MATCH(tblLines[[#This Row],[Description (Product)]],Products!$B$4:$B$500,0)),"") | K133: =IF(OR(tblLines[[#This Row],[Description (Product)]]="",tblLines[[#This Row],[Rate 40Kg]]=""),"",tblLines[[#This Row],[Rate 40Kg]]/40*tblLines[[#This Row],[Pack Wt (KG)]]) | L133: =IF(OR(tblLines[[#This Row],[Rate / Pack]]="",tblLines[[#This Row],[Qty (Packs)]]=""),"",ROUND(tblLines[[#This Row],[Rate / Pack]]*tblLines[[#This Row],[Qty (Packs)]],0)) | M133: =IF(tblLines[[#This Row],[Amount]]="","",tblLines[[#This Row],[Amount]]*IFERROR(INDEX(Products!$I$4:$I$500,MATCH(tblLines[[#This Row],[Description (Product)]],Products!$B$4:$B$500,0)),frmCommRate)) | N133: =IF(tblLines[[#This Row],[Qty (Packs)]]="","",tblLines[[#This Row],[Qty (Packs)]]*tblLines[[#This Row],[Pack Wt (KG)]])
A134: 109 | B134: 46274 | C134: Pak Rice Traders | D134: Alam Shah Traders | E134: Dina | F134: Arslan Ahmed Dar | G134: ZAFARANI STEAM EVERYDAY 25KG | H134: 50 | I134: 8300 | J134: =IFERROR(INDEX(Products!$E$4:$E$500,MATCH(tblLines[[#This Row],[Description (Product)]],Products!$B$4:$B$500,0)),"") -> 25 | K134: =IF(OR(tblLines[[#This Row],[Description (Product)]]="",tblLines[[#This Row],[Rate 40Kg]]=""),"",tblLines[[#This Row],[Rate 40Kg]]/40*tblLines[[#This Row],[Pack Wt (KG)]]) -> 5187.5 | L134: =IF(OR(tblLines[[#This Row],[Rate / Pack]]="",tblLines[[#This Row],[Qty (Packs)]]=""),"",ROUND(tblLines[[#This Row],[Rate / Pack]]*tblLines[[#This Row],[Qty (Packs)]],0)) -> 259375 | M134: =IF(tblLines[[#This Row],[Amount]]="","",tblLines[[#This Row],[Amount]]*IFERROR(INDEX(Products!$I$4:$I$500,MATCH(tblLines[[#This Row],[Description (Product)]],Products!$B$4:$B$500,0)),frmCommRate)) -> 907.8125 | N134: =IF(tblLines[[#This Row],[Qty (Packs)]]="","",tblLines[[#This Row],[Qty (Packs)]]*tblLines[[#This Row],[Pack Wt (KG)]]) -> 1250
A135: 109 | B135: 46274 | C135: Pak Rice Traders | D135: Alam Shah Traders | E135: Dina | F135: Arslan Ahmed Dar | G135: ZAFARANI STEAM B-2, 25KG | H135: 86 | I135: 5900 | J135: =IFERROR(INDEX(Products!$E$4:$E$500,MATCH(tblLines[[#This Row],[Description (Product)]],Products!$B$4:$B$500,0)),"") -> 25 | K135: =IF(OR(tblLines[[#This Row],[Description (Product)]]="",tblLines[[#This Row],[Rate 40Kg]]=""),"",tblLines[[#This Row],[Rate 40Kg]]/40*tblLines[[#This Row],[Pack Wt (KG)]]) -> 3687.5 | L135: =IF(OR(tblLines[[#This Row],[Rate / Pack]]="",tblLines[[#This Row],[Qty (Packs)]]=""),"",ROUND(tblLines[[#This Row],[Rate / Pack]]*tblLines[[#This Row],[Qty (Packs)]],0)) -> 317125 | M135: =IF(tblLines[[#This Row],[Amount]]="","",tblLines[[#This Row],[Amount]]*IFERROR(INDEX(Products!$I$4:$I$500,MATCH(tblLines[[#This Row],[Description (Product)]],Products!$B$4:$B$500,0)),frmCommRate)) -> 1109.9375 | N135: =IF(tblLines[[#This Row],[Qty (Packs)]]="","",tblLines[[#This Row],[Qty (Packs)]]*tblLines[[#This Row],[Pack Wt (KG)]]) -> 2150
A136: 109 | B136: 46274 | C136: Pak Rice Traders | D136: Alam Shah Traders | E136: Dina | F136: Arslan Ahmed Dar | G136: HAZARA B-2, 25KG | H136: 50 | I136: 4350 | J136: =IFERROR(INDEX(Products!$E$4:$E$500,MATCH(tblLines[[#This Row],[Description (Product)]],Products!$B$4:$B$500,0)),"") -> 25 | K136: =IF(OR(tblLines[[#This Row],[Description (Product)]]="",tblLines[[#This Row],[Rate 40Kg]]=""),"",tblLines[[#This Row],[Rate 40Kg]]/40*tblLines[[#This Row],[Pack Wt (KG)]]) -> 2718.75 | L136: =IF(OR(tblLines[[#This Row],[Rate / Pack]]="",tblLines[[#This Row],[Qty (Packs)]]=""),"",ROUND(tblLines[[#This Row],[Rate / Pack]]*tblLines[[#This Row],[Qty (Packs)]],0)) -> 135938 | M136: =IF(tblLines[[#This Row],[Amount]]="","",tblLines[[#This Row],[Amount]]*IFERROR(INDEX(Products!$I$4:$I$500,MATCH(tblLines[[#This Row],[Description (Product)]],Products!$B$4:$B$500,0)),frmCommRate)) -> 475.783 | N136: =IF(tblLines[[#This Row],[Qty (Packs)]]="","",tblLines[[#This Row],[Qty (Packs)]]*tblLines[[#This Row],[Pack Wt (KG)]]) -> 1250
A137: 109 | B137: 46274 | C137: Pak Rice Traders | D137: Alam Shah Traders | E137: Dina | F137: Arslan Ahmed Dar | G137: ZAFARANI STEAM PLATINUM 25KG | H137: 170 | I137: 13300 | J137: =IFERROR(INDEX(Products!$E$4:$E$500,MATCH(tblLines[[#This Row],[Description (Product)]],Products!$B$4:$B$500,0)),"") -> 25 | K137: =IF(OR(tblLines[[#This Row],[Description (Product)]]="",tblLines[[#This Row],[Rate 40Kg]]=""),"",tblLines[[#This Row],[Rate 40Kg]]/40*tblLines[[#This Row],[Pack Wt (KG)]]) -> 8312.5 | L137: =IF(OR(tblLines[[#This Row],[Rate / Pack]]="",tblLines[[#This Row],[Qty (Packs)]]=""),"",ROUND(tblLines[[#This Row],[Rate / Pack]]*tblLines[[#This Row],[Qty (Packs)]],0)) -> 1413125 | M137: =IF(tblLines[[#This Row],[Amount]]="","",tblLines[[#This Row],[Amount]]*IFERROR(INDEX(Products!$I$4:$I$500,MATCH(tblLines[[#This Row],[Description (Product)]],Products!$B$4:$B$500,0)),frmCommRate)) -> 4945.9375 | N137: =IF(tblLines[[#This Row],[Qty (Packs)]]="","",tblLines[[#This Row],[Qty (Packs)]]*tblLines[[#This Row],[Pack Wt (KG)]]) -> 4250
A138: 109 | B138: 46274 | C138: Pak Rice Traders | D138: Alam Shah Traders | E138: Dina | F138: Arslan Ahmed Dar | G138: ZAFARANI SELLA GOLDEN 25KG | H138: 50 | I138: 12150 | J138: =IFERROR(INDEX(Products!$E$4:$E$500,MATCH(tblLines[[#This Row],[Description (Product)]],Products!$B$4:$B$500,0)),"") -> 25 | K138: =IF(OR(tblLines[[#This Row],[Description (Product)]]="",tblLines[[#This Row],[Rate 40Kg]]=""),"",tblLines[[#This Row],[Rate 40Kg]]/40*tblLines[[#This Row],[Pack Wt (KG)]]) -> 7593.75 | L138: =IF(OR(tblLines[[#This Row],[Rate / Pack]]="",tblLines[[#This Row],[Qty (Packs)]]=""),"",ROUND(tblLines[[#This Row],[Rate / Pack]]*tblLines[[#This Row],[Qty (Packs)]],0)) -> 379688 | M138: =IF(tblLines[[#This Row],[Amount]]="","",tblLines[[#This Row],[Amount]]*IFERROR(INDEX(Products!$I$4:$I$500,MATCH(tblLines[[#This Row],[Description (Product)]],Products!$B$4:$B$500,0)),frmCommRate)) -> 1328.908 | N138: =IF(tblLines[[#This Row],[Qty (Packs)]]="","",tblLines[[#This Row],[Qty (Packs)]]*tblLines[[#This Row],[Pack Wt (KG)]]) -> 1250
A139: 130 | B139: 46277 | C139: Hassan Enterprises | E139: Fatehjang | F139: Farhan Khalid | G139: WHITE CHANNA 9MM 25KG | H139: 520 | I139: 10300 | J139: =IFERROR(INDEX(Products!$E$4:$E$500,MATCH(tblLines[[#This Row],[Description (Product)]],Products!$B$4:$B$500,0)),"") -> 25 | K139: =IF(OR(tblLines[[#This Row],[Description (Product)]]="",tblLines[[#This Row],[Rate 40Kg]]=""),"",tblLines[[#This Row],[Rate 40Kg]]/40*tblLines[[#This Row],[Pack Wt (KG)]]) -> 6437.5 | L139: =IF(OR(tblLines[[#This Row],[Rate / Pack]]="",tblLines[[#This Row],[Qty (Packs)]]=""),"",ROUND(tblLines[[#This Row],[Rate / Pack]]*tblLines[[#This Row],[Qty (Packs)]],0)) -> 3347500 | M139: =IF(tblLines[[#This Row],[Amount]]="","",tblLines[[#This Row],[Amount]]*IFERROR(INDEX(Products!$I$4:$I$500,MATCH(tblLines[[#This Row],[Description (Product)]],Products!$B$4:$B$500,0)),frmCommRate)) -> 11716.25 | N139: =IF(tblLines[[#This Row],[Qty (Packs)]]="","",tblLines[[#This Row],[Qty (Packs)]]*tblLines[[#This Row],[Pack Wt (KG)]]) -> 13000
A140: 131 | B140: 46277 | C140: Hassan Enterprises | E140: Fatehjang | F140: Farhan Khalid | G140: ZAFARANI SUTRANGI 25KG | H140: 80 | I140: 10800 | J140: =IFERROR(INDEX(Products!$E$4:$E$500,MATCH(tblLines[[#This Row],[Description (Product)]],Products!$B$4:$B$500,0)),"") -> 25 | K140: =IF(OR(tblLines[[#This Row],[Description (Product)]]="",tblLines[[#This Row],[Rate 40Kg]]=""),"",tblLines[[#This Row],[Rate 40Kg]]/40*tblLines[[#This Row],[Pack Wt (KG)]]) -> 6750 | L140: =IF(OR(tblLines[[#This Row],[Rate / Pack]]="",tblLines[[#This Row],[Qty (Packs)]]=""),"",ROUND(tblLines[[#This Row],[Rate / Pack]]*tblLines[[#This Row],[Qty (Packs)]],0)) -> 540000 | M140: =IF(tblLines[[#This Row],[Amount]]="","",tblLines[[#This Row],[Amount]]*IFERROR(INDEX(Products!$I$4:$I$500,MATCH(tblLines[[#This Row],[Description (Product)]],Products!$B$4:$B$500,0)),frmCommRate)) -> 1890 | N140: =IF(tblLines[[#This Row],[Qty (Packs)]]="","",tblLines[[#This Row],[Qty (Packs)]]*tblLines[[#This Row],[Pack Wt (KG)]]) -> 2000
A141: 132 | B141: 46277 | C141: Ashfaq Commission shop | E141: Rawalpindi | F141: Farhan Khalid | G141: ZAFARANI STEAM PLATINUM 25KG | H141: 600 | I141: 13500 | J141: =IFERROR(INDEX(Products!$E$4:$E$500,MATCH(tblLines[[#This Row],[Description (Product)]],Products!$B$4:$B$500,0)),"") -> 25 | K141: =IF(OR(tblLines[[#This Row],[Description (Product)]]="",tblLines[[#This Row],[Rate 40Kg]]=""),"",tblLines[[#This Row],[Rate 40Kg]]/40*tblLines[[#This Row],[Pack Wt (KG)]]) -> 8437.5 | L141: =IF(OR(tblLines[[#This Row],[Rate / Pack]]="",tblLines[[#This Row],[Qty (Packs)]]=""),"",ROUND(tblLines[[#This Row],[Rate / Pack]]*tblLines[[#This Row],[Qty (Packs)]],0)) -> 5062500 | M141: =IF(tblLines[[#This Row],[Amount]]="","",tblLines[[#This Row],[Amount]]*IFERROR(INDEX(Products!$I$4:$I$500,MATCH(tblLines[[#This Row],[Description (Product)]],Products!$B$4:$B$500,0)),frmCommRate)) -> 17718.75 | N141: =IF(tblLines[[#This Row],[Qty (Packs)]]="","",tblLines[[#This Row],[Qty (Packs)]]*tblLines[[#This Row],[Pack Wt (KG)]]) -> 15000
A142: 133 | B142: 46277 | C142: Pakistan Traders | E142: Haripur | F142: Farhan Khalid | G142: ZAFARANI STEAM PLATINUM 25KG | H142: 150 | I142: 13500 | J142: =IFERROR(INDEX(Products!$E$4:$E$500,MATCH(tblLines[[#This Row],[Description (Product)]],Products!$B$4:$B$500,0)),"") -> 25 | K142: =IF(OR(tblLines[[#This Row],[Description (Product)]]="",tblLines[[#This Row],[Rate 40Kg]]=""),"",tblLines[[#This Row],[Rate 40Kg]]/40*tblLines[[#This Row],[Pack Wt (KG)]]) -> 8437.5 | L142: =IF(OR(tblLines[[#This Row],[Rate / Pack]]="",tblLines[[#This Row],[Qty (Packs)]]=""),"",ROUND(tblLines[[#This Row],[Rate / Pack]]*tblLines[[#This Row],[Qty (Packs)]],0)) -> 1265625 | M142: =IF(tblLines[[#This Row],[Amount]]="","",tblLines[[#This Row],[Amount]]*IFERROR(INDEX(Products!$I$4:$I$500,MATCH(tblLines[[#This Row],[Description (Product)]],Products!$B$4:$B$500,0)),frmCommRate)) -> 4429.6875 | N142: =IF(tblLines[[#This Row],[Qty (Packs)]]="","",tblLines[[#This Row],[Qty (Packs)]]*tblLines[[#This Row],[Pack Wt (KG)]]) -> 3750
A143: 133 | B143: 46277 | C143: Pakistan Traders | E143: Haripur | F143: Farhan Khalid | G143: HAZARA B-2, 25KG | H143: 450 | I143: 4550 | J143: =IFERROR(INDEX(Products!$E$4:$E$500,MATCH(tblLines[[#This Row],[Description (Product)]],Products!$B$4:$B$500,0)),"") -> 25 | K143: =IF(OR(tblLines[[#This Row],[Description (Product)]]="",tblLines[[#This Row],[Rate 40Kg]]=""),"",tblLines[[#This Row],[Rate 40Kg]]/40*tblLines[[#This Row],[Pack Wt (KG)]]) -> 2843.75 | L143: =IF(OR(tblLines[[#This Row],[Rate / Pack]]="",tblLines[[#This Row],[Qty (Packs)]]=""),"",ROUND(tblLines[[#This Row],[Rate / Pack]]*tblLines[[#This Row],[Qty (Packs)]],0)) -> 1279688 | M143: =IF(tblLines[[#This Row],[Amount]]="","",tblLines[[#This Row],[Amount]]*IFERROR(INDEX(Products!$I$4:$I$500,MATCH(tblLines[[#This Row],[Description (Product)]],Products!$B$4:$B$500,0)),frmCommRate)) -> 4478.908 | N143: =IF(tblLines[[#This Row],[Qty (Packs)]]="","",tblLines[[#This Row],[Qty (Packs)]]*tblLines[[#This Row],[Pack Wt (KG)]]) -> 11250
A144: 134 | B144: 46276 | C144: Imran Traders | E144: Attock | F144: Farhan Khalid | G144: HAZARA B-2, 25KG | H144: 100 | I144: 4550 | J144: =IFERROR(INDEX(Products!$E$4:$E$500,MATCH(tblLines[[#This Row],[Description (Product)]],Products!$B$4:$B$500,0)),"") -> 25 | K144: =IF(OR(tblLines[[#This Row],[Description (Product)]]="",tblLines[[#This Row],[Rate 40Kg]]=""),"",tblLines[[#This Row],[Rate 40Kg]]/40*tblLines[[#This Row],[Pack Wt (KG)]]) -> 2843.75 | L144: =IF(OR(tblLines[[#This Row],[Rate / Pack]]="",tblLines[[#This Row],[Qty (Packs)]]=""),"",ROUND(tblLines[[#This Row],[Rate / Pack]]*tblLines[[#This Row],[Qty (Packs)]],0)) -> 284375 | M144: =IF(tblLines[[#This Row],[Amount]]="","",tblLines[[#This Row],[Amount]]*IFERROR(INDEX(Products!$I$4:$I$500,MATCH(tblLines[[#This Row],[Description (Product)]],Products!$B$4:$B$500,0)),frmCommRate)) -> 995.3125 | N144: =IF(tblLines[[#This Row],[Qty (Packs)]]="","",tblLines[[#This Row],[Qty (Packs)]]*tblLines[[#This Row],[Pack Wt (KG)]]) -> 2500
A145: 134 | B145: 46276 | C145: Imran Traders | E145: Attock | F145: Farhan Khalid | G145: ZAFARANI STEAM PLATINUM 25KG | H145: 350 | I145: 13500 | J145: =IFERROR(INDEX(Products!$E$4:$E$500,MATCH(tblLines[[#This Row],[Description (Product)]],Products!$B$4:$B$500,0)),"") -> 25 | K145: =IF(OR(tblLines[[#This Row],[Description (Product)]]="",tblLines[[#This Row],[Rate 40Kg]]=""),"",tblLines[[#This Row],[Rate 40Kg]]/40*tblLines[[#This Row],[Pack Wt (KG)]]) -> 8437.5 | L145: =IF(OR(tblLines[[#This Row],[Rate / Pack]]="",tblLines[[#This Row],[Qty (Packs)]]=""),"",ROUND(tblLines[[#This Row],[Rate / Pack]]*tblLines[[#This Row],[Qty (Packs)]],0)) -> 2953125 | M145: =IF(tblLines[[#This Row],[Amount]]="","",tblLines[[#This Row],[Amount]]*IFERROR(INDEX(Products!$I$4:$I$500,MATCH(tblLines[[#This Row],[Description (Product)]],Products!$B$4:$B$500,0)),frmCommRate)) -> 10335.938 | N145: =IF(tblLines[[#This Row],[Qty (Packs)]]="","",tblLines[[#This Row],[Qty (Packs)]]*tblLines[[#This Row],[Pack Wt (KG)]]) -> 8750
A146: 157 | B146: 46280 | C146: Pak Rice Traders | E146: Dina | F146: Farhan Khalid | G146: ZAFARANI STEAM SHADMANI 25KG | H146: 17000 | I146: 7300 | J146: =IFERROR(INDEX(Products!$E$4:$E$500,MATCH(tblLines[[#This Row],[Description (Product)]],Products!$B$4:$B$500,0)),"") -> 25 | K146: =IF(OR(tblLines[[#This Row],[Description (Product)]]="",tblLines[[#This Row],[Rate 40Kg]]=""),"",tblLines[[#This Row],[Rate 40Kg]]/40*tblLines[[#This Row],[Pack Wt (KG)]]) -> 4562.5 | L146: =IF(OR(tblLines[[#This Row],[Rate / Pack]]="",tblLines[[#This Row],[Qty (Packs)]]=""),"",ROUND(tblLines[[#This Row],[Rate / Pack]]*tblLines[[#This Row],[Qty (Packs)]],0)) -> 77562500 | M146: =IF(tblLines[[#This Row],[Amount]]="","",tblLines[[#This Row],[Amount]]*IFERROR(INDEX(Products!$I$4:$I$500,MATCH(tblLines[[#This Row],[Description (Product)]],Products!$B$4:$B$500,0)),frmCommRate)) -> 271468.75 | N146: =IF(tblLines[[#This Row],[Qty (Packs)]]="","",tblLines[[#This Row],[Qty (Packs)]]*tblLines[[#This Row],[Pack Wt (KG)]]) -> 425000
A147: 155 | B147: 46280 | C147: Pak Rice Traders | E147: Dina | F147: Farhan Khalid | G147: ZAFARANI SUTRANGI 25KG | H147: 100 | I147: 10600 | J147: =IFERROR(INDEX(Products!$E$4:$E$500,MATCH(tblLines[[#This Row],[Description (Product)]],Products!$B$4:$B$500,0)),"") -> 25 | K147: =IF(OR(tblLines[[#This Row],[Description (Product)]]="",tblLines[[#This Row],[Rate 40Kg]]=""),"",tblLines[[#This Row],[Rate 40Kg]]/40*tblLines[[#This Row],[Pack Wt (KG)]]) -> 6625 | L147: =IF(OR(tblLines[[#This Row],[Rate / Pack]]="",tblLines[[#This Row],[Qty (Packs)]]=""),"",ROUND(tblLines[[#This Row],[Rate / Pack]]*tblLines[[#This Row],[Qty (Packs)]],0)) -> 662500 | M147: =IF(tblLines[[#This Row],[Amount]]="","",tblLines[[#This Row],[Amount]]*IFERROR(INDEX(Products!$I$4:$I$500,MATCH(tblLines[[#This Row],[Description (Product)]],Products!$B$4:$B$500,0)),frmCommRate)) -> 2318.75 | N147: =IF(tblLines[[#This Row],[Qty (Packs)]]="","",tblLines[[#This Row],[Qty (Packs)]]*tblLines[[#This Row],[Pack Wt (KG)]]) -> 2500
A148: 155 | B148: 46280 | C148: Pak Rice Traders | E148: Dina | F148: Farhan Khalid | G148: ZAFARANI STEAM GOLD 25KG | H148: 100 | I148: 12500 | J148: =IFERROR(INDEX(Products!$E$4:$E$500,MATCH(tblLines[[#This Row],[Description (Product)]],Products!$B$4:$B$500,0)),"") -> 25 | K148: =IF(OR(tblLines[[#This Row],[Description (Product)]]="",tblLines[[#This Row],[Rate 40Kg]]=""),"",tblLines[[#This Row],[Rate 40Kg]]/40*tblLines[[#This Row],[Pack Wt (KG)]]) -> 7812.5 | L148: =IF(OR(tblLines[[#This Row],[Rate / Pack]]="",tblLines[[#This Row],[Qty (Packs)]]=""),"",ROUND(tblLines[[#This Row],[Rate / Pack]]*tblLines[[#This Row],[Qty (Packs)]],0)) -> 781250 | M148: =IF(tblLines[[#This Row],[Amount]]="","",tblLines[[#This Row],[Amount]]*IFERROR(INDEX(Products!$I$4:$I$500,MATCH(tblLines[[#This Row],[Description (Product)]],Products!$B$4:$B$500,0)),frmCommRate)) -> 2734.375 | N148: =IF(tblLines[[#This Row],[Qty (Packs)]]="","",tblLines[[#This Row],[Qty (Packs)]]*tblLines[[#This Row],[Pack Wt (KG)]]) -> 2500
A149: 155 | B149: 46280 | C149: Pak Rice Traders | E149: Dina | F149: Farhan Khalid | G149: ZAFARANI SELLA GOLDEN 25KG | H149: 817 | I149: 12150 | J149: =IFERROR(INDEX(Products!$E$4:$E$500,MATCH(tblLines[[#This Row],[Description (Product)]],Products!$B$4:$B$500,0)),"") -> 25 | K149: =IF(OR(tblLines[[#This Row],[Description (Product)]]="",tblLines[[#This Row],[Rate 40Kg]]=""),"",tblLines[[#This Row],[Rate 40Kg]]/40*tblLines[[#This Row],[Pack Wt (KG)]]) -> 7593.75 | L149: =IF(OR(tblLines[[#This Row],[Rate / Pack]]="",tblLines[[#This Row],[Qty (Packs)]]=""),"",ROUND(tblLines[[#This Row],[Rate / Pack]]*tblLines[[#This Row],[Qty (Packs)]],0)) -> 6204094 | M149: =IF(tblLines[[#This Row],[Amount]]="","",tblLines[[#This Row],[Amount]]*IFERROR(INDEX(Products!$I$4:$I$500,MATCH(tblLines[[#This Row],[Description (Product)]],Products!$B$4:$B$500,0)),frmCommRate)) -> 21714.329 | N149: =IF(tblLines[[#This Row],[Qty (Packs)]]="","",tblLines[[#This Row],[Qty (Packs)]]*tblLines[[#This Row],[Pack Wt (KG)]]) -> 20425
A150: 155 | B150: 46280 | C150: Pak Rice Traders | E150: Dina | F150: Farhan Khalid | G150: ZAFARANI STEAM B-1, 25KG | H150: 100 | I150: 5900 | J150: =IFERROR(INDEX(Products!$E$4:$E$500,MATCH(tblLines[[#This Row],[Description (Product)]],Products!$B$4:$B$500,0)),"") -> 25 | K150: =IF(OR(tblLines[[#This Row],[Description (Product)]]="",tblLines[[#This Row],[Rate 40Kg]]=""),"",tblLines[[#This Row],[Rate 40Kg]]/40*tblLines[[#This Row],[Pack Wt (KG)]]) -> 3687.5 | L150: =IF(OR(tblLines[[#This Row],[Rate / Pack]]="",tblLines[[#This Row],[Qty (Packs)]]=""),"",ROUND(tblLines[[#This Row],[Rate / Pack]]*tblLines[[#This Row],[Qty (Packs)]],0)) -> 368750 | M150: =IF(tblLines[[#This Row],[Amount]]="","",tblLines[[#This Row],[Amount]]*IFERROR(INDEX(Products!$I$4:$I$500,MATCH(tblLines[[#This Row],[Description (Product)]],Products!$B$4:$B$500,0)),frmCommRate)) -> 1290.625 | N150: =IF(tblLines[[#This Row],[Qty (Packs)]]="","",tblLines[[#This Row],[Qty (Packs)]]*tblLines[[#This Row],[Pack Wt (KG)]]) -> 2500
... A155: 156 | B155: 46280 | C155: Pak Rice Traders | E155: Dina | F155: Farhan Khalid | G155: DAAL CHANNA REGULAR 25KG | H155: 20 | I155: 9100 | J155: =IFERROR(INDEX(Products!$E$4:$E$500,MATCH(tblLines[[#This Row],[Description (Product)]],Products!$B$4:$B$500,0)),"") -> 25 | K155: =IF(OR(tblLines[[#This Row],[Description (Product)]]="",tblLines[[#This Row],[Rate 40Kg]]=""),"",tblLines[[#This Row],[Rate 40Kg]]/40*tblLines[[#This Row],[Pack Wt (KG)]]) -> 5687.5 | L155: =IF(OR(tblLines[[#This Row],[Rate / Pack]]="",tblLines[[#This Row],[Qty (Packs)]]=""),"",ROUND(tblLines[[#This Row],[Rate / Pack]]*tblLines[[#This Row],[Qty (Packs)]],0)) -> 113750 | M155: =IF(tblLines[[#This Row],[Amount]]="","",tblLines[[#This Row],[Amount]]*IFERROR(INDEX(Products!$I$4:$I$500,MATCH(tblLines[[#This Row],[Description (Product)]],Products!$B$4:$B$500,0)),frmCommRate)) -> 398.125 | N155: =IF(tblLines[[#This Row],[Qty (Packs)]]="","",tblLines[[#This Row],[Qty (Packs)]]*tblLines[[#This Row],[Pack Wt (KG)]]) -> 500
J156: =IFERROR(INDEX(Products!$E$4:$E$500,MATCH(tblLines[[#This Row],[Description (Product)]],Products!$B$4:$B$500,0)),"") | K156: =IF(OR(tblLines[[#This Row],[Description (Product)]]="",tblLines[[#This Row],[Rate 40Kg]]=""),"",tblLines[[#This Row],[Rate 40Kg]]/40*tblLines[[#This Row],[Pack Wt (KG)]]) | L156: =IF(OR(tblLines[[#This Row],[Rate / Pack]]="",tblLines[[#This Row],[Qty (Packs)]]=""),"",ROUND(tblLines[[#This Row],[Rate / Pack]]*tblLines[[#This Row],[Qty (Packs)]],0)) | M156: =IF(tblLines[[#This Row],[Amount]]="","",tblLines[[#This Row],[Amount]]*IFERROR(INDEX(Products!$I$4:$I$500,MATCH(tblLines[[#This Row],[Description (Product)]],Products!$B$4:$B$500,0)),frmCommRate)) | N156: =IF(tblLines[[#This Row],[Qty (Packs)]]="","",tblLines[[#This Row],[Qty (Packs)]]*tblLines[[#This Row],[Pack Wt (KG)]])

Sheet Payments
B1: WAQAR RICE MILLS
B2: Payments Recovery · log each recovery against the party
B4: NEW PAYMENT ENTRY | F4: PARTY POSITION
B5: Date | F5: Invoiced | G5: {=IF($C$6="","",SUMPRODUCT((TRIM(tblLines[Party (Name)])=$C$6)*IFERROR(tblLines[Amount]+0,0)))}
B6: Party (Name) | F6: Recovered so far | G6: {=IF($C$6="","",SUMPRODUCT((TRIM(tblPayments[Party (Name)])=$C$6)*IFERROR(tblPayments[Amount]+0,0)))}
B7: Sub Party | F7: Outstanding | G7: =IF($C$6="","",$G$5-$G$6)
B8: Slip No. | F8: After this payment | G8: =IF($C$6="","",$G$7-IFERROR($C$10+0,0))
B9: Bank
B10: Amount
B11: Remarks
B15: Fill the fields above, then click SAVE ENTRY. The row is appended to the payment log below and the summary updates itself.
B19: PAYMENT ENTRIES | J19: RECOVERY SUMMARY BY PARTY
B20: Date | C20: Party (Name) | D20: Sub Party | E20: Slip No. | F20: Bank | G20: Amount | H20: Remarks | J20: Party (Name) | K20: Invoiced | L20: Recovered | M20: Outstanding | N20: % Rec.
J21: {=IFERROR(_xlfn._xlws.SORT(_xlfn.UNIQUE(_xlfn._xlws.FILTER(TRIM(tblLines[Party (Name)]),TRIM(tblLines[Party (Name)])<>""))),"")} -> Allah Walay Traders | K21: {=IF($J21="","",SUMPRODUCT((TRIM(tblLines[Party (Name)])=$J21)*IFERROR(tblLines[Amount]+0,0)))} -> 9287189 | L21: {=IF($J21="","",SUMPRODUCT((TRIM(tblPayments[Party (Name)])=$J21)*IFERROR(tblPayments[Amount]+0,0)))} -> 0 | M21: =IF($J21="","",$K21-$L21) -> 9287189 | N21: =IF(OR($J21="",$K21=0),"",$L21/$K21) -> 0
J22: Ashfaq Commission shop | K22: {=IF($J22="","",SUMPRODUCT((TRIM(tblLines[Party (Name)])=$J22)*IFERROR(tblLines[Amount]+0,0)))} -> 5062500 | L22: {=IF($J22="","",SUMPRODUCT((TRIM(tblPayments[Party (Name)])=$J22)*IFERROR(tblPayments[Amount]+0,0)))} -> 0 | M22: =IF($J22="","",$K22-$L22) -> 5062500 | N22: =IF(OR($J22="",$K22=0),"",$L22/$K22) -> 0
J23: Bhayya Traders | K23: {=IF($J23="","",SUMPRODUCT((TRIM(tblLines[Party (Name)])=$J23)*IFERROR(tblLines[Amount]+0,0)))} -> 4556250 | L23: {=IF($J23="","",SUMPRODUCT((TRIM(tblPayments[Party (Name)])=$J23)*IFERROR(tblPayments[Amount]+0,0)))} -> 0 | M23: =IF($J23="","",$K23-$L23) -> 4556250 | N23: =IF(OR($J23="",$K23=0),"",$L23/$K23) -> 0
J24: Hamdard Traders | K24: {=IF($J24="","",SUMPRODUCT((TRIM(tblLines[Party (Name)])=$J24)*IFERROR(tblLines[Amount]+0,0)))} -> 6053807 | L24: {=IF($J24="","",SUMPRODUCT((TRIM(tblPayments[Party (Name)])=$J24)*IFERROR(tblPayments[Amount]+0,0)))} -> 0 | M24: =IF($J24="","",$K24-$L24) -> 6053807 | N24: =IF(OR($J24="",$K24=0),"",$L24/$K24) -> 0
J25: Hassan Enterprises | K25: {=IF($J25="","",SUMPRODUCT((TRIM(tblLines[Party (Name)])=$J25)*IFERROR(tblLines[Amount]+0,0)))} -> 12054139 | L25: {=IF($J25="","",SUMPRODUCT((TRIM(tblPayments[Party (Name)])=$J25)*IFERROR(tblPayments[Amount]+0,0)))} -> 0 | M25: =IF($J25="","",$K25-$L25) -> 12054139 | N25: =IF(OR($J25="",$K25=0),"",$L25/$K25) -> 0
J26: Imran Traders | K26: {=IF($J26="","",SUMPRODUCT((TRIM(tblLines[Party (Name)])=$J26)*IFERROR(tblLines[Amount]+0,0)))} -> 3237500 | L26: {=IF($J26="","",SUMPRODUCT((TRIM(tblPayments[Party (Name)])=$J26)*IFERROR(tblPayments[Amount]+0,0)))} -> 0 | M26: =IF($J26="","",$K26-$L26) -> 3237500 | N26: =IF(OR($J26="",$K26=0),"",$L26/$K26) -> 0
J27: Pak Rice Traders | K27: {=IF($J27="","",SUMPRODUCT((TRIM(tblLines[Party (Name)])=$J27)*IFERROR(tblLines[Amount]+0,0)))} -> 122823474 | L27: {=IF($J27="","",SUMPRODUCT((TRIM(tblPayments[Party (Name)])=$J27)*IFERROR(tblPayments[Amount]+0,0)))} -> 0 | M27: =IF($J27="","",$K27-$L27) -> 122823474 | N27: =IF(OR($J27="",$K27=0),"",$L27/$K27) -> 0
J28: Pakistan Traders | K28: {=IF($J28="","",SUMPRODUCT((TRIM(tblLines[Party (Name)])=$J28)*IFERROR(tblLines[Amount]+0,0)))} -> 2545313 | L28: {=IF($J28="","",SUMPRODUCT((TRIM(tblPayments[Party (Name)])=$J28)*IFERROR(tblPayments[Amount]+0,0)))} -> 0 | M28: =IF($J28="","",$K28-$L28) -> 2545313 | N28: =IF(OR($J28="",$K28=0),"",$L28/$K28) -> 0
J29: Shalimar Traders | K29: {=IF($J29="","",SUMPRODUCT((TRIM(tblLines[Party (Name)])=$J29)*IFERROR(tblLines[Amount]+0,0)))} -> 20111694 | L29: {=IF($J29="","",SUMPRODUCT((TRIM(tblPayments[Party (Name)])=$J29)*IFERROR(tblPayments[Amount]+0,0)))} -> 0 | M29: =IF($J29="","",$K29-$L29) -> 20111694 | N29: =IF(OR($J29="",$K29=0),"",$L29/$K29) -> 0
J30: Sheikh Traders | K30: {=IF($J30="","",SUMPRODUCT((TRIM(tblLines[Party (Name)])=$J30)*IFERROR(tblLines[Amount]+0,0)))} -> 4249063 | L30: {=IF($J30="","",SUMPRODUCT((TRIM(tblPayments[Party (Name)])=$J30)*IFERROR(tblPayments[Amount]+0,0)))} -> 0 | M30: =IF($J30="","",$K30-$L30) -> 4249063 | N30: =IF(OR($J30="",$K30=0),"",$L30/$K30) -> 0
J31: Tayyab Traders | K31: {=IF($J31="","",SUMPRODUCT((TRIM(tblLines[Party (Name)])=$J31)*IFERROR(tblLines[Amount]+0,0)))} -> 3476505 | L31: {=IF($J31="","",SUMPRODUCT((TRIM(tblPayments[Party (Name)])=$J31)*IFERROR(tblPayments[Amount]+0,0)))} -> 0 | M31: =IF($J31="","",$K31-$L31) -> 3476505 | N31: =IF(OR($J31="",$K31=0),"",$L31/$K31) -> 0
K32: {=IF($J32="","",SUMPRODUCT((TRIM(tblLines[Party (Name)])=$J32)*IFERROR(tblLines[Amount]+0,0)))} | L32: {=IF($J32="","",SUMPRODUCT((TRIM(tblPayments[Party (Name)])=$J32)*IFERROR(tblPayments[Amount]+0,0)))} | M32: =IF($J32="","",$K32-$L32) | N32: =IF(OR($J32="",$K32=0),"",$L32/$K32)
K33: {=IF($J33="","",SUMPRODUCT((TRIM(tblLines[Party (Name)])=$J33)*IFERROR(tblLines[Amount]+0,0)))} | L33: {=IF($J33="","",SUMPRODUCT((TRIM(tblPayments[Party (Name)])=$J33)*IFERROR(tblPayments[Amount]+0,0)))} | M33: =IF($J33="","",$K33-$L33) | N33: =IF(OR($J33="",$K33=0),"",$L33/$K33)
K34: {=IF($J34="","",SUMPRODUCT((TRIM(tblLines[Party (Name)])=$J34)*IFERROR(tblLines[Amount]+0,0)))} | L34: {=IF($J34="","",SUMPRODUCT((TRIM(tblPayments[Party (Name)])=$J34)*IFERROR(tblPayments[Amount]+0,0)))} | M34: =IF($J34="","",$K34-$L34) | N34: =IF(OR($J34="",$K34=0),"",$L34/$K34)
K35: {=IF($J35="","",SUMPRODUCT((TRIM(tblLines[Party (Name)])=$J35)*IFERROR(tblLines[Amount]+0,0)))} | L35: {=IF($J35="","",SUMPRODUCT((TRIM(tblPayments[Party (Name)])=$J35)*IFERROR(tblPayments[Amount]+0,0)))} | M35: =IF($J35="","",$K35-$L35) | N35: =IF(OR($J35="",$K35=0),"",$L35/$K35)
K36: {=IF($J36="","",SUMPRODUCT((TRIM(tblLines[Party (Name)])=$J36)*IFERROR(tblLines[Amount]+0,0)))} | L36: {=IF($J36="","",SUMPRODUCT((TRIM(tblPayments[Party (Name)])=$J36)*IFERROR(tblPayments[Amount]+0,0)))} | M36: =IF($J36="","",$K36-$L36) | N36: =IF(OR($J36="",$K36=0),"",$L36/$K36)
K37: {=IF($J37="","",SUMPRODUCT((TRIM(tblLines[Party (Name)])=$J37)*IFERROR(tblLines[Amount]+0,0)))} | L37: {=IF($J37="","",SUMPRODUCT((TRIM(tblPayments[Party (Name)])=$J37)*IFERROR(tblPayments[Amount]+0,0)))} | M37: =IF($J37="","",$K37-$L37) | N37: =IF(OR($J37="",$K37=0),"",$L37/$K37)
K38: {=IF($J38="","",SUMPRODUCT((TRIM(tblLines[Party (Name)])=$J38)*IFERROR(tblLines[Amount]+0,0)))} | L38: {=IF($J38="","",SUMPRODUCT((TRIM(tblPayments[Party (Name)])=$J38)*IFERROR(tblPayments[Amount]+0,0)))} | M38: =IF($J38="","",$K38-$L38) | N38: =IF(OR($J38="",$K38=0),"",$L38/$K38)
K39: {=IF($J39="","",SUMPRODUCT((TRIM(tblLines[Party (Name)])=$J39)*IFERROR(tblLines[Amount]+0,0)))} | L39: {=IF($J39="","",SUMPRODUCT((TRIM(tblPayments[Party (Name)])=$J39)*IFERROR(tblPayments[Amount]+0,0)))} | M39: =IF($J39="","",$K39-$L39) | N39: =IF(OR($J39="",$K39=0),"",$L39/$K39)
K40: {=IF($J40="","",SUMPRODUCT((TRIM(tblLines[Party (Name)])=$J40)*IFERROR(tblLines[Amount]+0,0)))} | L40: {=IF($J40="","",SUMPRODUCT((TRIM(tblPayments[Party (Name)])=$J40)*IFERROR(tblPayments[Amount]+0,0)))} | M40: =IF($J40="","",$K40-$L40) | N40: =IF(OR($J40="",$K40=0),"",$L40/$K40)
K41: {=IF($J41="","",SUMPRODUCT((TRIM(tblLines[Party (Name)])=$J41)*IFERROR(tblLines[Amount]+0,0)))} | L41: {=IF($J41="","",SUMPRODUCT((TRIM(tblPayments[Party (Name)])=$J41)*IFERROR(tblPayments[Amount]+0,0)))} | M41: =IF($J41="","",$K41-$L41) | N41: =IF(OR($J41="",$K41=0),"",$L41/$K41)
K42: {=IF($J42="","",SUMPRODUCT((TRIM(tblLines[Party (Name)])=$J42)*IFERROR(tblLines[Amount]+0,0)))} | L42: {=IF($J42="","",SUMPRODUCT((TRIM(tblPayments[Party (Name)])=$J42)*IFERROR(tblPayments[Amount]+0,0)))} | M42: =IF($J42="","",$K42-$L42) | N42: =IF(OR($J42="",$K42=0),"",$L42/$K42)
K43: {=IF($J43="","",SUMPRODUCT((TRIM(tblLines[Party (Name)])=$J43)*IFERROR(tblLines[Amount]+0,0)))} | L43: {=IF($J43="","",SUMPRODUCT((TRIM(tblPayments[Party (Name)])=$J43)*IFERROR(tblPayments[Amount]+0,0)))} | M43: =IF($J43="","",$K43-$L43) | N43: =IF(OR($J43="",$K43=0),"",$L43/$K43)
... K60: {=IF($J60="","",SUMPRODUCT((TRIM(tblLines[Party (Name)])=$J60)*IFERROR(tblLines[Amount]+0,0)))} | L60: {=IF($J60="","",SUMPRODUCT((TRIM(tblPayments[Party (Name)])=$J60)*IFERROR(tblPayments[Amount]+0,0)))} | M60: =IF($J60="","",$K60-$L60) | N60: =IF(OR($J60="",$K60=0),"",$L60/$K60)
J62: TOTAL | K62: =SUM(K21:K60) -> 193457434 | L62: =SUM(L21:L60) -> 0 | M62: =SUM(M21:M60) -> 193457434 | N62: =IF(K62=0,"",L62/K62) -> 0

Sheet Sheet1
D4: Date | E4: Party Name | F4: Bank | G4: Tansaction/slip no | H4: Amount | I4: Discription
D5: 46266 | E5: Allah walay Nakyal | F5: Grainco Ubl | G5: 718334 | H5: 2000000 | I5: from meezan bank app
D6: 46266 | E6: Pak Rice Traders dina | F6: Waqar Rice Abl | G6: 285843 | H6: 352000 | I6: from abl mobile app | L6: =SUM(H5:H983) -> 88533905 | N6: =L6*0.35% -> 309868.67
D7: 46266 | E7: Pak Rice Traders dina | F7: grainco foods | H7: 141630
D8: 46266 | E8: Hazrat Hussain Sawat | F8: Waqr Rice Mills | H8: 3000000
D9: 46266 | E9: Pak Rice Traders dina | F9: ubl Grainco | H9: 1000000
D10: 46266 | E10: Bin Sadeeq Traders | F10: cash | H10: 400000
D11: 46266 | E11: Pak Rice Traders dina | F11: grainco | H11: 200000
D12: 46266 | E12: Pak Rice Traders dina | F12: grainco | H12: 200000
D13: 46266 | E13: Pak Rice Traders dina | F13: grainco | H13: 75800
D14: 46267 | E14: Allah walay Nakyal | F14: grainco ubl | H14: 2700000
D15: 46267 | E15: Tayyab Traders Chakwal | F15: grainco | H15: 774000
D16: 46266 | E16: Pak Rice Traders dina | F16: grainco | H16: 300000
D17: 46267 | E17: Ashfaq Commission Shop | F17: Grainco | H17: 40000
D18: 46267 | E18: Ashfaq Commission Shop | F18: Waqar Rice Abl | H18: 500000
D19: 46268 | E19: Tayyab Traders Chakwal | F19: cash | H19: 1800000
D20: 46268 | E20: Islamabad Commission Shop | H20: 290000
D21: 46268 | E21: Islamabad Commission Shop | H21: 600000
D22: 46268 | E22: Islamabad Commission Shop | H22: 2000000
D23: 46268 | E23: Pak Rice Traders dina | H23: 400000
D24: 46268 | E24: Pak Rice Traders dina | H24: 100000
D25: 46268 | E25: Pak Rice Traders dina | H25: 128000
D26: 46268 | E26: Pak Rice Traders dina | H26: 171000
D27: 46268 | E27: Pak Rice Traders dina | H27: 13000
D28: 46268 | E28: Pak Rice Traders dina | H28: 19800
D29: 46269 | E29: Pak Rice Traders dina | H29: 3144250
D30: 46269 | E30: Pak Rice Traders dina | H30: 81250
D31: 46270 | E31: Tayyab Traders Chakwal | H31: 280000
... D90: 46277 | E90: Ashfaq Commission Shop | H90: 250000

Sheet Products
A1: Product List
A3: # | B3: Product | C3: Unit Weight (KG) | D3: Pack (pcs) | E3: Pack Weight (KG) | F3: Commission Rate | G3: 0.0035 | H3: Category | I3: Comm Rate | J3: Category | K3: Commission Rate
A4: 1 | B4: ZAFARANI STEAM PLATINUM 25KG | C4: 25 | D4: 1 | E4: =C4*D4 -> 25 | H4: Rice | I4: =IFERROR(INDEX($K$4:$K$6,MATCH($H4,$J$4:$J$6,0)),$G$3) -> 0.0035 | J4: Rice | K4: =$G$3 -> 0.0035
A5: 2 | B5: ZAFARANI STEAM PLATINUM 20KG | C5: 20 | D5: 1 | E5: =C5*D5 -> 20 | H5: Rice | I5: =IFERROR(INDEX($K$4:$K$6,MATCH($H5,$J$4:$J$6,0)),$G$3) -> 0.0035 | J5: Pulses | K5: 0.0035
A6: 3 | B6: ZAFARANI STEAM PLATINUM 10KG | C6: 10 | D6: 4 | E6: =C6*D6 -> 40 | H6: Rice | I6: =IFERROR(INDEX($K$4:$K$6,MATCH($H6,$J$4:$J$6,0)),$G$3) -> 0.0035 | J6: Other | K6: =$G$3 -> 0.0035
A7: 4 | B7: ZAFARANI STEAM PLATINUM 5KG | C7: 5 | D7: 8 | E7: =C7*D7 -> 40 | H7: Rice | I7: =IFERROR(INDEX($K$4:$K$6,MATCH($H7,$J$4:$J$6,0)),$G$3) -> 0.0035
A8: 5 | B8: ZAFARANI STEAM PLATINUM 1KG | C8: 1 | D8: 20 | E8: =C8*D8 -> 20 | H8: Rice | I8: =IFERROR(INDEX($K$4:$K$6,MATCH($H8,$J$4:$J$6,0)),$G$3) -> 0.0035
A9: 6 | B9: ZAFARANI STEAM GOLD 25KG | C9: 25 | D9: 1 | E9: =C9*D9 -> 25 | H9: Rice | I9: =IFERROR(INDEX($K$4:$K$6,MATCH($H9,$J$4:$J$6,0)),$G$3) -> 0.0035
A10: 7 | B10: ZAFARANI STEAM GOLD 5KG | C10: 5 | D10: 8 | E10: =C10*D10 -> 40 | H10: Rice | I10: =IFERROR(INDEX($K$4:$K$6,MATCH($H10,$J$4:$J$6,0)),$G$3) -> 0.0035
A11: 8 | B11: ZAFARANI STEAM SHADMANI 25KG | C11: 25 | D11: 1 | E11: =C11*D11 -> 25 | H11: Rice | I11: =IFERROR(INDEX($K$4:$K$6,MATCH($H11,$J$4:$J$6,0)),$G$3) -> 0.0035
A12: 9 | B12: ZAFARANI STEAM EVERYDAY 25KG | C12: 25 | D12: 1 | E12: =C12*D12 -> 25 | H12: Rice | I12: =IFERROR(INDEX($K$4:$K$6,MATCH($H12,$J$4:$J$6,0)),$G$3) -> 0.0035
A13: 10 | B13: ZAFARANI STEAM EVERYDAY 5KG | C13: 5 | D13: 8 | E13: =C13*D13 -> 40 | H13: Rice | I13: =IFERROR(INDEX($K$4:$K$6,MATCH($H13,$J$4:$J$6,0)),$G$3) -> 0.0035
A14: 11 | B14: ZAFARANI SELLA GOLDEN 25KG | C14: 25 | D14: 1 | E14: =C14*D14 -> 25 | H14: Rice | I14: =IFERROR(INDEX($K$4:$K$6,MATCH($H14,$J$4:$J$6,0)),$G$3) -> 0.0035
A15: 12 | B15: ZAFARANI SELLA GOLDEN 10KG | C15: 10 | D15: 4 | E15: =C15*D15 -> 40 | H15: Rice | I15: =IFERROR(INDEX($K$4:$K$6,MATCH($H15,$J$4:$J$6,0)),$G$3) -> 0.0035
A16: 13 | B16: ZAFARANI SELLA GOLDEN 5KG | C16: 5 | D16: 8 | E16: =C16*D16 -> 40 | H16: Rice | I16: =IFERROR(INDEX($K$4:$K$6,MATCH($H16,$J$4:$J$6,0)),$G$3) -> 0.0035
A17: 14 | B17: ZAFARANI SELLA AWAMI 25KG | C17: 25 | D17: 1 | E17: =C17*D17 -> 25 | H17: Rice | I17: =IFERROR(INDEX($K$4:$K$6,MATCH($H17,$J$4:$J$6,0)),$G$3) -> 0.0035
A18: 15 | B18: ZAFARANI STEAM SHORT GRAIN 25KG | C18: 25 | D18: 1 | E18: =C18*D18 -> 25 | H18: Rice | I18: =IFERROR(INDEX($K$4:$K$6,MATCH($H18,$J$4:$J$6,0)),$G$3) -> 0.0035
... A47: 44 | B47: DESI GHEE 1KG | C47: 1 | D47: 1 | E47: =C47*D47 -> 1 | H47: Other | I47: =IFERROR(INDEX($K$4:$K$6,MATCH($H47,$J$4:$J$6,0)),$G$3) -> 0.0035
A48: =A47+1 -> 45 | B48: ZAFARANI LOBIA PINTO 25KG | C48: 25 | D48: 1 | E48: =C48*D48 -> 25 | H48: Pulses | I48: =IFERROR(INDEX($K$4:$K$6,MATCH($H48,$J$4:$J$6,0)),$G$3) -> 0.0035

Sheet Lists
A1: Party (Name) | B1: City | C1: ASM / Salesperson | D1: Sub Party | E1: Bank
A2: {=IFERROR(_xlfn._xlws.SORT(_xlfn.UNIQUE(_xlfn._xlws.FILTER(TRIM(tblLines[Party (Name)]),TRIM(tblLines[Party (Name)])<>""))),"")} -> Allah Walay Traders | B2: {=IFERROR(_xlfn._xlws.SORT(_xlfn.UNIQUE(_xlfn._xlws.FILTER(TRIM(tblLines[City]),TRIM(tblLines[City])<>""))),"")} -> Attock | C2: {=IFERROR(_xlfn._xlws.SORT(_xlfn.UNIQUE(_xlfn._xlws.FILTER(TRIM(tblLines[ASM / Salesperson]),TRIM(tblLines[ASM / Salesperson])<>""))),"")} -> Arslan Ahmed Dar | D2: {=IFERROR(_xlfn._xlws.SORT(_xlfn.UNIQUE(_xlfn._xlws.FILTER(TRIM(tblLines[Sub Party]),TRIM(tblLines[Sub Party])<>""))),"")} -> Alam Shah Traders | E2: Allied Bank
A3: Ashfaq Commission shop | B3: Chakwal | C3: Farhan Khalid | D3: Iftikhar Traders | E3: Askari Bank
A4: Bhayya Traders | B4: Dina | D4: M Zaman Kotli | E4: Bank Alfalah
A5: Hamdard Traders | B5: Fatehjang | D5: Shahmeer Traders Kharian | E5: Bank of Punjab
A6: Hassan Enterprises | B6: Gahkuch | D6: Sheikh Abid Gujjar Khan | E6: Faysal Bank
A7: Imran Traders | B7: Gilgit | D7: Talha & co Kotla | E7: HBL
A8: Pak Rice Traders | B8: Gujrat | E8: Meezan Bank
A9: Pakistan Traders | B9: Haripur | E9: MCB
A10: Shalimar Traders | B10: Lalamusa | E10: National Bank
A11: Sheikh Traders | B11: Nakyal Ajk | E11: UBL
A12: Tayyab Traders | B12: Rawalpindi | E12: Cash

Sheet How To (VBA)
A1: SAVE BUTTON — INSTALLATION GUIDE
A3: This code finds the form by reading its own labels and headings, then remembers the positions as
A4: named ranges. If you ever move rows or columns, just run SetupNames once - no code editing.
A6: STEP 1 - The file must be saved as .xlsm (File > Save As > Excel Macro-Enabled Workbook).
A7: If a yellow security bar appears, click Enable Content.
A9: STEP 2 - Press ALT + F11 to open the VBA editor.
A11: STEP 3 - Remove any OLD module: right-click Module1 in the left pane > Remove Module1 > No.
A12: Skipping this causes 'Ambiguous name detected'.
A13: STEP 4 - Insert > Module. Then on this sheet click A29, press CTRL + SHIFT + END,
A14: CTRL + C, click into the blank module window and CTRL + V.
A17: STEP 5 - Debug > Compile VBAProject. Silence means it is clean.
A19: STEP 6 - Press ALT + F8, select SetupNames, click Run. You should see 'Form map rebuilt'.
... A346: End Sub
